Workbook

Sheet PROP DAILY PNL
A1: Date | B1: PNL | C1: Percentage Return | D1: MR PNL | E1: Absolute PNL on NAV | F1: NAV VALUE | G1: MAX DD | H1: DD | I1: 0 Dte PNL | J1: NEW NIFTY RANGE BO | K1: NIFTY RSI | L1: NON dte setup | M1: NIFTY DIREC | N1: MIDCAP ORB | O1: MIDCAP RSI | P1: BANKS RSI | Q1: Non direc EMI | R1: VWAP/EMA (WEF 1 DEC) | S1: EMA QTY | T1: pts | U1: cumm pts | V1: ND SYSTEM | W1: Non dte Qty | X1: Pts | Y1: Cumm pts | Z1: Direct Day wise profit/loss | AA1: Cumm Direct PNL | AB1: QTY NON Directional | AC1: NON direc pts | AD1: Cumm Non dte pts | AE1: Nifty Direc Qty | AF1: Pts | AG1: Cumm Pts | AH1: ND system QTY | AI1: Pts | AJ1: Cumm Pts | AK1: NIFTY ORB QTy | AL1: Pts | AM1: Cumm Pts | AN1: NIFTY Pts | AO1: NIFTY RSI cumm pts | AP1: MIDCP ORB QTY | AQ1: Pts | AR1: Cumm Pts | AS1: MIDCAP RSI QTY | AT1: MIDCAP RSI PTS | AU1: MIDCAP CUm pts | AV1: BANKS RSI QTY | AW1: BANKS Pts RSI | AX1: BANKS Cumm pts | AY1: MR qty | AZ1: MR | BA1: MR CUMM pts | BE1: Learnings
A2: 45446 | B2: 82622.25 | C2: =B2/'Clients Balance'!B2 -> 0.027032106 | E2: =C2*100 -> 2.7032106 | F2: =100*(1+C2) -> 102.70321 | G2: =MAX($F$2:F2) -> 102.70321 | H2: =(F2-G2)/F2 -> 0
A3: 45447 | B3: 155760 | C3: =B3/'Clients Balance'!B3 -> 0.049619774 | E3: =C3*F2 -> 5.0961101 | F3: =F2*(1+C3) -> 107.79932 | G3: =MAX($F$2:F3) -> 107.79932 | H3: =(F3-G3)/F3 -> 0
A4: 45448 | B4: -13672.5 | C4: =B4/'Clients Balance'!B4 -> -0.0041496816 | E4: =C4*F3 -> -0.44733286 | F4: =F3*(1+C4) -> 107.35199 | G4: =MAX($F$2:F4) -> 107.79932 | H4: =(F4-G4)/F4 -> -0.0041669732
A5: 45449 | B5: =11487-5580 -> 5907 | C5: =B5/'Clients Balance'!B5 -> 0.0018002787 | E5: =C5*F4 -> 0.1932635 | F5: =F4*(1+C5) -> 107.54525 | G5: =MAX($F$2:F5) -> 107.79932 | H5: =(F5-G5)/F5 -> -0.0023624414
A6: 45450 | B6: 32298 | C6: =B6/'Clients Balance'!B6 -> 0.009825785 | E6: =C6*F5 -> 1.0567165 | F6: =F5*(1+C6) -> 108.60197 | G6: =MAX($F$2:F6) -> 108.60197 | H6: =(F6-G6)/F6 -> 0
A7: 45453 | B7: 32068.5 | C7: =B7/'Clients Balance'!B7 -> 0.0096610386 | E7: =C7*F6 -> 1.0492078 | F7: =F6*(1+C7) -> 109.65118 | G7: =MAX($F$2:F7) -> 109.65118 | H7: =(F7-G7)/F7 -> 0
A8: 45454 | B8: 537 | C8: =B8/'Clients Balance'!B8 -> 0.00016023001 | E8: =C8*F7 -> 0.017569409 | F8: =F7*(1+C8) -> 109.66875 | G8: =MAX($F$2:F8) -> 109.66875 | H8: =(F8-G8)/F8 -> 0
A9: 45455 | B9: -8304 | C9: =B9/'Clients Balance'!B9 -> -0.0024773498 | E9: =C9*F8 -> -0.27168784 | F9: =F8*(1+C9) -> 109.39706 | G9: =MAX($F$2:F9) -> 109.66875 | H9: =(F9-G9)/F9 -> -0.0024835023
A10: 45456 | B10: 9743.25 | C10: =B10/'Clients Balance'!B10 -> 0.0029139431 | E10: =C10*F9 -> 0.3187768 | F10: =F9*(1+C10) -> 109.71583 | G10: =MAX($F$2:F10) -> 109.71583 | H10: =(F10-G10)/F10 -> 0
A11: 45457 | B11: 485.5 | C11: =B11/'Clients Balance'!B11 -> 0.00014477807 | E11: =C11*F10 -> 0.015884447 | F11: =F10*(1+C11) -> 109.73172 | G11: =MAX($F$2:F11) -> 109.73172 | H11: =(F11-G11)/F11 -> 0
A12: 45461 | B12: 6382.25 | C12: =B12/'Clients Balance'!B12 -> 0.0019029374 | E12: =C12*F11 -> 0.20881259 | F12: =F11*(1+C12) -> 109.94053 | G12: =MAX($F$2:F12) -> 109.94053 | H12: =(F12-G12)/F12 -> 0
A13: 45462 | B13: -57802.75 | C13: =B13/'Clients Balance'!B13 -> -0.017201786 | E13: =C13*F12 -> -1.8911735 | F13: =F12*(1+C13) -> 108.04936 | G13: =MAX($F$2:F13) -> 109.94053 | H13: =(F13-G13)/F13 -> -0.017502866
A14: 45463 | B14: 4544 | C14: =B14/'Clients Balance'!B14 -> 0.0013759384 | E14: =C14*F13 -> 0.14866926 | F14: =F13*(1+C14) -> 108.19803 | G14: =MAX($F$2:F14) -> 109.94053 | H14: =(F14-G14)/F14 -> -0.016104769
A15: 45464 | B15: -64673.25 | C15: =B15/'Clients Balance'!B15 -> -0.019556368 | E15: =C15*F14 -> -2.1159605 | F15: =F14*(1+C15) -> 106.08207 | G15: =MAX($F$2:F15) -> 109.94053 | H15: =(F15-G15)/F15 -> -0.03637245
A16: 45467 | B16: 30066 | C16: =B16/'Clients Balance'!B16 -> 0.0092729207 | E16: =C16*F15 -> 0.98369059 | F16: =F15*(1+C16) -> 107.06576 | G16: =MAX($F$2:F16) -> 109.94053 | H16: =(F16-G16)/F16 -> -0.026850546 | I16: =B16-K16 -> 30066
A17: 45468 | B17: 60457 | C17: =B17/'Clients Balance'!B17 -> 0.018474763 | E17: =C17*F16 -> 1.9780144 | F17: =F16*(1+C17) -> 109.04377 | G17: =MAX($F$2:F17) -> 109.94053 | H17: =(F17-G17)/F17 -> -0.0082238502 | I17: =B17-K17 -> 60457
A18: 45469 | B18: 46637.5 | C18: =B18/'Clients Balance'!B18 -> 0.013993207 | E18: =C18*F17 -> 1.5258721 | F18: =F17*(1+C18) -> 110.56964 | G18: =MAX($F$2:F18) -> 110.56964 | H18: =(F18-G18)/F18 -> 0 | I18: =B18-K18 -> 40845 | K18: 5792.5 | AK18: 850 | AN18: =K18/AK18 -> 6.8147059 | AO18: =AN18 -> 6.8147059
A19: 45470 | B19: -142558.75 | C19: =B19/'Clients Balance'!B19 -> -0.042183327 | E19: =C19*F18 -> -4.6641955 | F19: =F18*(1+C19) -> 105.90545 | G19: =MAX($F$2:F19) -> 110.56964 | H19: =(F19-G19)/F19 -> -0.044041129 | I19: =B19-K19 -> -46912.5 | K19: =-23841.25-17723.75-47910-26702.5+20531.25 -> -95646.25 | AK19: 850 | AN19: =K19/AK19 -> -112.525 | AO19: =AO18+AN19 -> -105.71029
A20: 45471 | B20: -57876.25 | C20: =B20/'Clients Balance'!B20 -> -0.017879894 | E20: =C20*F19 -> -1.8935782 | F20: =F19*(1+C20) -> 104.01187 | G20: =MAX($F$2:F20) -> 110.56964 | H20: =(F20-G20)/F20 -> -0.06304832 | I20: =B20-K20 -> -17122.5 | K20: =-41796.25-12518.75+13561.25 -> -40753.75 | AK20: 850 | AN20: =K20/AK20 -> -47.945588 | AO20: =AO19+AN20 -> -153.65588
A21: 45474 | B21: -11219 | C21: =B21/'Clients Balance'!B21 -> -0.0035290199 | E21: =C21*F20 -> -0.36705996 | F21: =F20*(1+C21) -> 103.64481 | G21: =MAX($F$2:F21) -> 110.56964 | H21: =(F21-G21)/F21 -> -0.066813125 | I21: =B21-K21 -> -3569 | K21: -7650 | AK21: 850 | AN21: =K21/AK21 -> -9 | AO21: =AO20+AN21 -> -162.65588
A22: 45475 | B22: -24815.5 | C22: =B22/'Clients Balance'!B22 -> -0.0080709209 | E22: =C22*F21 -> -0.83650906 | F22: =F21*(1+C22) -> 102.8083 | G22: =MAX($F$2:F22) -> 110.56964 | H22: =(F22-G22)/F22 -> -0.075493347 | I22: =B22-K22 -> -5048 | K22: -19767.5 | AK22: 850 | AN22: =K22/AK22 -> -23.255882 | AO22: =AO21+AN22 -> -185.91176
A23: 45476 | B23: 112503.75 | C23: =B23/'Clients Balance'!B23 -> 0.036717719 | E23: =C23*F22 -> 3.7748863 | F23: =F22*(1+C23) -> 106.58319 | G23: =MAX($F$2:F23) -> 110.56964 | H23: =(F23-G23)/F23 -> -0.0374023 | I23: =B23-K23 -> 113913.75 | K23: =4256.25-5666.25 -> -1410 | AK23: 850 | AN23: =K23/AK23 -> -1.6588235 | AO23: =AO22+AN23 -> -187.57059
A24: 45477 | B24: 39878.75 | C24: =B24/'Clients Balance'!B24 -> 0.013120885 | E24: =C24*F23 -> 1.3984657 | F24: =F23*(1+C24) -> 107.98165 | G24: =MAX($F$2:F24) -> 110.56964 | H24: =(F24-G24)/F24 -> -0.023966948 | I24: =B24-K24 -> 77998.75 | K24: =-720-37400 -> -38120 | AK24: 850 | AN24: =K24/AK24 -> -44.847059 | AO24: =AO23+AN24 -> -232.41765
A25: 45478 | B25: -25744.5 | C25: =B25/'Clients Balance'!B25 -> -0.0081680919 | E25: =C25*F24 -> -0.88200407 | F25: =F24*(1+C25) -> 107.09965 | G25: =MAX($F$2:F25) -> 110.56964 | H25: =(F25-G25)/F25 -> -0.032399684 | I25: =B25-K25 -> -582.5 | K25: -25162 | AK25: 975 | AN25: -40 | AO25: =AO24+AN25 -> -272.41765
A26: 45481 | B26: -44632.5 | C26: =B26/'Clients Balance'!B26 -> -0.013983855 | E26: =C26*F25 -> -1.497666 | F26: =F25*(1+C26) -> 105.60198 | G26: =MAX($F$2:F26) -> 110.56964 | H26: =(F26-G26)/F26 -> -0.047041358 | I26: =B26-K26 -> -44632.5 | K26: 0 | AK26: 975 | AN26: =K26/AK26 -> 0 | AO26: =AO25+AN26 -> -272.41765
A27: 45482 | B27: -12644.75 | C27: =B27/'Clients Balance'!B27 -> -0.0039939552 | E27: =C27*F26 -> -0.42176959 | F27: =F26*(1+C27) -> 105.18021 | G27: =MAX($F$2:F27) -> 110.56964 | H27: =(F27-G27)/F27 -> -0.051239964 | I27: =B27-K27 -> -28728.75 | K27: =-708+16792 -> 16084 | AK27: 975 | AN27: =K27/AK27 -> 16.49641 | AO27: =AO26+AN27 -> -255.92124
A28: 45483 | B28: 61934.25 | C28: =B28/'Clients Balance'!B28 -> 0.019842203 | E28: =C28*F27 -> 2.0870071 | F28: =F27*(1+C28) -> 107.26722 | G28: =MAX($F$2:F28) -> 110.56964 | H28: =(F28-G28)/F28 -> -0.030786881 | I28: =B28-K28 -> 61056.25 | K28: =-755+1633 -> 878 | AK28: 975 | AN28: =K28/AK28 -> 0.90051282 | AO28: =AO27+AN28 -> -255.02072
A29: 45484 | B29: 21988.75 | C29: =B29/'Clients Balance'!B29 -> 0.0070733064 | E29: =C29*F28 -> 0.75873391 | F29: =F28*(1+C29) -> 108.02595 | G29: =MAX($F$2:F29) -> 110.56964 | H29: =(F29-G29)/F29 -> -0.02354702 | I29: =B29-K29 -> 21988.75 | K29: 0 | AK29: 975 | AN29: =K29/AK29 -> 0 | AO29: =AO28+AN29 -> -255.02072
A30: 45485 | B30: 12094 | C30: =B30/'Clients Balance'!B30 -> 0.0038143852 | E30: =C30*F29 -> 0.4120526 | F30: =F29*(1+C30) -> 108.43801 | G30: =MAX($F$2:F30) -> 110.56964 | H30: =(F30-G30)/F30 -> -0.019657653 | I30: =B30-K30 -> -8754 | K30: 20848 | AK30: 975 | AN30: =K30/AK30 -> 21.382564 | AO30: =AO29+AN30 -> -233.63816
A31: 45488 | B31: 2925 | C31: =B31/'Clients Balance'!B31 -> 0.00091617609 | E31: =C31*F30 -> 0.099348309 | F31: =F30*(1+C31) -> 108.53736 | G31: =MAX($F$2:F31) -> 110.56964 | H31: =(F31-G31)/F31 -> -0.018724322 | I31: =B31-K31 -> 16360 | K31: =-1045-12390 -> -13435 | AK31: 975 | AN31: =K31/AK31 -> -13.779487 | AO31: =AO30+AN31 -> -247.41765
A32: 45489 | B32: 107071.25 | C32: =B32/'Clients Balance'!B32 -> 0.033410572 | E32: =C32*F31 -> 3.6262951 | F32: =F31*(1+C32) -> 112.16365 | G32: =MAX($F$2:F32) -> 112.16365 | H32: =(F32-G32)/F32 -> 0 | I32: =B32-K32 -> 148544.25 | K32: =-26263-15210 -> -41473 | AK32: 975 | AN32: =K32/AK32 -> -42.53641 | AO32: =AO31+AN32 -> -289.95406
A33: 45491 | B33: -40965 | C33: =B33/'Clients Balance'!B33 -> -0.012771085 | E33: =C33*F32 -> -1.4324515 | F33: =F32*(1+C33) -> 110.7312 | G33: =MAX($F$2:F33) -> 112.16365 | H33: =(F33-G33)/F33 -> -0.012936295 | I33: =B33-K33 -> -14997 | K33: =-64701+38733 -> -25968 | AK33: 975 | AN33: =K33/AK33 -> -26.633846 | AO33: =AO32+AN33 -> -316.5879
A34: 45492 | B34: 90556.75 | C34: =B34/'Clients Balance'!B34 -> 0.027319677 | E34: =C34*F33 -> 3.0251406 | F34: =F33*(1+C34) -> 113.75634 | G34: =MAX($F$2:F34) -> 113.75634 | H34: =(F34-G34)/F34 -> 0 | I34: =B34-K34 -> 72763.75 | K34: =17793 -> 17793 | AK34: 975 | AN34: =K34/AK34 -> 18.249231 | AO34: =AO33+AN34 -> -298.33867
A35: 45495 | B35: -72237 | C35: =B35/'Clients Balance'!B35 -> -0.022065569 | E35: =C35*F34 -> -2.5100983 | F35: =F34*(1+C35) -> 111.24624 | G35: =MAX($F$2:F35) -> 113.75634 | H35: =(F35-G35)/F35 -> -0.022563444 | I35: =B35-K35 -> -39654 | K35: =-18888-13695 -> -32583 | AK35: 975 | AN35: =K35/AK35 -> -33.418462 | AO35: =AO34+AN35 -> -331.75713
A36: 45496 | B36: -116609.75 | C36: =B36/'Clients Balance'!B36 -> -0.034660928 | E36: =C36*F35 -> -3.855898 | F36: =F35*(1+C36) -> 107.39034 | G36: =MAX($F$2:F36) -> 113.75634 | H36: =(F36-G36)/F36 -> -0.059279039 | I36: =B36-K36 -> -71046.75 | K36: =-8318-25142-12103 -> -45563 | AK36: 600 | AN36: =K36/AK36 -> -75.938333 | AO36: =AO35+AN36 -> -407.69547
A37: 45497 | B37: -114589.75 | C37: =B37/'Clients Balance'!B37 -> -0.034807888 | E37: =C37*F36 -> -3.7380311 | F37: =F36*(1+C37) -> 103.65231 | G37: =MAX($F$2:F37) -> 113.75634 | H37: =(F37-G37)/F37 -> -0.09748 | I37: =B37-K37 -> -114589.75 | K37: 0 | AK37: 975 | AN37: =K37/AK37 -> 0 | AO37: =AO36+AN37 -> -407.69547
A38: 45498 | B38: 62031.25 | C38: =B38/'Clients Balance'!B38 -> 0.019534615 | E38: =C38*F37 -> 2.024808 | F38: =F37*(1+C38) -> 105.67712 | G38: =MAX($F$2:F38) -> 113.75634 | H38: =(F38-G38)/F38 -> -0.076451926 | I38: =B38-K38 -> 64281.25 | K38: -2250 | AK38: 975 | AN38: =K38/AK38 -> -2.3076923 | AO38: =AO37+AN38 -> -410.00316
A39: 45499 | B39: 241007.25 | C39: =B39/'Clients Balance'!B39 -> 0.078738328 | E39: =C39*F38 -> 8.3208397 | F39: =F38*(1+C39) -> 113.99796 | G39: =MAX($F$2:F39) -> 113.99796 | H39: =(F39-G39)/F39 -> 0 | I39: =B39-K39 -> 46107.25 | K39: =137013+57887 -> 194900 | AK39: 800 | AN39: =K39/AK39 -> 243.625 | AO39: =AO38+AN39 -> -166.37816
A40: 45502 | B40: -85260 | C40: =B40/'Clients Balance'!B40 -> -0.027301595 | E40: =C40*F39 -> -3.1123262 | F40: =F39*(1+C40) -> 110.88563 | G40: =MAX($F$2:F40) -> 113.99796 | H40: =(F40-G40)/F40 -> -0.028067894 | I40: =B40-K40 -> -101851 | K40: 16591 | AK40: 500 | AN40: =K40/AK40 -> 33.182 | AO40: =AO39+AN40 -> -133.19616
A41: 45503 | B41: -111340 | C41: =B41/'Clients Balance'!B41 -> -0.03309847 | E41: =C41*F40 -> -3.6701448 | F41: =F40*(1+C41) -> 107.21549 | G41: =MAX($F$2:F41) -> 113.99796 | H41: =(F41-G41)/F41 -> -0.063260179 | I41: =B41-K41 -> -111340 | K41: 0 | AK41: 500 | AN41: =K41/AK41 -> 0 | AO41: =AO40+AN41 -> -133.19616
A42: 45504 | B42: -52723.5 | C42: =B42/'Clients Balance'!B42 -> -0.016080897 | E42: =C42*F41 -> -1.7241213 | F42: =F41*(1+C42) -> 105.49137 | G42: =MAX($F$2:F42) -> 113.99796 | H42: =(F42-G42)/F42 -> -0.080637804 | I42: =B42-K42 -> -43570.5 | K42: =-5562-3591 -> -9153 | AK42: 500 | AN42: =K42/AK42 -> -18.306 | AO42: =AO41+AN42 -> -151.50216
A43: 45505 | B43: 100578 | C43: =B43/'Clients Balance'!B43 -> 0.031755106 | E43: =C43*F42 -> 3.3498895 | F43: =F42*(1+C43) -> 108.84126 | G43: =MAX($F$2:F43) -> 113.99796 | H43: =(F43-G43)/F43 -> -0.047378199 | I43: =B43-K43-D43 -> 130843 | K43: =-6637+2748-10885-2475-13016 -> -30265 | AK43: 500 | AN43: =K43/AK43 -> -60.53 | AO43: =AO42+AN43 -> -212.03216
A44: 45506 | B44: 133516.25 | C44: =B44/'Clients Balance'!B44 -> 0.042868164 | D44: =-2681-2473 -> -5154 | E44: =C44*F43 -> 4.6658249 | F44: =F43*(1+C44) -> 113.50708 | G44: =MAX($F$2:F44) -> 113.99796 | H44: =(F44-G44)/F44 -> -0.0043246449 | I44: =B44-K44-D44 -> 141316.25 | K44: =-490-1706-450 -> -2646 | AK44: 500 | AN44: =K44/AK44 -> -5.292 | AO44: =AO43+AN44 -> -217.32416 | AY44: 200 | AZ44: =D44/AY44 -> -25.77 | BA44: =AZ44 -> -25.77 | BB44: =BA44+AO44 -> -243.09416
A45: 45509 | B45: -31221 | C45: =B45/'Clients Balance'!B45 -> -0.010428588 | D45: -12200 | E45: =C45*F44 -> -1.1837186 | F45: =F44*(1+C45) -> 112.32336 | G45: =MAX($F$2:F45) -> 113.99796 | H45: =(F45-G45)/F45 -> -0.014908709 | I45: =B45-K45-D45 -> -65145 | K45: =53340-7216 -> 46124 | AK45: 500 | AN45: =K45/AK45 -> 92.248 | AO45: =AO44+AN45 -> -125.07616 | AY45: 300 | AZ45: =D45/AY45 -> -40.666667 | BA45: =AZ45+BA44 -> -66.436667 | BB45: =BA45+AO45 -> -191.51283
A46: 45510 | B46: 75800 | C46: =B46/'Clients Balance'!B46 -> 0.024496118 | D46: 24408 | E46: =C46*F45 -> 2.7514863 | F46: =F45*(1+C46) -> 115.07485 | G46: =MAX($F$2:F46) -> 115.07485 | H46: =(F46-G46)/F46 -> 0 | I46: =B46-K46-D46 -> 29802 | K46: 21590 | AK46: 500 | AN46: =K46/AK46 -> 43.18 | AO46: =AO45+AN46 -> -81.89616 | AY46: 300 | AZ46: =D46/AY46 -> 81.36 | BA46: =AZ46+BA45 -> 14.923333 | BB46: =BA46+AO46 -> -66.972827
A47: 45511 | B47: -6379 | C47: =B47/'Clients Balance'!B47 -> -0.0019762172 | D47: 0 | E47: =C47*F46 -> -0.22741289 | F47: =F46*(1+C47) -> 114.84744 | G47: =MAX($F$2:F47) -> 115.07485 | H47: =(F47-G47)/F47 -> -0.0019801303 | I47: =B47-K47-D47 -> 11864 | K47: -18243 | AK47: 450 | AN47: =K47/AK47 -> -40.54 | AO47: =AO46+AN47 -> -122.43616 | AY47: 300 | AZ47: =D47/AY47 -> 0 | BA47: =AZ47+BA46 -> 14.923333 | BB47: =BA47+AO47 -> -107.51283
A48: 45512 | B48: 16131 | C48: =B48/'Clients Balance'!B48 -> 0.0050461996 | D48: 28650 | E48: =C48*F47 -> 0.57954308 | F48: =F47*(1+C48) -> 115.42698 | G48: =MAX($F$2:F48) -> 115.42698 | H48: =(F48-G48)/F48 -> 0 | I48: =B48-K48-D48 -> 15716 | K48: -28235 | AK48: 375 | AN48: =K48/AK48 -> -75.293333 | AO48: =AO47+AN48 -> -197.72949 | AY48: 300 | AZ48: =D48/AY48 -> 95.5 | BA48: =AZ48+BA47 -> 110.42333 | BB48: =BA48+AO48 -> -87.30616
A49: 45513 | B49: 168443 | C49: =B49/'Clients Balance'!B49 -> 0.051472849 | D49: -5373 | E49: =C49*F48 -> 5.9413555 | F49: =F48*(1+C49) -> 121.36834 | G49: =MAX($F$2:F49) -> 121.36834 | H49: =(F49-G49)/F49 -> 0 | I49: =B49-K49-D49 -> 187466 | K49: -13650 | AK49: 500 | AN49: =K49/AK49 -> -27.3 | AO49: =AO48+AN49 -> -225.02949 | AY49: 300 | AZ49: =D49/AY49 -> -17.91 | BA49: =AZ49+BA48 -> 92.513333 | BB49: =BA49+AO49 -> -132.51616
A50: 45516 | B50: 43822 | C50: =B50/'Clients Balance'!B50 -> 0.013417291 | D50: 33222 | E50: =C50*F49 -> 1.6284342 | F50: =F49*(1+C50) -> 122.99677 | G50: =MAX($F$2:F50) -> 122.99677 | H50: =(F50-G50)/F50 -> 0 | I50: =B50-K50-D50 -> 30368 | K50: -19768 | AK50: 500 | AN50: =K50/AK50 -> -39.536 | AO50: =AO49+AN50 -> -264.56549 | AY50: 375 | AZ50: =D50/AY50 -> 88.592 | BA50: =AZ50+BA49 -> 181.10533 | BB50: =BA50+AO50 -> -83.46016
A51: 45517 | B51: 203 | C51: =B51/'Clients Balance'!B51 -> 6.1848475e-05 | D51: -12833 | E51: =C51*F50 -> 0.0076071627 | F51: =F50*(1+C51) -> 123.00438 | G51: =MAX($F$2:F51) -> 123.00438 | H51: =(F51-G51)/F51 -> 0 | I51: =B51-K51-D51 -> 5056 | K51: 7980 | AK51: 400 | AN51: =K51/AK51 -> 19.95 | AO51: =AO50+AN51 -> -244.61549 | AY51: 450 | AZ51: =D51/AY51 -> -28.517778 | BA51: =AZ51+BA50 -> 152.58756 | BB51: =BA51+AO51 -> -92.027938
A52: 45518 | B52: 38464 | C52: =B52/'Clients Balance'!B52 -> 0.011146859 | D52: -15440 | E52: =C52*F51 -> 1.3711125 | F52: =F51*(1+C52) -> 124.37549 | G52: =MAX($F$2:F52) -> 124.37549 | H52: =(F52-G52)/F52 -> 0 | I52: =B52-K52-D52 -> 77455 | K52: -23551 | AK52: 500 | AN52: =K52/AK52 -> -47.102 | AO52: =AO51+AN52 -> -291.71749 | AY52: 400 | AZ52: =D52/AY52 -> -38.6 | BA52: =AZ52+BA51 -> 113.98756 | BB52: =BA52+AO52 -> -177.72994
A53: 45520 | B53: -5838 | C53: =B53/'Clients Balance'!B53 -> -0.0016706348 | D53: -1627 | E53: =C53*F52 -> -0.20778602 | F53: =F52*(1+C53) -> 124.1677 | G53: =MAX($F$2:F53) -> 124.37549 | H53: =(F53-G53)/F53 -> -0.0016734305 | I53: =B53-K53-D53 -> 3150 | K53: -7361 | AK53: 500 | AN53: =K53/AK53 -> -14.722 | AO53: =AO52+AN53 -> -306.43949 | AY53: 450 | AZ53: =D53/AY53 -> -3.6155556 | BA53: =AZ53+BA52 -> 110.372 | BB53: =BA53+AO53 -> -196.06749
A54: 45523 | B54: -15076 | C54: =B54/'Clients Balance'!B54 -> -0.004313982 | D54: -3597 | E54: =C54*F53 -> -0.53565723 | F54: =F53*(1+C54) -> 123.63205 | G54: =MAX($F$2:F54) -> 124.37549 | H54: =(F54-G54)/F54 -> -0.006013354 | I54: =B54-K54-D54 -> 6401 | K54: -17880 | AK54: 500 | AN54: =K54/AK54 -> -35.76 | AO54: =AO53+AN54 -> -342.19949 | AY54: 450 | AZ54: =D54/AY54 -> -7.9933333 | BA54: =AZ54+BA53 -> 102.37867 | BB54: =BA54+AO54 -> -239.82083
A55: 45524 | B55: 42558 | C55: =B55/'Clients Balance'!B55 -> 0.012045352 | D55: -14206 | E55: =C55*F54 -> 1.4891915 | F55: =F54*(1+C55) -> 125.12124 | G55: =MAX($F$2:F55) -> 125.12124 | H55: =(F55-G55)/F55 -> 0 | I55: =B55-K55-D55 -> 58939 | K55: -2175 | AK55: 500 | AN55: =K55/AK55 -> -4.35 | AO55: =AO54+AN55 -> -346.54949 | AY55: 500 | AZ55: =D55/AY55 -> -28.412 | BA55: =AZ55+BA54 -> 73.966667 | BB55: =BA55+AO55 -> -272.58283
A56: 45525 | B56: -38280 | C56: =B56/'Clients Balance'!B56 -> -0.010852465 | D56: -10343 | E56: =C56*F55 -> -1.3578739 | F56: =F55*(1+C56) -> 123.76336 | G56: =MAX($F$2:F56) -> 125.12124 | H56: =(F56-G56)/F56 -> -0.010971534 | I56: =B56-K56-D56 -> -22437 | K56: -5500 | AK56: 500 | AN56: =K56/AK56 -> -11 | AO56: =AO55+AN56 -> -357.54949 | AY56: 500 | AZ56: =D56/AY56 -> -20.686 | BA56: =AZ56+BA55 -> 53.280667 | BB56: =BA56+AO56 -> -304.26883
A57: 45526 | B57: 72650 | C57: =B57/'Clients Balance'!B57 -> 0.020684846 | D57: -21706 | E57: =C57*F56 -> 2.5600261 | F57: =F56*(1+C57) -> 126.32339 | G57: =MAX($F$2:F57) -> 126.32339 | H57: =(F57-G57)/F57 -> 0 | I57: =B57-K57-D57 -> 98263 | K57: -3907 | AK57: 500 | AN57: =K57/AK57 -> -7.814 | AO57: =AO56+AN57 -> -365.36349 | AY57: 500 | AZ57: =D57/AY57 -> -43.412 | BA57: =AZ57+BA56 -> 9.8686667 | BB57: =BA57+AO57 -> -355.49483
... A60: 45531 | B60: -36528 | C60: =B60/'Clients Balance'!B60 -> -0.010177309 | D60: 4131 | E60: =C60*F59 -> -1.3221354 | F60: =F59*(1+C60) -> 128.58798 | G60: =MAX($F$2:F60) -> 129.91012 | H60: =(F60-G60)/F60 -> -0.010281951 | I60: =B60-K60-D60 -> -27384 | K60: -13275 | AK60: 500 | AN60: =K60/AK60 -> -26.55 | AO60: =AO59+AN60 -> -368.76349 | AY60: 500 | AZ60: =D60/AY60 -> 8.262 | BA60: =AZ60+BA59 -> 15.230667 | BB60: =BA60+AO60 -> -353.53283
A61: 45532 | B61: 102213 | C61: =B61/'Clients Balance'!B61 -> 0.028221033 | D61: 50000 | E61: =C61*F60 -> 3.6288857 | F61: =F60*(1+C61) -> 132.21687 | G61: =MAX($F$2:F61) -> 132.21687 | H61: =(F61-G61)/F61 -> 0 | I61: s | K61: -26400 | AK61: 500 | AN61: =K61/AK61 -> -52.8 | AO61: =AO60+AN61 -> -421.56349 | AY61: 500 | AZ61: =D61/AY61 -> 100 | BA61: =AZ61+BA60 -> 115.23067 | BB61: =BA61+AO61 -> -306.33283
A62: 45533 | B62: -85183 | C62: =B62/'Clients Balance'!B62 -> -0.02309269 | D62: 43886 | E62: =C62*F61 -> -3.0532431 | F62: =F61*(1+C62) -> 129.16363 | G62: =MAX($F$2:F62) -> 132.21687 | H62: =(F62-G62)/F62 -> -0.023638568 | I62: =B62-K62-D62 -> -122694 | K62: -6375 | AK62: 500 | AN62: =K62/AK62 -> -12.75 | AO62: =AO61+AN62 -> -434.31349 | AY62: 500 | AZ62: =D62/AY62 -> 87.772 | BA62: =AZ62+BA61 -> 203.00267 | BB62: =BA62+AO62 -> -231.31083
A63: 45534 | B63: 32478.5 | C63: =B63/'Clients Balance'!B63 -> 0.0088928223 | D63: -20906.25 | E63: =C63*F62 -> 1.1486292 | F63: =F62*(1+C63) -> 130.31225 | G63: =MAX($F$2:F63) -> 132.21687 | H63: =(F63-G63)/F63 -> -0.01461577 | I63: =B63-K63-D63 -> 53384.75 | K63: 0 | AK63: 500 | AN63: =K63/AK63 -> 0 | AO63: =AO62+AN63 -> -434.31349 | AY63: 500 | AZ63: =D63/AY63 -> -41.8125 | BA63: =AZ63+BA62 -> 161.19017 | BB63: =BA63+AO63 -> -273.12333
A64: 45537 | B64: -37710.25 | C64: =B64/'Clients Balance'!B64 -> -0.010044206 | D64: 16406 | E64: =C64*F63 -> -1.3088831 | F64: =F63*(1+C64) -> 129.00337 | G64: =MAX($F$2:F64) -> 132.21687 | H64: =(F64-G64)/F64 -> -0.024910179 | I64: =B64-K64-D64 -> -42044.25 | K64: -12072 | AK64: 550 | AN64: =K64/AK64 -> -21.949091 | AO64: =AO63+AN64 -> -456.26258 | AY64: 700 | AZ64: =D64/AY64 -> 23.437143 | BA64: =AZ64+BA63 -> 184.62731 | BB64: =BA64+AO64 -> -271.63527
A65: 45538 | B65: -134005 | C65: =B65/'Clients Balance'!B65 -> -0.036521136 | D65: 0 | E65: =C65*F64 -> -4.7113497 | F65: =F64*(1+C65) -> 124.29202 | G65: =MAX($F$2:F65) -> 132.21687 | H65: =(F65-G65)/F65 -> -0.063759899 | I65: =B65-K65-D65 -> -134005 | K65: 0 | AK65: 550 | AN65: =K65/AK65 -> 0 | AO65: =AO64+AN65 -> -456.26258 | AY65: 700 | AZ65: =D65/AY65 -> 0 | BA65: =AZ65+BA64 -> 184.62731 | BB65: =BA65+AO65 -> -271.63527
A66: 45539 | B66: 149400 | C66: =B66/'Clients Balance'!B66 -> 0.040359577 | D66: 15015 | E66: =C66*F65 -> 5.0163734 | F66: =F65*(1+C66) -> 129.3084 | G66: =MAX($F$2:F66) -> 132.21687 | H66: =(F66-G66)/F66 -> -0.022492533 | I66: =B66-K66-D66 -> 143322 | K66: -8937 | AK66: 550 | AN66: =K66/AK66 -> -16.249091 | AO66: =AO65+AN66 -> -472.51168 | AY66: 700 | AZ66: =D66/AY66 -> 21.45 | BA66: =AZ66+BA65 -> 206.07731 | BB66: =BA66+AO66 -> -266.43437
A67: 45540 | B67: 225402 | C67: =B67/'Clients Balance'!B67 -> 0.054168711 | D67: -7621 | E67: =C67*F66 -> 7.0044691 | F67: =F66*(1+C67) -> 136.31286 | G67: =MAX($F$2:F67) -> 136.31286 | H67: =(F67-G67)/F67 -> 0 | I67: =B67-K67-D67 -> 248065 | K67: -15042 | AK67: 550 | AN67: =K67/AK67 -> -27.349091 | AO67: =AO66+AN67 -> -499.86077 | AY67: 700 | AZ67: =D67/AY67 -> -10.887143 | BA67: =AZ67+BA66 -> 195.19017 | BB67: =BA67+AO67 -> -304.6706
A68: 45541 | B68: 18404 | C68: =B68/'Clients Balance'!B68 -> 0.0044633066 | D68: -37222 | E68: =C68*F67 -> 0.6084061 | F68: =F67*(1+C68) -> 136.92127 | G68: =MAX($F$2:F68) -> 136.92127 | H68: =(F68-G68)/F68 -> 0 | I68: 36754 | K68: 66880 | AK68: 550 | AN68: =K68/AK68 -> 121.6 | AO68: =AO67+AN68 -> -378.26077 | AY68: 700 | AZ68: =D68/AY68 -> -53.174286 | BA68: =AZ68+BA67 -> 142.01588 | BB68: =BA68+AO68 -> -236.24489
A69: 45544 | B69: 75873 | C69: =B69/'Clients Balance'!B69 -> 0.019018672 | D69: 16123 | E69: =C69*F68 -> 2.6040607 | F69: =F68*(1+C69) -> 139.52533 | G69: =MAX($F$2:F69) -> 139.52533 | H69: =(F69-G69)/F69 -> 0 | I69: 2983 | K69: 0 | AK69: 550 | AN69: =K69/AK69 -> 0 | AO69: =AO68+AN69 -> -378.26077 | AY69: 700 | AZ69: =D69/AY69 -> 23.032857 | BA69: =AZ69+BA68 -> 165.04874 | BB69: =BA69+AO69 -> -213.21203
A70: 45545 | B70: -24887 | C70: =B70/'Clients Balance'!B70 -> -0.0060131023 | D70: 35227 | E70: =C70*F69 -> -0.83898009 | F70: =F69*(1+C70) -> 138.68635 | G70: =MAX($F$2:F70) -> 139.52533 | H70: =(F70-G70)/F70 -> -0.0060494785 | I70: -69880 | K70: 9156 | AK70: 700 | AN70: =K70/AK70 -> 13.08 | AO70: =AO69+AN70 -> -365.18077 | AY70: 700 | AZ70: =D70/AY70 -> 50.324286 | BA70: =AZ70+BA69 -> 215.37302 | BB70: =BA70+AO70 -> -149.80774
A71: 45546 | B71: 74070 | C71: =B71/'Clients Balance'!B71 -> 0.016972193 | D71: 0 | E71: =C71*F70 -> 2.3538115 | F71: =F70*(1+C71) -> 141.04016 | G71: =MAX($F$2:F71) -> 141.04016 | H71: =(F71-G71)/F71 -> 0 | I71: =B71-K71 -> 64898 | K71: 9172 | AK71: 700 | AN71: =K71/AK71 -> 13.102857 | AO71: =AO70+AN71 -> -352.07791 | AY71: 700 | AZ71: =D71/AY71 -> 0 | BA71: =AZ71+BA70 -> 215.37302 | BB71: =BA71+AO71 -> -136.70488
A72: 45547 | B72: 260346 | C72: =B72/'Clients Balance'!B72 -> 0.059404445 | D72: 0 | E72: =C72*F71 -> 8.3784125 | F72: =F71*(1+C72) -> 149.41858 | G72: =MAX($F$2:F72) -> 149.41858 | H72: =(F72-G72)/F72 -> 0 | I72: -791 | K72: 76825 | AK72: 700 | AN72: =K72/AK72 -> 109.75 | AO72: =AO71+AN72 -> -242.32791 | AY72: 700 | AZ72: =D72/AY72 -> 0 | BA72: =AZ72+BA71 -> 215.37302 | BB72: =BA72+AO72 -> -26.954885
A73: 45548 | B73: -2582 | C73: =B73/'Clients Balance'!B73 -> -0.00057912187 | D73: 0 | E73: =C73*F72 -> -0.086531564 | F73: =F72*(1+C73) -> 149.33204 | G73: =MAX($F$2:F73) -> 149.41858 | H73: =(F73-G73)/F73 -> -0.00057945744 | I73: =B73 -> -2582 | K73: 0 | AK73: 700 | AN73: =K73/AK73 -> 0 | AO73: =AO72+AN73 -> -242.32791 | AY73: 700 | AZ73: =D73/AY73 -> 0 | BA73: =AZ73+BA72 -> 215.37302 | BB73: =BA73+AO73 -> -26.954885
A74: 45551 | B74: 97514.5 | C74: =B74/'Clients Balance'!B74 -> 0.021994492 | D74: 15163.5 | E74: =C74*F73 -> 3.2844824 | F74: =F73*(1+C74) -> 152.61653 | G74: =MAX($F$2:F74) -> 152.61653 | H74: =(F74-G74)/F74 -> 0 | I74: =B74-D74-K74 -> 95234 | K74: -12883 | AK74: 700 | AN74: =K74/AK74 -> -18.404286 | AO74: =AO73+AN74 -> -260.73219 | AY74: 700 | AZ74: =D74/AY74 -> 21.662143 | BA74: =AZ74+BA73 -> 237.03517 | BB74: =BA74+AO74 -> -23.697028
A75: 45552 | B75: 132710 | C75: =B75/'Clients Balance'!B75 -> 0.029441013 | D75: 0 | E75: =C75*F74 -> 4.4931852 | F75: =F74*(1+C75) -> 157.10971 | G75: =MAX($F$2:F75) -> 157.10971 | H75: =(F75-G75)/F75 -> 0 | I75: =B75-D75-K75 -> 132710 | K75: 0 | AK75: 700 | AN75: =K75/AK75 -> 0 | AO75: =AO74+AN75 -> -260.73219 | AY75: 700 | AZ75: =D75/AY75 -> 0 | BA75: =AZ75+BA74 -> 237.03517 | BB75: =BA75+AO75 -> -23.697028
A76: 45553 | B76: 74528 | C76: =B76/'Clients Balance'!B76 -> 0.015630861 | D76: 55938 | E76: =C76*F75 -> 2.4557601 | F76: =F75*(1+C76) -> 159.56547 | G76: =MAX($F$2:F76) -> 159.56547 | H76: =(F76-G76)/F76 -> 0 | I76: =B76-D76-K76 -> 25778 | K76: -7188 | AK76: 700 | AN76: =K76/AK76 -> -10.268571 | AO76: =AO75+AN76 -> -271.00077 | AY76: 700 | AZ76: =D76/AY76 -> 79.911429 | BA76: =AZ76+BA75 -> 316.9466 | BB76: =BA76+AO76 -> 45.945829
A77: 45554 | B77: 67763 | C77: =B77/'Clients Balance'!B77 -> 0.014219729 | D77: 47351 | E77: =C77*F76 -> 2.2689777 | F77: =F76*(1+C77) -> 161.83445 | G77: =MAX($F$2:F77) -> 161.83445 | H77: =(F77-G77)/F77 -> 0 | I77: =B77-D77-K77 -> 43587 | K77: -23175 | AK77: 700 | AN77: =K77/AK77 -> -33.107143 | AO77: =AO76+AN77 -> -304.10791 | AY77: 900 | AZ77: =D77/AY77 -> 52.612222 | BA77: =AZ77+BA76 -> 369.55882 | BB77: =BA77+AO77 -> 65.450909
A78: 45555 | B78: -5417 | C78: =B78/'Clients Balance'!B78 -> -0.0011139361 | D78: 16800 | E78: =C78*F77 -> -0.18027324 | F78: =F77*(1+C78) -> 161.65418 | G78: =MAX($F$2:F78) -> 161.83445 | H78: =(F78-G78)/F78 -> -0.0011151784 | I78: -168847 | K78: 34687 | AK78: 700 | AN78: =K78/AK78 -> 49.552857 | AO78: =AO77+AN78 -> -254.55505 | AY78: 700 | AZ78: =D78/AY78 -> 24 | BA78: =AZ78+BA77 -> 393.55882 | BB78: =BA78+AO78 -> 139.00377
A79: 45558 | B79: 19316.5 | C79: =B79/'Clients Balance'!B79 -> 0.0038666672 | D79: -26783 | E79: =C79*F78 -> 0.6250629 | F79: =F78*(1+C79) -> 162.27924 | G79: =MAX($F$2:F79) -> 162.27924 | H79: =(F79-G79)/F79 -> 0 | I79: =B79-D79-K79 -> 67324.5 | K79: -21225 | AK79: 700 | AN79: =K79/AK79 -> -30.321429 | AO79: =AO78+AN79 -> -284.87648 | AY79: 700 | AZ79: =D79/AY79 -> -38.261429 | BA79: =AZ79+BA78 -> 355.29739 | BB79: =BA79+AO79 -> 70.420909
A80: 45559 | B80: -198612.5 | C80: =B80/'Clients Balance'!B80 -> -0.03917272 | D80: -28822 | E80: =C80*F79 -> -6.3569191 | F80: =F79*(1+C80) -> 155.92232 | G80: =MAX($F$2:F80) -> 162.27924 | H80: =(F80-G80)/F80 -> -0.040769783 | I80: =B80-D80-K80 -> -137878.5 | K80: -31912 | AK80: 700 | AN80: =K80/AK80 -> -45.588571 | AO80: =AO79+AN80 -> -330.46505 | AY80: 700 | AZ80: =D80/AY80 -> -41.174286 | BA80: =AZ80+BA79 -> 314.1231 | BB80: =BA80+AO80 -> -16.341948
A81: 45560 | B81: 252855 | C81: =B81/'Clients Balance'!B81 -> 0.049213333 | D81: 31336 | E81: =C81*F80 -> 7.6734571 | F81: =F80*(1+C81) -> 163.59578 | G81: =MAX($F$2:F81) -> 163.59578 | H81: =(F81-G81)/F81 -> 0 | I81: =B81-D81 -> 221519 | K81: 0 | AK81: 700 | AN81: =K81/AK81 -> 0 | AO81: =AO80+AN81 -> -330.46505 | AY81: 700 | AZ81: =D81/AY81 -> 44.765714 | BA81: =AZ81+BA80 -> 358.88882 | BB81: =BA81+AO81 -> 28.423766
A82: 45561 | B82: 87618 | C82: =B82/'Clients Balance'!B82 -> 0.017071147 | D82: -367 | E82: =C82*F81 -> 2.7927675 | F82: =F81*(1+C82) -> 166.38854 | G82: =MAX($F$2:F82) -> 166.38854 | H82: =(F82-G82)/F82 -> 0 | I82: =B82-D82-K82 -> 49923 | K82: 38062 | AK82: 700 | AN82: =K82/AK82 -> 54.374286 | AO82: =AO81+AN82 -> -276.09077 | AY82: 700 | AZ82: =D82/AY82 -> -0.52428571 | BA82: =AZ82+BA81 -> 358.36453 | BB82: =BA82+AO82 -> 82.273766
A83: 45562 | B83: -9273 | C83: =B83/'Clients Balance'!B83 -> -0.0017999407 | D83: -1382 | E83: =C83*F82 -> -0.29948951 | F83: =F82*(1+C83) -> 166.08905 | G83: =MAX($F$2:F83) -> 166.38854 | H83: =(F83-G83)/F83 -> -0.0018031863 | I83: =B83-D83-K83 -> 8460 | K83: -16351 | AK83: 700 | AN83: =K83/AK83 -> -23.358571 | AO83: =AO82+AN83 -> -299.44934 | AY83: 700 | AZ83: =D83/AY83 -> -1.9742857 | BA83: =AZ83+BA82 -> 356.39025 | BB83: =BA83+AO83 -> 56.940909
A84: 45565 | B84: 111540 | C84: =B84/'Clients Balance'!B84 -> 0.022518667 | D84: -34908 | E84: =C84*F83 -> 3.7401042 | F84: =F83*(1+C84) -> 169.82916 | G84: =MAX($F$2:F84) -> 169.82916 | H84: =(F84-G84)/F84 -> 0 | I84: =B84-D84-K84 -> 24879 | K84: 121569 | AK84: 700 | AN84: =K84/AK84 -> 173.67 | AO84: =AO83+AN84 -> -125.77934 | AY84: 700 | AZ84: =D84/AY84 -> -49.868571 | BA84: =AZ84+BA83 -> 306.52167 | BB84: =BA84+AO84 -> 180.74234
A85: 45566 | B85: 14454 | C85: =B85/'Clients Balance'!B85 -> 0.0027763698 | D85: -33528 | E85: =C85*F84 -> 0.47150854 | F85: =F84*(1+C85) -> 170.30067 | G85: =MAX($F$2:F85) -> 170.30067 | H85: =(F85-G85)/F85 -> 0 | I85: =B85-D85-K85 -> 47982 | K85: 0 | AK85: 1000 | AN85: =K85/AK85 -> 0 | AO85: =AO84+AN85 -> -125.77934 | AY85: 1000 | AZ85: =D85/AY85 -> -33.528 | BA85: =AZ85+BA84 -> 272.99367 | BB85: =BA85+AO85 -> 147.21434 | BC85: 20000000
A86: 45568 | B86: -88497 | C86: =B86/'Clients Balance'!B86 -> -0.016717429 | D86: -78701 | E86: =C86*F85 -> -2.8469893 | F86: =F85*(1+C86) -> 167.45368 | G86: =MAX($F$2:F86) -> 170.30067 | H86: =(F86-G86)/F86 -> -0.017001653 | I86: =B86-D86-K86 -> -66620 | K86: 56824 | AK86: 1000 | AN86: =K86/AK86 -> 56.824 | AO86: =AO85+AN86 -> -68.955337 | AY86: 1000 | AZ86: =D86/AY86 -> -78.701 | BA86: =AZ86+BA85 -> 194.29267 | BB86: =BA86+AO86 -> 125.33734
A87: 45569 | B87: -106267.5 | C87: =B87/'Clients Balance'!B87 -> -0.020109572 | D87: 44862 | E87: =C87*F86 -> -3.3674217 | F87: =F86*(1+C87) -> 164.08626 | G87: =MAX($F$2:F87) -> 170.30067 | H87: =(F87-G87)/F87 -> -0.037872831 | I87: =B87-D87-K87 -> -104248.5 | K87: -46881 | AK87: 1000 | AN87: =K87/AK87 -> -46.881 | AO87: =AO86+AN87 -> -115.83634 | AY87: 1000 | AZ87: =D87/AY87 -> 44.862 | BA87: =AZ87+BA86 -> 239.15467 | BB87: =BA87+AO87 -> 123.31834
A88: 45572 | B88: 22884 | C88: =B88/'Clients Balance'!B88 -> 0.0039827381 | D88: -27926 | E88: =C88*F87 -> 0.65351258 | F88: =F87*(1+C88) -> 164.73977 | G88: =MAX($F$2:F88) -> 170.30067 | H88: =(F88-G88)/F88 -> -0.033755653 | I88: -195828 | K88: -41796 | AK88: 1000 | AN88: =K88/AK88 -> -41.796 | AO88: =AO87+AN88 -> -157.63234 | AY88: 1000 | AZ88: =D88/AY88 -> -27.926 | BA88: =AZ88+BA87 -> 211.22867 | BB88: =BA88+AO88 -> 53.596337
A89: 45573 | B89: 239096 | C89: =B89/'Clients Balance'!B89 -> 0.041507922 | D89: 0 | E89: =C89*F88 -> 6.8380054 | F89: =F88*(1+C89) -> 171.57777 | G89: =MAX($F$2:F89) -> 171.57777 | H89: =(F89-G89)/F89 -> 0 | I89: =B89-D89-K89 -> 239096 | K89: 0 | AK89: 1000 | AN89: =K89/AK89 -> 0 | AO89: =AO88+AN89 -> -157.63234 | AY89: 1000 | AZ89: =D89/AY89 -> 0 | BA89: =AZ89+BA88 -> 211.22867 | BB89: =BA89+AO89 -> 53.596337
A90: 45574 | B90: -73310 | C90: =B90/'Clients Balance'!B90 -> -0.012925457 | D90: -40719 | E90: =C90*F89 -> -2.2177212 | F90: =F89*(1+C90) -> 169.36005 | G90: =MAX($F$2:F90) -> 171.57777 | H90: =(F90-G90)/F90 -> -0.013094713 | I90: =B90-D90-K90 -> 23159 | K90: -55750 | AK90: 1000 | AN90: =K90/AK90 -> -55.75 | AO90: =AO89+AN90 -> -213.38234 | AY90: 1000 | AZ90: =D90/AY90 -> -40.719 | BA90: =AZ90+BA89 -> 170.50967 | BB90: =BA90+AO90 -> -42.872663
A91: 45575 | B91: 294787 | C91: =B91/'Clients Balance'!B91 -> 0.052966989 | D91: 0 | E91: =C91*F90 -> 8.970492 | F91: =F90*(1+C91) -> 178.33054 | G91: =MAX($F$2:F91) -> 178.33054 | H91: =(F91-G91)/F91 -> 0 | I91: =B91-D91-K91 -> 294787 | K91: 0 | AK91: 1000 | AN91: =K91/AK91 -> 0 | AO91: =AO90+AN91 -> -213.38234 | AY91: 1000 | AZ91: =D91/AY91 -> 0 | BA91: =AZ91+BA90 -> 170.50967 | BB91: =BA91+AO91 -> -42.872663
A92: 45576 | B92: 164311 | C92: =B92/'Clients Balance'!B92 -> 0.029402316 | D92: -31443 | E92: =C92*F91 -> 5.243331 | F92: =F91*(1+C92) -> 183.57388 | G92: =MAX($F$2:F92) -> 183.57388 | H92: =(F92-G92)/F92 -> 0 | I92: =B92-D92-K92 -> 246234 | K92: -50480 | AK92: 1000 | AN92: =K92/AK92 -> -50.48 | AO92: =AO91+AN92 -> -263.86234 | AY92: 1000 | AZ92: =D92/AY92 -> -31.443 | BA92: =AZ92+BA91 -> 139.06667 | BB92: =BA92+AO92 -> -124.79566 | BD92: 519807
A93: 45579 | B93: -97599 | C93: =B93/'Clients Balance'!B93 -> -0.016748105 | D93: -44402 | E93: =C93*F92 -> -3.0745145 | F93: =F92*(1+C93) -> 180.49936 | G93: =MAX($F$2:F93) -> 183.57388 | H93: =(F93-G93)/F93 -> -0.017033382 | I93: =B93-D93-K93 -> -72797 | K93: 19600 | AK93: 1000 | AN93: =K93/AK93 -> 19.6 | AO93: =AO92+AN93 -> -244.26234 | AY93: 1000 | AZ93: =D93/AY93 -> -44.402 | BA93: =AZ93+BA92 -> 94.664675 | BB93: =BA93+AO93 -> -149.59766 | BD93: =B94+BD92 -> 174099
A94: 45580 | B94: -345708 | C94: =B94/'Clients Balance'!B94 -> -0.060079713 | D94: 69358 | E94: =C94*F93 -> -10.84435 | F94: =F93*(1+C94) -> 169.65501 | G94: =MAX($F$2:F94) -> 183.57388 | H94: =(F94-G94)/F94 -> -0.082042164 | I94: =B94-D94-K94 -> -373416 | K94: -41650 | AK94: 1000 | AN94: =K94/AK94 -> -41.65 | AO94: =AO93+AN94 -> -285.91234 | AY94: 1000 | AZ94: =D94/AY94 -> 69.358 | BA94: =AZ94+BA93 -> 164.02267 | BB94: =BA94+AO94 -> -121.88966 | BC94: -519807 | BD94: =BC94-B94 -> -174099
A95: 45581 | B95: 236251 | C95: =B95/'Clients Balance'!B95 -> 0.03905658 | D95: 20863 | E95: =C95*F94 -> 6.6261445 | F95: =F94*(1+C95) -> 176.28116 | G95: =MAX($F$2:F95) -> 183.57388 | H95: =(F95-G95)/F95 -> -0.04136982 | I95: =B95-D95-K95 -> 257202 | K95: -41814 | AK95: 1000 | AN95: =K95/AK95 -> -41.814 | AO95: =AO94+AN95 -> -327.72634 | AY95: 1000 | AZ95: =D95/AY95 -> 20.863 | BA95: =AZ95+BA94 -> 184.88567 | BB95: =BA95+AO95 -> -142.84066 | BC95: 264828 | BD95: =BC95-B95 -> 28577
A96: 45582 | B96: 158995 | C96: =B96/'Clients Balance'!B96 -> 0.025589653 | D96: -16467 | E96: =C96*F95 -> 4.5109737 | F96: =F95*(1+C96) -> 180.79213 | G96: =MAX($F$2:F96) -> 183.57388 | H96: =(F96-G96)/F96 -> -0.015386433 | I96: =B96-D96-K96 -> 125238 | K96: 50224 | AK96: 800 | AN96: =K96/AK96 -> 62.78 | AO96: =AO95+AN96 -> -264.94634 | AY96: 800 | AZ96: =D96/AY96 -> -20.58375 | BA96: =AZ96+BA95 -> 164.30192 | BB96: =BA96+AO96 -> -100.64441 | BC96: 167227 | BD96: =BC96-B96 -> 8232
A97: 45583 | B97: -41355 | C97: =B97/'Clients Balance'!B97 -> -0.0067621546 | D97: 68195 | E97: =C97*F96 -> -1.2225443 | F97: =F96*(1+C97) -> 179.56959 | G97: =MAX($F$2:F97) -> 183.57388 | H97: =(F97-G97)/F97 -> -0.02229938 | I97: =B97-D97-K97 -> -82975 | K97: -26575 | AK97: 1000 | AN97: =K97/AK97 -> -26.575 | AO97: =AO96+AN97 -> -291.52134 | AY97: 1000 | AZ97: =D97/AY97 -> 68.195 | BA97: =AZ97+BA96 -> 232.49692 | BB97: =BA97+AO97 -> -59.024413 | BC97: -19005 | BD97: =BC97-B97 -> 22350
A98: 45586 | B98: -61145 | C98: =B98/'Clients Balance'!B98 -> -0.010597152 | D98: 70783 | E98: =C98*F97 -> -1.9029262 | F98: =F97*(1+C98) -> 177.66666 | G98: =MAX($F$2:F98) -> 183.57388 | H98: =(F98-G98)/F98 -> -0.033248875 | I98: =B98-D98-K98 -> -112988 | K98: -18940 | AK98: 1000 | AN98: =K98/AK98 -> -18.94 | AO98: =AO97+AN98 -> -310.46134 | AY98: 1025 | AZ98: =D98/AY98 -> 69.056585 | BA98: =AZ98+BA97 -> 301.55351 | BB98: =BA98+AO98 -> -8.9078274 | BC98: -45093 | BD98: =BC98-B98 -> 16052
A99: 45587 | B99: -178656 | C99: =B99/'Clients Balance'!B99 -> -0.029745276 | D99: -28812 | E99: =C99*F98 -> -5.2847439 | F99: =F98*(1+C99) -> 172.38192 | G99: =MAX($F$2:F99) -> 183.57388 | H99: =(F99-G99)/F99 -> -0.064925375 | I99: =B99-D99-K99 -> -149844 | K99: 0 | AK99: 1000 | AN99: =K99/AK99 -> 0 | AO99: =AO98+AN99 -> -310.46134 | AY99: 1025 | AZ99: =D99/AY99 -> -28.109268 | BA99: =AZ99+BA98 -> 273.44424 | BB99: =BA99+AO99 -> -37.017096
A100: 45588 | B100: -6201 | C100: =B100/'Clients Balance'!B100 -> -0.001005808 | D100: 13790 | E100: =C100*F99 -> -0.17338312 | F100: =F99*(1+C100) -> 172.20853 | G100: =MAX($F$2:F100) -> 183.57388 | H100: =(F100-G100)/F100 -> -0.065997564 | I100: =B100-D100-K100 -> -12090 | K100: -7901 | AK100: 1000 | AN100: =K100/AK100 -> -7.901 | AO100: =AO99+AN100 -> -318.36234 | AY100: 1000 | AZ100: =D100/AY100 -> 13.79 | BA100: =AZ100+BA99 -> 287.23424 | BB100: =BA100+AO100 -> -31.128096 | BC100: 20197 | BD100: =BC100-B100 -> 26398
A101: 45589 | B101: 83202 | C101: =B101/'Clients Balance'!B101 -> 0.013586579 | D101: -8000 | E101: =C101*F100 -> 2.3397248 | F101: =F100*(1+C101) -> 174.54826 | G101: =MAX($F$2:F101) -> 183.57388 | H101: =(F101-G101)/F101 -> -0.051708444 | I101: =B101-D101-K101 -> 128642 | K101: -37440 | AK101: 1000 | AN101: =K101/AK101 -> -37.44 | AO101: =AO100+AN101 -> -355.80234 | AY101: 1000 | AZ101: =D101/AY101 -> -8 | BA101: =AZ101+BA100 -> 279.23424 | BB101: =BA101+AO101 -> -76.568096 | BC101: 157566 | BD101: =BC101-B101 -> 74364
A102: 45590 | B102: -179893 | C102: =B102/'Clients Balance'!B102 -> -0.029672131 | D102: -45130 | E102: =C102*F101 -> -5.1792187 | F102: =F101*(1+C102) -> 169.36904 | G102: =MAX($F$2:F102) -> 183.57388 | H102: =(F102-G102)/F102 -> -0.083869151 | I102: =B102-D102-K102 -> -199835 | K102: 65072 | AK102: 800 | AN102: =K102/AK102 -> 81.34 | AO102: =AO101+AN102 -> -274.46234 | AY102: 1000 | AZ102: =D102/AY102 -> -45.13 | BA102: =AZ102+BA101 -> 234.10424 | BB102: =BA102+AO102 -> -40.358096
...

Sheet Dec 25 Performance
A1: Date | B1: Cumm Capital | C1: Directional_1_Strategy_PNL | D1: Directional_2_Strategy_PNL | E1: NON_Directional_PNL | F1: 0Dte_PNL | G1: Total_PNL | H1: Cumm_PNL | I1: Drawdown | J1: Cumm pNL adjusted prev month
A2: ='PROP DAILY PNL'!A376 -> 45992 | B2: 128000 | C2: ='PROP DAILY PNL'!J376/$B$2/100 -> 0.0047592188 | D2: ='PROP DAILY PNL'!R376/$B$2/100 -> -0.0037075 | E2: ='PROP DAILY PNL'!Q376/$B$2/100 -> 0.0023203125 | F2: ='PROP DAILY PNL'!I376/$B$2/100 -> 0 | G2: =SUM(C2:F2) -> 0.0033720313 | H2: =G2 -> 0.0033720313 | I2: =IF(ISBLANK(J2),,J2-MAX($J$2:J2,0)) -> -0.034015938 | J2: =H2+'Nov 25 Performance'!I21 -> -0.034015938
A3: ='PROP DAILY PNL'!A377 -> 45993 | C3: ='PROP DAILY PNL'!J377/$B$2/100 -> 0.0033822656 | D3: ='PROP DAILY PNL'!R377/$B$2/100 -> 0.00046140625 | E3: ='PROP DAILY PNL'!Q377/$B$2/100 -> 0 | F3: ='PROP DAILY PNL'!I377/$B$2/100 -> 0.011873672 | G3: =SUM(C3:F3) -> 0.015717344 | H3: =H2+G3 -> 0.019089375 | I3: =IF(ISBLANK(J3),,J3-MAX($J$2:J3,0)) -> -0.018298594 | J3: =J2+G3 -> -0.018298594
A4: ='PROP DAILY PNL'!A378 -> 45994 | C4: ='PROP DAILY PNL'!J378/$B$2/100 -> -0.00029296875 | D4: ='PROP DAILY PNL'!R378/$B$2/100 -> 0.0047621875 | E4: ='PROP DAILY PNL'!Q378/$B$2/100 -> 0.0038810937 | F4: ='PROP DAILY PNL'!I378/$B$2/100 -> 0 | G4: =SUM(C4:F4) -> 0.0083503125 | H4: =H3+G4 -> 0.027439688 | I4: =IF(ISBLANK(J4),,J4-MAX($J$2:J4,0)) -> -0.0099482812 | J4: =J3+G4 -> -0.0099482812
A5: ='PROP DAILY PNL'!A379 -> 45995 | C5: ='PROP DAILY PNL'!J379/$B$2/100 -> 0.0016786719 | D5: ='PROP DAILY PNL'!R379/$B$2/100 -> 0.005160625 | E5: ='PROP DAILY PNL'!Q379/$B$2/100 -> 0 | F5: ='PROP DAILY PNL'!I379/$B$2/100 -> -0.0039028906 | G5: =SUM(C5:F5) -> 0.0029364063 | H5: =H4+G5 -> 0.030376094 | I5: =IF(ISBLANK(J5),,J5-MAX($J$2:J5,0)) -> -0.007011875 | J5: =J4+G5 -> -0.007011875
A6: ='PROP DAILY PNL'!A380 -> 45996 | C6: ='PROP DAILY PNL'!J380/$B$2/100 -> 0.00048570313 | D6: ='PROP DAILY PNL'!R380/$B$2/100 -> 0.00628125 | E6: ='PROP DAILY PNL'!Q380/$B$2/100 -> -0.0017196875 | F6: ='PROP DAILY PNL'!I380/$B$2/100 -> 0 | G6: =SUM(C6:F6) -> 0.0050472656 | H6: =H5+G6 -> 0.035423359 | I6: =IF(ISBLANK(J6),,J6-MAX($J$2:J6,0)) -> -0.0019646094 | J6: =J5+G6 -> -0.0019646094
A7: ='PROP DAILY PNL'!A381 -> 45999 | C7: ='PROP DAILY PNL'!J381/$B$2/100 -> 0.011570703 | D7: ='PROP DAILY PNL'!R381/$B$2/100 -> 0.0098290625 | E7: ='PROP DAILY PNL'!Q381/$B$2/100 -> 0.0011445312 | F7: ='PROP DAILY PNL'!I381/$B$2/100 -> 0 | G7: =SUM(C7:F7) -> 0.022544297 | H7: =H6+G7 -> 0.057967656 | I7: =IF(ISBLANK(J7),,J7-MAX($J$2:J7,0)) -> 0 | J7: =J6+G7 -> 0.020579687
A8: ='PROP DAILY PNL'!A382 -> 46000 | C8: ='PROP DAILY PNL'!J382/$B$2/100 -> -0.004709375 | D8: ='PROP DAILY PNL'!R382/$B$2/100 -> -0.00055953125 | E8: ='PROP DAILY PNL'!Q382/$B$2/100 -> 0 | F8: ='PROP DAILY PNL'!I382/$B$2/100 -> -0.0032278906 | G8: =SUM(C8:F8) -> -0.0084967969 | H8: =H7+G8 -> 0.049470859 | I8: =IF(ISBLANK(J8),,J8-MAX($J$2:J8,0)) -> -0.0084967969 | J8: =J7+G8 -> 0.012082891
A9: ='PROP DAILY PNL'!A383 -> 46001 | C9: ='PROP DAILY PNL'!J383/$B$2/100 -> -0.0037602344 | D9: ='PROP DAILY PNL'!R383/$B$2/100 -> -0.0024883594 | E9: ='PROP DAILY PNL'!Q383/$B$2/100 -> -0.0082109375 | F9: ='PROP DAILY PNL'!I383/$B$2/100 -> 0 | G9: =SUM(C9:F9) -> -0.014459531 | H9: =H8+G9 -> 0.035011328 | I9: =IF(ISBLANK(J9),,J9-MAX($J$2:J9,0)) -> -0.022956328 | J9: =J8+G9 -> -0.0023766406
A10: ='PROP DAILY PNL'!A384 -> 46002 | C10: ='PROP DAILY PNL'!J384/$B$2/100 -> 0.00041179687 | D10: ='PROP DAILY PNL'!R384/$B$2/100 -> -0.00099460938 | E10: ='PROP DAILY PNL'!Q384/$B$2/100 -> 0 | F10: ='PROP DAILY PNL'!I384/$B$2/100 -> -0.0018739062 | G10: =SUM(C10:F10) -> -0.0024567188 | H10: =H9+G10 -> 0.032554609 | I10: =IF(ISBLANK(J10),,J10-MAX($J$2:J10,0)) -> -0.025413047 | J10: =J9+G10 -> -0.0048333594
A11: ='PROP DAILY PNL'!A385 -> 46003 | C11: ='PROP DAILY PNL'!J385/$B$2/100 -> -0.0022890625 | D11: ='PROP DAILY PNL'!R385/$B$2/100 -> 0.0012896094 | E11: ='PROP DAILY PNL'!Q385/$B$2/100 -> 0.00098226563 | F11: ='PROP DAILY PNL'!I385/$B$2/100 -> 0 | G11: =SUM(C11:F11) -> -1.71875e-05 | H11: =H10+G11 -> 0.032537422 | I11: =IF(ISBLANK(J11),,J11-MAX($J$2:J11,0)) -> -0.025430234 | J11: =J10+G11 -> -0.0048505469
A12: ='PROP DAILY PNL'!A386 -> 46006 | C12: ='PROP DAILY PNL'!J386/$B$2/100 -> 0.00092234375 | D12: ='PROP DAILY PNL'!R386/$B$2/100 -> -0.0040625 | E12: ='PROP DAILY PNL'!Q386/$B$2/100 -> 0.0031875 | F12: ='PROP DAILY PNL'!I386/$B$2/100 -> 0 | G12: =SUM(C12:F12) -> 4.734375e-05 | H12: =H11+G12 -> 0.032584766 | I12: =IF(ISBLANK(J12),,J12-MAX($J$2:J12,0)) -> -0.025382891 | J12: =J11+G12 -> -0.0048032031
A13: ='PROP DAILY PNL'!A387 -> 46007 | C13: ='PROP DAILY PNL'!J387/$B$2/100 -> 0.001223125 | D13: ='PROP DAILY PNL'!R387/$B$2/100 -> -0.00042625 | E13: ='PROP DAILY PNL'!Q387/$B$2/100 -> 0 | F13: ='PROP DAILY PNL'!I387/$B$2/100 -> 0.010054375 | G13: =SUM(C13:F13) -> 0.01085125 | H13: =H12+G13 -> 0.043436016 | I13: =IF(ISBLANK(J13),,J13-MAX($J$2:J13,0)) -> -0.014531641 | J13: =J12+G13 -> 0.0060480469
A14: ='PROP DAILY PNL'!A388 -> 46008 | C14: ='PROP DAILY PNL'!J388/$B$2/100 -> 0.00179 | D14: ='PROP DAILY PNL'!R388/$B$2/100 -> 0.001888125 | E14: ='PROP DAILY PNL'!Q388/$B$2/100 -> 0.0044657813 | F14: ='PROP DAILY PNL'!I388/$B$2/100 -> 0 | G14: =SUM(C14:F14) -> 0.0081439062 | H14: =H13+G14 -> 0.051579922 | I14: =IF(ISBLANK(J14),,J14-MAX($J$2:J14,0)) -> -0.0063877344 | J14: =J13+G14 -> 0.014191953
... A24: ='PROP DAILY PNL'!A398 -> 46022 | C24: ='PROP DAILY PNL'!J398/$B$2/100 -> 0 | D24: ='PROP DAILY PNL'!R398/$B$2/100 -> 0 | E24: ='PROP DAILY PNL'!Q398/$B$2/100 -> 0 | F24: ='PROP DAILY PNL'!I398/$B$2/100 -> 0 | G24: =SUM(C24:F24) -> 0 | H24: =H23+G24 -> 0.064087695 | I24: =IF(ISBLANK(J24),,J24-MAX($J$2:J24,0)) -> -0.00084757813 | J24: =J23+G24 -> 0.026699727
A26: ='PROP DAILY PNL'!A400

Sheet Nov 25 Performance
A1: Date | B1: Cumm Capital | C1: Directional_1_Strategy_PNL | D1: Directional_2_Strategy_PNL | E1: NON_Directional_PNL | F1: 0Dte_PNL | G1: Total_PNL | H1: Cumm_PNL | I1: Drawdown
A2: ='PROP DAILY PNL'!A356 -> 45964 | B2: 128000 | C2: ='PROP DAILY PNL'!J356/$B$2/100 -> -0.0077914844 | D2: ='PROP DAILY PNL'!R356/$B$2/100 -> -0.0012023438 | E2: ='PROP DAILY PNL'!Q356/$B$2/100 -> 0.0031033594 | F2: ='PROP DAILY PNL'!I356/$B$2/100 -> 0 | G2: =SUM(C2:F2) -> -0.0058904687 | H2: =G2 -> -0.0058904687 | I2: =H2 -> -0.0058904687
A3: ='PROP DAILY PNL'!A357 -> 45965 | C3: ='PROP DAILY PNL'!J357/$B$2/100 -> 0.0093808594 | D3: ='PROP DAILY PNL'!R357/$B$2/100 -> 0.0044921875 | E3: ='PROP DAILY PNL'!Q357/$B$2/100 -> 0 | F3: ='PROP DAILY PNL'!I357/$B$2/100 -> 0.013676719 | G3: =SUM(C3:F3) -> 0.027549766 | H3: =G3+H2 -> 0.021659297 | I3: =H3 - MAX($H$2:H3) -> 0
A4: ='PROP DAILY PNL'!A358 -> 45966 | C4: ='PROP DAILY PNL'!J358/$B$2/100 -> 0 | D4: ='PROP DAILY PNL'!R358/$B$2/100 -> 0 | E4: ='PROP DAILY PNL'!Q358/$B$2/100 -> 0 | F4: ='PROP DAILY PNL'!I358/$B$2/100 -> 0 | G4: =SUM(C4:F4) -> 0 | H4: =G4+H3 -> 0.021659297 | I4: =H4 - MAX($H$2:H4) -> 0
A5: ='PROP DAILY PNL'!A359 -> 45967 | C5: ='PROP DAILY PNL'!J359/$B$2/100 -> -0.0018661719 | D5: ='PROP DAILY PNL'!R359/$B$2/100 -> 0.0025382813 | E5: ='PROP DAILY PNL'!Q359/$B$2/100 -> 0 | F5: ='PROP DAILY PNL'!I359/$B$2/100 -> -0.0020663281 | G5: =SUM(C5:F5) -> -0.0013942188 | H5: =G5+H4 -> 0.020265078 | I5: =H5 - MAX($H$2:H5) -> -0.0013942188
A6: ='PROP DAILY PNL'!A360 -> 45968 | C6: ='PROP DAILY PNL'!J360/$B$2/100 -> -0.0045658594 | D6: ='PROP DAILY PNL'!R360/$B$2/100 -> 0.0043863281 | E6: ='PROP DAILY PNL'!Q360/$B$2/100 -> -0.0049726562 | F6: ='PROP DAILY PNL'!I360/$B$2/100 -> 0 | G6: =SUM(C6:F6) -> -0.0051521875 | H6: =G6+H5 -> 0.015112891 | I6: =H6 - MAX($H$2:H6) -> -0.0065464063
A7: ='PROP DAILY PNL'!A361 -> 45971 | C7: ='PROP DAILY PNL'!J361/$B$2/100 -> -0.00089648438 | D7: ='PROP DAILY PNL'!R361/$B$2/100 -> -0.0027164063 | E7: ='PROP DAILY PNL'!Q361/$B$2/100 -> 0.0024765625 | F7: ='PROP DAILY PNL'!I361/$B$2/100 -> 0 | G7: =SUM(C7:F7) -> -0.0011363281 | H7: =G7+H6 -> 0.013976562 | I7: =H7 - MAX($H$2:H7) -> -0.0076827344
A8: ='PROP DAILY PNL'!A362 -> 45972 | C8: ='PROP DAILY PNL'!J362/$B$2/100 -> 0.0036400781 | D8: ='PROP DAILY PNL'!R362/$B$2/100 -> 0.0052739844 | E8: ='PROP DAILY PNL'!Q362/$B$2/100 -> 0 | F8: ='PROP DAILY PNL'!I362/$B$2/100 -> -0.009140625 | G8: =SUM(C8:F8) -> -0.0002265625 | H8: =G8+H7 -> 0.01375 | I8: =H8 - MAX($H$2:H8) -> -0.0079092969
A9: ='PROP DAILY PNL'!A363 -> 45973 | C9: ='PROP DAILY PNL'!J363/$B$2/100 -> 0.0022411719 | D9: ='PROP DAILY PNL'!R363/$B$2/100 -> -0.0024380469 | E9: ='PROP DAILY PNL'!Q363/$B$2/100 -> 0.0015621094 | F9: ='PROP DAILY PNL'!I363/$B$2/100 -> 0 | G9: =SUM(C9:F9) -> 0.0013652344 | H9: =G9+H8 -> 0.015115234 | I9: =H9 - MAX($H$2:H9) -> -0.0065440625
A10: ='PROP DAILY PNL'!A364 -> 45974 | C10: ='PROP DAILY PNL'!J364/$B$2/100 -> -0.00022851563 | D10: ='PROP DAILY PNL'!R364/$B$2/100 -> -0.010442656 | E10: ='PROP DAILY PNL'!Q364/$B$2/100 -> 0 | F10: ='PROP DAILY PNL'!I364/$B$2/100 -> -0.010365391 | G10: =SUM(C10:F10) -> -0.021036563 | H10: =G10+H9 -> -0.0059213281 | I10: =H10 - MAX($H$2:H10) -> -0.027580625
A11: ='PROP DAILY PNL'!A365 -> 45975 | C11: ='PROP DAILY PNL'!J365/$B$2/100 -> -0.0014707031 | D11: ='PROP DAILY PNL'!R365/$B$2/100 -> -0.013150469 | E11: ='PROP DAILY PNL'!Q365/$B$2/100 -> 0.004765625 | F11: ='PROP DAILY PNL'!I365/$B$2/100 -> 0 | G11: =SUM(C11:F11) -> -0.0098555469 | H11: =G11+H10 -> -0.015776875 | I11: =H11 - MAX($H$2:H11) -> -0.037436172
A12: ='PROP DAILY PNL'!A366 -> 45978 | C12: ='PROP DAILY PNL'!J366/$B$2/100 -> 0.00075609375 | D12: ='PROP DAILY PNL'!R366/$B$2/100 -> 0.0023657031 | E12: ='PROP DAILY PNL'!Q366/$B$2/100 -> -0.0002590625 | F12: ='PROP DAILY PNL'!I366/$B$2/100 -> 0 | G12: =SUM(C12:F12) -> 0.0028627344 | H12: =G12+H11 -> -0.012914141 | I12: =H12 - MAX($H$2:H12) -> -0.034573437
A13: ='PROP DAILY PNL'!A367 -> 45979 | C13: ='PROP DAILY PNL'!J367/$B$2/100 -> -0.002798125 | D13: ='PROP DAILY PNL'!R367/$B$2/100 -> 0.00030054687 | E13: ='PROP DAILY PNL'!Q367/$B$2/100 -> 0 | F13: ='PROP DAILY PNL'!I367/$B$2/100 -> 0.0095153125 | G13: =SUM(C13:F13) -> 0.0070177344 | H13: =G13+H12 -> -0.0058964062 | I13: =H13 - MAX($H$2:H13) -> -0.027555703
A14: ='PROP DAILY PNL'!A368 -> 45980 | C14: ='PROP DAILY PNL'!J368/$B$2/100 -> 0.0053027344 | D14: ='PROP DAILY PNL'!R368/$B$2/100 -> 0.00046195313 | E14: ='PROP DAILY PNL'!Q368/$B$2/100 -> -0.00314875 | F14: ='PROP DAILY PNL'!I368/$B$2/100 -> 0 | G14: =SUM(C14:F14) -> 0.0026159375 | H14: =G14+H13 -> -0.0032804687 | I14: =H14 - MAX($H$2:H14) -> -0.024939766
... A21: ='PROP DAILY PNL'!A375 -> 45989 | C21: ='PROP DAILY PNL'!J375/$B$2/100 -> -0.0024486719 | D21: ='PROP DAILY PNL'!R375/$B$2/100 -> -0.0036101563 | E21: ='PROP DAILY PNL'!Q375/$B$2/100 -> 0.0054107031 | F21: ='PROP DAILY PNL'!I375/$B$2/100 -> 0 | G21: =SUM(C21:F21) -> -0.000648125 | H21: =G21+H20 -> -0.015728672 | I21: =H21 - MAX($H$2:H21) -> -0.037387969
A22: ='PROP DAILY PNL'!A378 -> 45994

Sheet Oct 25 Performance 
A1: Date | B1: Cumm Capital | C1: Directional_1_Strategy_PNL | D1: Directional_2_Strategy_PNL | E1: NON_Directional_PNL | F1: 0Dte_PNL | G1: Total_PNL | H1: Cumm_PNL | I1: Drawdown
A2: ='PROP DAILY PNL'!A333 -> 45931 | B2: 13000000 | C2: ='PROP DAILY PNL'!J333/$B$2 -> 0.0098566923 | D2: ='PROP DAILY PNL'!R333/$B$2 -> 0.0040638462 | E2: ='PROP DAILY PNL'!Q333/$B$2 -> 0 | F2: ='PROP DAILY PNL'!I333/$B$2 -> 0.017064 | G2: =SUM(C2:F2) -> 0.030984538 | H2: =G2 -> 0.030984538 | I2: =(H2 - MAX($H$2:H2)) -> 0
A3: ='PROP DAILY PNL'!A334 -> 45932 | C3: ='PROP DAILY PNL'!J334/$B$2 -> 0 | D3: ='PROP DAILY PNL'!R334/$B$2 -> 0 | E3: ='PROP DAILY PNL'!Q334/$B$2 -> 0 | F3: ='PROP DAILY PNL'!I334/$B$2 -> 0 | G3: =SUM(C3:F3) -> 0 | H3: =H2+G3 -> 0.030984538 | I3: =(H3 - MAX($H$2:H3)) -> 0
A4: ='PROP DAILY PNL'!A335 -> 45933 | C4: ='PROP DAILY PNL'!J335/$B$2 -> 0.0026030769 | D4: ='PROP DAILY PNL'!R335/$B$2 -> -0.0045588462 | E4: ='PROP DAILY PNL'!Q335/$B$2 -> 0.0036946154 | F4: ='PROP DAILY PNL'!I335/$B$2 -> 0 | G4: =SUM(C4:F4) -> 0.0017388462 | H4: =H3+G4 -> 0.032723385 | I4: =(H4 - MAX($H$2:H4)) -> 0 | L4: Oct Performance
A5: ='PROP DAILY PNL'!A336 -> 45936 | C5: ='PROP DAILY PNL'!J336/$B$2 -> 0.0088303846 | D5: ='PROP DAILY PNL'!R336/$B$2 -> 0.0013413077 | E5: ='PROP DAILY PNL'!Q336/$B$2 -> -0.0058197692 | F5: ='PROP DAILY PNL'!I336/$B$2 -> 0 | G5: =SUM(C5:F5) -> 0.0043519231 | H5: =H4+G5 -> 0.037075308 | I5: =(H5 - MAX($H$2:H5)) -> 0
A6: ='PROP DAILY PNL'!A337 -> 45937 | C6: ='PROP DAILY PNL'!J337/$B$2 -> -0.0048615385 | D6: ='PROP DAILY PNL'!R337/$B$2 -> 0.00026384615 | E6: ='PROP DAILY PNL'!Q337/$B$2 -> 0 | F6: ='PROP DAILY PNL'!I337/$B$2 -> -0.0040769231 | G6: =SUM(C6:F6) -> -0.0086746154 | H6: =H5+G6 -> 0.028400692 | I6: =(H6 - MAX($H$2:H6)) -> -0.0086746154 | L6: Gross ROI | M6: =H24 -> 0.068891923 | O6: AVERAGE RETURN | P6: =AVERAGE(G:G) -> 0.002995301
A7: ='PROP DAILY PNL'!A338 -> 45938 | C7: ='PROP DAILY PNL'!J338/$B$2 -> -0.0041538462 | D7: ='PROP DAILY PNL'!R338/$B$2 -> 0.0026004615 | E7: ='PROP DAILY PNL'!Q338/$B$2 -> -0.0088076923 | F7: ='PROP DAILY PNL'!I338/$B$2 -> 0 | G7: =SUM(C7:F7) -> -0.010361077 | H7: =H6+G7 -> 0.018039615 | I7: =(H7 - MAX($H$2:H7)) -> -0.019035692 | L7: Charges | M7: 0.02 | O7: STD DEVIATION | P7: =STDEV(G:G) -> 0.011909351
A8: ='PROP DAILY PNL'!A339 -> 45939 | C8: ='PROP DAILY PNL'!J339/$B$2 -> -0.0022769231 | D8: ='PROP DAILY PNL'!R339/$B$2 -> 0.0018865385 | E8: ='PROP DAILY PNL'!Q339/$B$2 -> 0 | F8: ='PROP DAILY PNL'!I339/$B$2 -> -0.0083846154 | G8: =SUM(C8:F8) -> -0.008775 | H8: =H7+G8 -> 0.0092646154 | I8: =(H8 - MAX($H$2:H8)) -> -0.027810692 | L8: Net ROI | M8: =M6-M7 -> 0.048891923 | O8: Rf | P8: 0.000268
A9: ='PROP DAILY PNL'!A340 -> 45940 | D9: ='PROP DAILY PNL'!R340/$B$2 -> 0.002301 | E9: ='PROP DAILY PNL'!Q340/$B$2 -> 0.0065078462 | F9: ='PROP DAILY PNL'!I340/$B$2 -> 0 | G9: =SUM(C9:F9) -> 0.0088088462 | H9: =H8+G9 -> 0.018073462 | I9: =(H9 - MAX($H$2:H9)) -> -0.019001846 | L9: MAX DD | M9: =MIN(I:I) -> -0.027810692 | O9: Sharpe ratio | P9: =(P6-P8)/P7 -> 0.22900501
A10: ='PROP DAILY PNL'!A341 -> 45943 | C10: ='PROP DAILY PNL'!J341/$B$2 -> -0.0063484615 | D10: ='PROP DAILY PNL'!R341/$B$2 -> -0.001787 | E10: ='PROP DAILY PNL'!Q341/$B$2 -> 0.0064569231 | F10: ='PROP DAILY PNL'!I341/$B$2 -> 0 | G10: =SUM(C10:F10) -> -0.0016785385 | H10: =H9+G10 -> 0.016394923 | I10: =(H10 - MAX($H$2:H10)) -> -0.020680385 | L10: TOTAL WIN DAYS | M10: =COUNTIF(G:G,">0") -> 12
A11: ='PROP DAILY PNL'!A342 -> 45944 | C11: ='PROP DAILY PNL'!J342/$B$2 -> 0.0069507692 | D11: ='PROP DAILY PNL'!R342/$B$2 -> 0.0024615385 | E11: ='PROP DAILY PNL'!Q342/$B$2 -> 0 | F11: ='PROP DAILY PNL'!I342/$B$2 -> 0.0068471538 | G11: =SUM(C11:F11) -> 0.016259462 | H11: =H10+G11 -> 0.032654385 | I11: =(H11 - MAX($H$2:H11)) -> -0.0044209231 | L11: TOTAL LOSS DAYS | M11: =COUNTIF(G:G,"<0") -> 8
A12: ='PROP DAILY PNL'!A343 -> 45945 | C12: ='PROP DAILY PNL'!J343/$B$2 -> 0.0024005385 | D12: ='PROP DAILY PNL'!R343/$B$2 -> -0.00064469231 | E12: ='PROP DAILY PNL'!Q343/$B$2 -> 0.0010338462 | F12: ='PROP DAILY PNL'!I343/$B$2 -> 0 | G12: =SUM(C12:F12) -> 0.0027896923 | H12: =H11+G12 -> 0.035444077 | I12: =(H12 - MAX($H$2:H12)) -> -0.0016312308 | L12: Sharpe annualised | M12: =0.24*SQRT(252) -> 3.8098819
A13: ='PROP DAILY PNL'!A344 -> 45946 | C13: ='PROP DAILY PNL'!J344/$B$2 -> 0.0072847692 | D13: ='PROP DAILY PNL'!R344/$B$2 -> 0.00076153846 | E13: ='PROP DAILY PNL'!Q344/$B$2 -> 0 | F13: ='PROP DAILY PNL'!I344/$B$2 -> 0.025769231 | G13: =SUM(C13:F13) -> 0.033815538 | H13: =H12+G13 -> 0.069259615 | I13: =(H13 - MAX($H$2:H13)) -> 0
A14: ='PROP DAILY PNL'!A345 -> 45947 | C14: ='PROP DAILY PNL'!J345/$B$2 -> -0.00068361538 | D14: ='PROP DAILY PNL'!R345/$B$2 -> 0.0045216154 | E14: ='PROP DAILY PNL'!Q345/$B$2 -> -0.012076923 | F14: ='PROP DAILY PNL'!I345/$B$2 -> 0 | G14: =SUM(C14:F14) -> -0.0082389231 | H14: =H13+G14 -> 0.061020692 | I14: =(H14 - MAX($H$2:H14)) -> -0.0082389231
A15: ='PROP DAILY PNL'!A346 -> 45950 | C15: ='PROP DAILY PNL'!J346/$B$2 -> 0 | D15: ='PROP DAILY PNL'!R346/$B$2 -> 0.00049123077 | E15: ='PROP DAILY PNL'!Q346/$B$2 -> 0 | F15: ='PROP DAILY PNL'!I346/$B$2 -> -0.009 | G15: =SUM(C15:F15) -> -0.0085087692 | H15: =H14+G15 -> 0.052511923 | I15: =(H15 - MAX($H$2:H15)) -> -0.016747692
A16: ='PROP DAILY PNL'!A347 -> 45951 | C16: ='PROP DAILY PNL'!J347/$B$2 -> 0 | D16: ='PROP DAILY PNL'!R347/$B$2 -> 0 | E16: ='PROP DAILY PNL'!Q347/$B$2 -> 0 | F16: ='PROP DAILY PNL'!I347/$B$2 -> 0 | G16: =SUM(C16:F16) -> 0 | H16: =H15+G16 -> 0.052511923 | I16: =(H16 - MAX($H$2:H16)) -> -0.016747692
A17: ='PROP DAILY PNL'!A348 -> 45952 | C17: ='PROP DAILY PNL'!J348/$B$2 -> 0 | D17: ='PROP DAILY PNL'!R348/$B$2 -> 0 | E17: ='PROP DAILY PNL'!Q348/$B$2 -> 0 | F17: ='PROP DAILY PNL'!I348/$B$2 -> 0 | G17: =SUM(C17:F17) -> 0 | H17: =H16+G17 -> 0.052511923 | I17: =(H17 - MAX($H$2:H17)) -> -0.016747692
A18: ='PROP DAILY PNL'!A349 -> 45953 | C18: ='PROP DAILY PNL'!J349/$B$2 -> 0.0045709231 | D18: ='PROP DAILY PNL'!R349/$B$2 -> 0.0028709231 | E18: ='PROP DAILY PNL'!Q349/$B$2 -> 0 | F18: ='PROP DAILY PNL'!I349/$B$2 -> 0.0070786154 | G18: =SUM(C18:F18) -> 0.014520462 | H18: =H17+G18 -> 0.067032385 | I18: =(H18 - MAX($H$2:H18)) -> -0.0022272308
A19: ='PROP DAILY PNL'!A350 -> 45954 | C19: ='PROP DAILY PNL'!J350/$B$2 -> 0.0051904615 | D19: ='PROP DAILY PNL'!R350/$B$2 -> 0.0024412308 | E19: ='PROP DAILY PNL'!Q350/$B$2 -> -0.0028941538 | F19: ='PROP DAILY PNL'!I350/$B$2 -> 0 | G19: =SUM(C19:F19) -> 0.0047375385 | H19: =H18+G19 -> 0.071769923 | I19: =(H19 - MAX($H$2:H19)) -> 0
A20: ='PROP DAILY PNL'!A351 -> 45957 | C20: ='PROP DAILY PNL'!J351/$B$2 -> -7.9307692e-05 | D20: ='PROP DAILY PNL'!R351/$B$2 -> -0.00053246154 | E20: ='PROP DAILY PNL'!Q351/$B$2 -> 0.0051603077 | F20: ='PROP DAILY PNL'!I351/$B$2 -> 0 | G20: =SUM(C20:F20) -> 0.0045485385 | H20: =H19+G20 -> 0.076318462 | I20: =(H20 - MAX($H$2:H20)) -> 0
A21: ='PROP DAILY PNL'!A352 -> 45958 | C21: ='PROP DAILY PNL'!J352/$B$2 -> -0.0071974615 | D21: ='PROP DAILY PNL'!R352/$B$2 -> -0.0034762308 | E21: ='PROP DAILY PNL'!Q352/$B$2 -> 0 | F21: ='PROP DAILY PNL'!I352/$B$2 -> -0.0022231538 | G21: =SUM(C21:F21) -> -0.012896846 | H21: =H20+G21 -> 0.063421615 | I21: =(H21 - MAX($H$2:H21)) -> -0.012896846
A22: ='PROP DAILY PNL'!A353 -> 45959 | C22: ='PROP DAILY PNL'!J353/$B$2 -> 0.00039369231 | D22: ='PROP DAILY PNL'!R353/$B$2 -> 0.00038076923 | E22: ='PROP DAILY PNL'!Q353/$B$2 -> -0.0018796923 | F22: ='PROP DAILY PNL'!I353/$B$2 -> 0 | G22: =SUM(C22:F22) -> -0.0011052308 | H22: =H21+G22 -> 0.062316385 | I22: =(H22 - MAX($H$2:H22)) -> -0.014002077
A23: ='PROP DAILY PNL'!A354 -> 45960 | C23: ='PROP DAILY PNL'!J354/$B$2 -> 0.0024092308 | D23: ='PROP DAILY PNL'!R354/$B$2 -> 0.0027792308 | E23: ='PROP DAILY PNL'!Q354/$B$2 -> 0 | F23: ='PROP DAILY PNL'!I354/$B$2 -> -0.00023 | G23: =SUM(C23:F23) -> 0.0049584615 | H23: =H22+G23 -> 0.067274846 | I23: =(H23 - MAX($H$2:H23)) -> -0.0090436154
A24: ='PROP DAILY PNL'!A355 -> 45961 | C24: ='PROP DAILY PNL'!J355/$B$2 -> -0.00043553846 | D24: ='PROP DAILY PNL'!R355/$B$2 -> 0.0046312308 | E24: ='PROP DAILY PNL'!Q355/$B$2 -> -0.0025786154 | F24: ='PROP DAILY PNL'!I355/$B$2 -> 0 | G24: =SUM(C24:F24) -> 0.0016170769 | H24: =H23+G24 -> 0.068891923 | I24: =(H24 - MAX($H$2:H24)) -> -0.0074265385

Sheet Clients Balance
A1: Date | B1: NET Prop Account | C1: Abhishek S | D1: Radhika | E1: KARAN | F1: Pavan | G1: Rasul | H1: SIVA | I1: RAVI | J1: MAHESH | K1: JAGADISH | L1: Bharghav | M1: Kaushik | N1: MAHESH A | O1: Aayushi A | P1: Dishant | Q1: BHARATH | R1: NARESH
A2: 45446 | B2: =SUM(C2:E2) -> 3056448.9 | C2: 2000000 | D2: 522572.87 | E2: 533876
A3: 45447 | B3: =SUM(C3:E3) -> 3139071.1 | C3: =C2+Sheet!C2 -> 2054064.2 | D3: =D2+Sheet!D2 -> 536699.12 | E3: =E2+Sheet!E2 -> 548307.79
A4: 45448 | B4: =SUM(C4:E4) -> 3294831.1 | C4: =C3+Sheet!C3 -> 2155986.4 | D4: =D3+Sheet!D3 -> 563330 | E4: =E3+Sheet!E3 -> 575514.7
A5: 45449 | B5: =SUM(C5:E5) -> 3281158.6 | C5: =C4+Sheet!C4 -> 2147039.8 | D5: =D4+Sheet!D4 -> 560992.36 | E5: =E4+Sheet!E4 -> 573126.5
A6: 45450 | B6: =SUM(C6:E6) -> 3287065.6 | C6: =C5+Sheet!C5 -> 2150905 | D6: =D5+Sheet!D5 -> 562002.31 | E6: =E5+Sheet!E5 -> 574158.29
A7: 45453 | B7: =SUM(C7:E7) -> 3319363.6 | C7: =C6+Sheet!C6 -> 2172039.4 | D7: =D6+Sheet!D6 -> 567524.42 | E7: =E6+Sheet!E6 -> 579799.84
A8: 45454 | B8: =SUM(C8:E8) -> 3351432.1 | C8: =C7+Sheet!C7 -> 2193023.5 | D8: =D7+Sheet!D7 -> 573007.3 | E8: =E7+Sheet!E7 -> 585401.31
A9: 45455 | B9: =SUM(C9:E9) -> 3351969.1 | C9: =C8+Sheet!C8 -> 2193374.9 | D9: =D8+Sheet!D8 -> 573099.11 | E9: =E8+Sheet!E8 -> 585495.11
A10: 45456 | B10: =SUM(C10:E10) -> 3343665.1 | C10: =C9+Sheet!C9 -> 2187941.1 | D10: =D9+Sheet!D9 -> 571679.34 | E10: =E9+Sheet!E9 -> 584044.63
A11: 45457 | B11: =SUM(C11:E11) -> 3353408.4 | C11: =C10+Sheet!C10 -> 2194316.7 | D11: =D10+Sheet!D10 -> 573345.18 | E11: =E10+Sheet!E10 -> 585746.51
A12: 45461 | B12: =SUM(C12:E12) -> 3353893.9 | C12: =C11+Sheet!C11 -> 2194634.4 | D12: =D11+Sheet!D11 -> 573428.19 | E12: =E11+Sheet!E11 -> 585831.31
A13: 45462 | B13: =SUM(C13:E13) -> 3360276.1 | C13: =C12+Sheet!C12 -> 2198810.6 | D13: =D12+Sheet!D12 -> 574519.39 | E13: =E12+Sheet!E12 -> 586946.11
A14: 45463 | B14: =SUM(C14:E14) -> 3302473.4 | C14: =C13+Sheet!C13 -> 2160987.2 | D14: =D13+Sheet!D13 -> 564636.63 | E14: =E13+Sheet!E13 -> 576849.59
... A21: 45472 | B21: =SUM(C21:E21) -> 3179069.6 | C21: =C20+Sheet!C20 -> 2080237.4 | D21: =D20+Sheet!D20 -> 543537.81 | E21: =E20+Sheet!E20 -> 555294.41
A22: 45474 | B22: =C22+D22+E22 -> 3074680.1 | C22: =Monthly!F4 -> 1994647.4 | D22: =Monthly!M4 -> 534238.63 | E22: =Monthly!S4 -> 545794.09
A23: 45475 | B23: =C23+D23+E23 -> 3064017.9 | C23: =C22+Sheet!C21 -> 1987608.2 | D23: =D22+Sheet!D21 -> 532430.86 | E23: =E22+Sheet!E21 -> 543978.82
A24: 45476 | B24: =C24+D24+E24 -> 3039333.9 | C24: =C23+Sheet!C22 -> 1971566.4 | D24: =D23+Sheet!D22 -> 528148.82 | E24: =E23+Sheet!E22 -> 539618.7
A25: 45477 | B25: =C25+D25+E25 -> 3151837.7 | C25: =C24+Sheet!C23 -> 2044546.9 | D25: =D24+Sheet!D23 -> 547698.47 | E25: =E24+Sheet!E23 -> 559592.36
A26: 45478 | B26: =C26+D26+E26 -> 3191716.4 | C26: =C25+Sheet!C24 -> 2070415.6 | D26: =D25+Sheet!D24 -> 554628.25 | E26: =E25+Sheet!E24 -> 566672.64
A27: 45481 | B27: =C27+D27+E27 -> 3165971.9 | C27: =C26+Sheet!C25 -> 2053715.5 | D27: =D26+Sheet!D25 -> 550154.59 | E27: =E26+Sheet!E25 -> 562101.84
A28: 45482 | B28: =C28+D28+E28 -> 3121339.4 | C28: =C27+Sheet!C26 -> 2024763.1 | D28: =D27+Sheet!D26 -> 542398.75 | E28: =E27+Sheet!E26 -> 554177.57
A29: 45483 | B29: =C29+D29+E29 -> 3108694.7 | C29: =C28+Sheet!C27 -> 2016560.7 | D29: =D28+Sheet!D27 -> 540201.46 | E29: =E28+Sheet!E27 -> 551932.56
A30: 45484 | B30: =C30+D30+E30 -> 3170628.9 | C30: =C29+Sheet!C28 -> 2056736.4 | D30: =D29+Sheet!D28 -> 550963.85 | E30: =E29+Sheet!E28 -> 562928.66
A31: 45485 | B31: =C31+D31+E31 -> 3192617.7 | C31: =C30+Sheet!C29 -> 2071000.2 | D31: =D30+Sheet!D29 -> 554784.86 | E31: =E30+Sheet!E29 -> 566832.65
A32: 45488 | B32: =C32+D32+E32 -> 3204711.7 | C32: =C31+Sheet!C30 -> 2078845.4 | D32: =D31+Sheet!D30 -> 556886.45 | E32: =E31+Sheet!E30 -> 568979.88
A33: 45489 | B33: =C33+D33+E33 -> 3207636.7 | C33: =C32+Sheet!C31 -> 2080742.8 | D33: =D32+Sheet!D31 -> 557394.73 | E33: =E32+Sheet!E31 -> 569499.2
A34: 45491 | B34: =C34+D34+E34 -> 3314707.9 | C34: =C33+Sheet!C32 -> 2150198.2 | D34: =D33+Sheet!D32 -> 576000.62 | E34: =E33+Sheet!E32 -> 588509.14
A35: 45492 | B35: =C35+D35+E35 -> 3273742.9 | C35: =C34+Sheet!C33 -> 2123624.8 | D35: =D34+Sheet!D33 -> 568882.09 | E35: =E34+Sheet!E33 -> 581236.02
A36: 45495 | B36: =C36+D36+E36 -> 3364299.7 | C36: =C35+Sheet!C34 -> 2182367.6 | D36: =D35+Sheet!D34 -> 584618.24 | E36: =E35+Sheet!E34 -> 597313.9 | F36: ATH
A37: 45496 | B37: =C37+D37+E37 -> 3292062.7 | C37: =C36+Sheet!C35 -> 2135508.6 | D37: =D36+Sheet!D35 -> 572065.53 | E37: =E36+Sheet!E35 -> 584488.59
A38: 45497 | B38: =C38+D38+E38 -> 3175452.9 | C38: =C37+Sheet!C36 -> 2059865.7 | D38: =D37+Sheet!D36 -> 551802.12 | E38: =E37+Sheet!E36 -> 563785.14
A39: 45498 | B39: =C39+D39+E39 -> 3060863.2 | C39: =C38+Sheet!C37 -> 1985533.1 | D39: =D38+Sheet!D37 -> 531889.73 | E39: =E38+Sheet!E37 -> 543440.33
A40: 45499 | B40: =C40+D40+E40 -> 3122894.4 | C40: =C39+Sheet!C38 -> 2025771.8 | D40: =D39+Sheet!D38 -> 542668.97 | E40: =E39+Sheet!E38 -> 554453.65
A41: 45502 | B41: =C41+D41+E41 -> 3363901.7 | C41: =C40+Sheet!C39 -> 2182109.4 | D41: =D40+Sheet!D39 -> 584549.08 | E41: =E40+Sheet!E39 -> 597243.23
A42: 45503 | B42: =C42+D42+E42 -> 3278641.7 | C42: =C41+Sheet!C40 -> 2126802.6 | D42: =D41+Sheet!D40 -> 569733.35 | E42: =E41+Sheet!E40 -> 582105.76
A43: 45504 | B43: =C43+D43+E43 -> 3167301.7 | C43: =C42+Sheet!C41 -> 2054578.1 | D43: =D42+Sheet!D41 -> 550385.67 | E43: =E42+Sheet!E41 -> 562337.93
A44: 45505 | B44: =C44+D44+E44 -> 3114578.2 | C44: =C43+Sheet!C42 -> 2020377.2 | D44: =D43+Sheet!D42 -> 541223.84 | E44: =E43+Sheet!E42 -> 552977.14
A45: 45506 | B45: =C45+D45+E45 -> 2993789.9 | C45: =Monthly!F5 -> 1924607.9 | D45: =Monthly!M5 -> 528871.32 | E45: =Monthly!S5 -> 540310.68
A46: 45509 | B46: =C46+D46+E46 -> 3094367.9 | C46: =C45+Sheet!C43 -> 1989851.2 | D46: =D45+Sheet!D43 -> 546348.87 | E46: =E45+Sheet!E43 -> 558167.78
A47: 45510 | B47: =C47+D47+E47 -> 3227884.1 | C47: =C46+Sheet!C44 -> 2076461.1 | D47: =D46+Sheet!D44 -> 569550.15 | E47: =E46+Sheet!E44 -> 581872.9
A48: 45511 | B48: =C48+D48+E48 -> 3196663.1 | C48: =C47+Sheet!C45 -> 2056390.1 | D48: =D47+Sheet!D45 -> 564034.77 | E48: =E47+Sheet!E45 -> 576238.22
A49: 45512 | B49: =C49+D49+E49 -> 3272463.1 | C49: =C48+Sheet!C46 -> 2105133.8 | D49: =D48+Sheet!D46 -> 577418.19 | E49: =E48+Sheet!E46 -> 589911.16
A50: 45513 | B50: =C50+D50+E50 -> 3266084.1 | C50: =C49+Sheet!C47 -> 2101030.2 | D50: =D49+Sheet!D47 -> 576292.64 | E50: =E49+Sheet!E47 -> 588761.26
A51: 45516 | B51: =C51+D51+E51 -> 3282215.1 | C51: =C50+Sheet!C48 -> 2111407.2 | D51: =D50+Sheet!D48 -> 579138.87 | E51: =E50+Sheet!E48 -> 591669.07
A52: 45517 | B52: =C52+D52+E52 -> 3450658.1 | C52: =C51+Sheet!C49 -> 2219764.4 | D52: =D51+Sheet!D49 -> 608860.23 | E52: =E51+Sheet!E49 -> 622033.48
A53: 45518 | B53: =C53+D53+E53 -> 3494480.1 | C53: =C52+Sheet!C50 -> 2247954.5 | D53: =D52+Sheet!D50 -> 616592.51 | E53: =E52+Sheet!E50 -> 629933.06
A54: 45519 | B54: =C54+D54+E54 -> 3494683.1 | C54: =C53+Sheet!C51 -> 2248085.1 | D54: =D53+Sheet!D51 -> 616628.33 | E54: =E53+Sheet!E51 -> 629969.65
A55: 45520 | B55: =C55+D55+E55 -> 3533147.1 | C55: =C54+Sheet!C52 -> 2272828.5 | D55: =D54+Sheet!D52 -> 623415.21 | E55: =E54+Sheet!E52 -> 636903.37
A56: 45523 | B56: =C56+D56+E56 -> 3527309.1 | C56: =C55+Sheet!C53 -> 2269073 | D56: =D55+Sheet!D53 -> 622385.11 | E56: =E55+Sheet!E53 -> 635850.98
A57: 45524 | B57: =C57+D57+E57 -> 3512233.1 | C57: =C56+Sheet!C54 -> 2259374.8 | D57: =D56+Sheet!D54 -> 619724.99 | E57: =E56+Sheet!E54 -> 633133.31
... A66: 45533 | B66: =C66+D66+E66 -> 3701723.6 | C66: =C65+Sheet!C63 -> 2381271.6 | D66: =D65+Sheet!D63 -> 653160.13 | E66: =E65+Sheet!E63 -> 667291.84
A67: 45534 | B67: =C67+D67+E67 -> 4161110.6 | C67: =Monthly!F6 -> 2616105.8 | D67: =Monthly!M6 -> 640574.65 | E67: =Monthly!S6 -> 904430.13
A68: 45537 | B68: =C68+D68+E68 -> 4123400.4 | C68: =C67+Sheet!C64 -> 2592397.3 | D68: =D67+Sheet!D64 -> 634769.42 | E68: =E67+Sheet!E64 -> 896233.69
A69: 45538 | B69: =C69+D69+E69 -> 3989395.4 | C69: =C68+Sheet!C65 -> 2508147.8 | D69: =D68+Sheet!D65 -> 614140.26 | E69: =E68+Sheet!E65 -> 867107.3
A70: 45539 | B70: =C70+D70+E70 -> 4138795.4 | C70: =C69+Sheet!C66 -> 2602076.1 | D70: =D69+Sheet!D66 -> 637139.37 | E70: =E69+Sheet!E66 -> 899579.85
A71: 45540 | B71: =C71+D71+E71 -> 4364197.4 | C71: =C70+Sheet!C67 -> 2743787.2 | D71: =D70+Sheet!D67 -> 671838.47 | E71: =E70+Sheet!E67 -> 948571.66
A72: 45541 | B72: =C72+D72+E72 -> 4382601.4 | C72: =C71+Sheet!C68 -> 2755357.9 | D72: =D71+Sheet!D68 -> 674671.65 | E72: =E71+Sheet!E68 -> 952571.83
A73: 45544 | B73: =C73+D73+E73 -> 4458474.4 | C73: =C72+Sheet!C69 -> 2803059.5 | D73: =D72+Sheet!D69 -> 686351.78 | E73: =E72+Sheet!E69 -> 969063.05
A74: 45545 | B74: =C74+D74+E74 -> 4433587.4 | C74: =C73+Sheet!C70 -> 2787413 | D74: =D73+Sheet!D70 -> 682520.59 | E74: =E73+Sheet!E70 -> 963653.79
A75: 45546 | B75: =C75+D75+E75 -> 4507657.4 | C75: =C74+Sheet!C71 -> 2833981.1 | D75: =D74+Sheet!D71 -> 693923.17 | E75: =E74+Sheet!E71 -> 979753.13
A76: 45547 | B76: =C76+D76+E76 -> 4768003.4 | C76: =C75+Sheet!C72 -> 2997661.6 | D76: =D75+Sheet!D72 -> 734001.66 | E76: =E75+Sheet!E72 -> 1036340.1
A77: 45548 | B77: =C77+D77+E77 -> 4765421.4 | C77: =C76+Sheet!C73 -> 2996038.3 | D77: =D76+Sheet!D73 -> 733604.18 | E77: =E76+Sheet!E73 -> 1035778.9
A78: 45551 | B78: =C78+D78+E78 -> 4862935.9 | C78: =C77+Sheet!C74 -> 3057346 | D78: =D77+Sheet!D74 -> 748615.87 | E78: =E77+Sheet!E74 -> 1056974
A79: 45552 | B79: =C79+D79+E79 -> 4995645.9 | C79: =C78+Sheet!C75 -> 3140781.3 | D79: =D78+Sheet!D75 -> 769045.67 | E79: =E78+Sheet!E75 -> 1085818.9
... A87: 45562 | B87: =C87+D87+E87 -> 5284423.9 | C87: =C86+Sheet!C83 -> 3322337.1 | D87: =D86+Sheet!D83 -> 813501.08 | E87: =E86+Sheet!E83 -> 1148585.7
A88: 45565 | B88: =C88+D88+E88 -> 5745795.9 | C88: =Monthly!F7 -> 3779486.7 | D88: =Monthly!M7 -> 815251.72 | E88: =Monthly!V6 -> 1151057.4
A89: 45566 | B89: =C89+D89+E89 -> 5760249.9 | C89: =C88+Sheet!C85 -> 3788994.3 | D89: =D88+Sheet!D85 -> 817302.55 | E89: =E88+Sheet!E85 -> 1153953
A90: 45568 | B90: =C90+D90+E90 -> 5671752.9 | C90: =C89+Sheet!C86 -> 3730782.5 | D90: =D89+Sheet!D86 -> 804746.01 | E90: =E89+Sheet!E86 -> 1136224.4
A91: 45569 | B91: =C91+D91+E91 -> 5565485.4 | C91: =C90+Sheet!C87 -> 3660881.5 | D91: =D90+Sheet!D87 -> 789668.07 | E91: =E90+Sheet!E87 -> 1114935.8
A92: 45572 | B92: =C92+D92+E92 -> 5588369.4 | C92: =C91+Sheet!C88 -> 3675934.2 | D92: =D91+Sheet!D88 -> 792915 | E92: =E91+Sheet!E88 -> 1119520.1
A93: 45573 | B93: =C93+D93+E93 -> 5827465.4 | C93: =C92+Sheet!C89 -> 3833207.5 | D93: =D92+Sheet!D89 -> 826839.53 | E93: =E92+Sheet!E89 -> 1167418.3
A94: 45574 | B94: =C94+D94+E94 -> 5754155.4 | C94: =C93+Sheet!C90 -> 3784985.4 | D94: =D93+Sheet!D90 -> 816437.82 | E94: =E93+Sheet!E90 -> 1152732.1
A95: 45575 | B95: =C95+D95+E95 -> 6048942.4 | C95: =C94+Sheet!C91 -> 3978891.3 | D95: =D94+Sheet!D91 -> 858264.16 | E95: =E94+Sheet!E91 -> 1211786.9
A96: 45576 | B96: =C96+D96+E96 -> 6213253.4 | C96: =C95+Sheet!C92 -> 4086972.3 | D96: =D95+Sheet!D92 -> 881577.7 | E96: =E95+Sheet!E92 -> 1244703.4
A97: 45579 | B97: =C97+D97+E97 -> 6115654.4 | C97: =C96+Sheet!C93 -> 4022773.3 | D97: =D96+Sheet!D93 -> 867729.71 | E97: =E96+Sheet!E93 -> 1225151.3
A98: 45580 | B98: =C98+D98+E98 -> 5769946.4 | C98: =C97+Sheet!C94 -> 3795372.5 | D98: =D97+Sheet!D94 -> 818678.36 | E98: =E97+Sheet!E94 -> 1155895.5
A99: 45581 | B99: =C99+D99+E99 -> 6006197.4 | C99: =C98+Sheet!C95 -> 3950774.4 | D99: =D98+Sheet!D95 -> 852199.22 | E99: =E98+Sheet!E95 -> 1203223.8
A100: 45582 | B100: =C100+D100+E100 -> 6165192.4 | C100: =C99+Sheet!C96 -> 4055358.6 | D100: =D99+Sheet!D96 -> 874758.49 | E100: =E99+Sheet!E96 -> 1235075.3
... A110: 45596 | B110: =C110+D110+E110 -> 5928337.4 | C110: =C109+Sheet!C106 -> 3899559.4 | D110: =D109+Sheet!D106 -> 841151.92 | E110: =E109+Sheet!E106 -> 1187626.1
A111: 45600 | B111: =C111+D111+E111 -> 5695951.4 | C111: =Monthly!F8 -> 3729589 | D111: =Monthly!M8 -> 815273.79 | E111: =Monthly!S8 -> 1151088.6 | F111: 4985616
A112: 45601 | B112: =C112+D112+E112 -> 5980442.4 | C112: =C111+Sheet!C107 -> 3916722.3 | D112: =D111+Sheet!D107 -> 855639.26 | E112: =E111+Sheet!E107 -> 1208080.8
A113: 45602 | B113: =C113+D113+E113 -> 6003700.4 | C113: =C112+Sheet!C108 -> 3931951.2 | D113: =D112+Sheet!D108 -> 858968.23 | E113: =E112+Sheet!E108 -> 1212781
A114: 45603 | B114: =C114+D114+E114 -> 6012169.4 | C114: =C113+Sheet!C109 -> 3937497.7 | D114: =D113+Sheet!D109 -> 860179.91 | E114: =E113+Sheet!E109 -> 1214491.8
A115: 45604 | B115: =C115+D115+E115 -> 6237471.4 | C115: =C114+Sheet!C110 -> 4085052.8 | D115: =D114+Sheet!D110 -> 892414.58 | E115: =E114+Sheet!E110 -> 1260004
A116: 45607 | B116: =C116+D116+E116 -> 6181259.4 | C116: =C115+Sheet!C111 -> 4048238.3 | D116: =D115+Sheet!D111 -> 884372.15 | E116: =E115+Sheet!E111 -> 1248648.9
A117: 45608 | B117: =C117+D117+E117 -> 6181259.4 | C117: =C116+Sheet!C112 -> 4048238.3 | D117: =D116+Sheet!D112 -> 884372.15 | E117: =E116+Sheet!E112 -> 1248648.9
A118: 45609 | B118: =C118+D118+E118 -> 6181259.4 | C118: =C117+Sheet!C113 -> 4048238.3 | D118: =D117+Sheet!D113 -> 884372.15 | E118: =E117+Sheet!E113 -> 1248648.9
A119: 45610 | B119: =C119+D119+E119 -> 6135950.4 | C119: =C118+Sheet!C114 -> 4018564.5 | D119: =D118+Sheet!D114 -> 877889.65 | E119: =E118+Sheet!E114 -> 1239496.2
A120: 45614 | B120: =C120+D120+E120 -> 6120863.4 | C120: =C119+Sheet!C115 -> 4008683.7 | D120: =D119+Sheet!D115 -> 875731.1 | E120: =E119+Sheet!E115 -> 1236448.5
A121: 45615 | B121: =C121+D121+E121 -> 6120863.4 | C121: =C120+Sheet!C116 -> 4008683.7 | D121: =D120+Sheet!D116 -> 875731.1 | E121: =E120+Sheet!E116 -> 1236448.5
A122: 45617 | B122: =C122+D122+E122 -> 6133820.4 | C122: =C121+Sheet!C117 -> 4017169.5 | D122: =D121+Sheet!D117 -> 877584.9 | E122: =E121+Sheet!E117 -> 1239065.9
A123: 45618 | B123: =C123+D123+E123 -> 6175272.4 | C123: =C122+Sheet!C118 -> 4044317.3 | D123: =D122+Sheet!D118 -> 883515.57 | E123: =E122+Sheet!E118 -> 1247439.5
... A129: 45626 | B129: =C129+D129+E129 -> 6260800.4 | C129: =C128+Sheet!C124 -> 4100331.4 | D129: =D128+Sheet!D124 -> 895752.33 | E129: =E128+Sheet!E124 -> 1264716.6
A130: 45627 | B130: =C130+D130+E130 -> 6101774.4 | C130: =Monthly!F9 -> 3978928 | D130: =Monthly!M9 -> 880153.64 | E130: =Monthly!S9 -> 1242692.7
A131: 45628 | B131: =C131+D131+E131 -> 6004832.4 | C131: =C130+Sheet!C125 -> 3915438.6 | D131: =D130+Sheet!D125 -> 866283.84 | E131: =E130+Sheet!E125 -> 1223109.9
A132: 45629 | B132: =C132+D132+E132 -> 6047328.4 | C132: =C131+Sheet!C126 -> 3943270.1 | D132: =D131+Sheet!D126 -> 872363.88 | E132: =E131+Sheet!E126 -> 1231694.3
A133: 45630 | B133: =C133+D133+E133 -> 5863546.4 | C133: =C132+Sheet!C127 -> 3823427.1 | D133: =D132+Sheet!D127 -> 845854.15 | E133: =E132+Sheet!E127 -> 1194265.1
A134: 45631 | B134: =C134+D134+E134 -> 5762999.4 | C134: =C133+Sheet!C128 -> 3757865.6 | D134: =D133+Sheet!D128 -> 831348.79 | E134: =E133+Sheet!E128 -> 1173785
A135: 45632 | B135: =C135+D135+E135 -> 5869261.4 | C135: =C134+Sheet!C129 -> 3827155.7 | D135: =D134+Sheet!D129 -> 846677.73 | E135: =E134+Sheet!E129 -> 1195428
...

Sheet Monthly
A1: Month | C1: Gross PNL | D1: Charges total | E1: Net PNL | F1: Abhishek | M1: Radhika | S1: Karan | Y1: Pavan | AE1: Rasul | AK1: SIVA | AQ1: RAVI | AW1: MAHESH | BC1: JAGADISH | BI1: BHARGHAV | BO1: KAUSHIK | BU1: MAHESH A | CA1: AAYUSHI A | CG1: Dishant | CM1: BHARATH | CS1: NARESH
B2: Start DATE of Month | F2: Open | G2: Profit | H2: charges | I2: Close | J2: Salary | K2: Deposit/Withdrawl | L2: % Return Net | M2: Open | N2: Profit | O2: charges | P2: Close | Q2: Deposit/Withdrawl | R2: % Return Net | S2: Open | T2: Profit | U2: Charges | V2: Close | W2: Deposit/Withdrawl | X2: % Return Net | Y2: Open | Z2: Profit | AA2: Charges | AB2: Close | AC2: Deposit/Withdrawl | AD2: % Return Net | AE2: Open | AF2: Profit | AG2: Charges | AH2: Close | AI2: Deposit/Withdrawl | AJ2: % Return Net | AK2: Open | AL2: Profit | AM2: Charges | AN2: Close | AO2: Deposit/Withdrawl | AP2: % Return Net | AQ2: Open | AR2: Profit | AS2: Charges | AT2: Close | AU2: Deposit/Withdrawl | AV2: % Return Net | AW2: Open | AX2: Profit | AY2: Charges | AZ2: Close | BA2: Deposit/Withdrawl | BB2: % Return Net | BC2: Open | BD2: Profit | BE2: Charges | BF2: Close | BG2: Deposit/Withdrawl | BH2: % Return Net | BI2: Open | BJ2: Profit | BK2: Charges | BL2: Close | BM2: Deposit/Withdrawl | BN2: % Return Net | BO2: Open | BP2: Profit | BQ2: Charges | BR2: Close | BS2: Deposit/Withdrawl | BT2: % Return Net | BU2: Open | BV2: Profit | BW2: Charges | BX2: Close | BY2: Deposit/Withdrawl | BZ2: % Return Net | CA2: Open | CB2: Profit | CC2: Charges | CD2: Close | CE2: Deposit/Withdrawl | CF2: % Return Net | CG2: Open | CH2: Profit | CI2: Charges | CJ2: Close | CK2: Deposit/Withdrawl | CL2: % Return Net | CM2: Open | CN2: Profit | CO2: Charges | CP2: Close | CQ2: Deposit/Withdrawl | CR2: % Return Net | CS2: Open | CT2: Profit | CU2: Charges | CV2: Close | CW2: Deposit/Withdrawl | CX2: % Return Net | CY2: Total Open capital | CZ2: Leverage Capital | DA2: Working Capital (70%)
A3: 45467 | B3: =DATE(2024,6,1) -> 45444 | C3: 147704 | D3: =Charges!H2 -> 79472.756 | E3: =C3-D3 -> 68231.244 | F3: ='Clients Balance'!C2 -> 2000000 | G3: =E3*F3/CY3 -> 44647.398 | H3: - | I3: =F3+G3 -> 2044647.4 | J3: 50000 | K3: 0 | L3: =(I3-F3)/F3*100 -> 2.2323699 | M3: ='Clients Balance'!D2 -> 522572.87 | N3: =E3*M3/CY3 -> 11665.759 | O3: - | P3: =M3+N3 -> 534238.63 | Q3: 0 | R3: =(P3-M3)/M3*100 -> 2.2323699 | S3: ='Clients Balance'!E2 -> 533876 | T3: =E3*S3/CY3 -> 11918.087 | U3: - | V3: =S3+T3 -> 545794.09 | W3: 0 | X3: =(V3-S3)/S3*100 -> 2.2323699 | CY3: =F3+M3+S3 -> 3056448.9
A4: 45497 | B4: =EDATE(B3,1) -> 45474 | C4: =SUM('PROP DAILY PNL'!B21:B42) -> 39209.75 | D4: =Charges!H4 -> 70100 | E4: =C4-D4 -> -30890.25 | F4: =I3-50000 -> 1994647.4 | G4: =E4*F4/CY4 -> -20039.534 | H4: - | I4: =F4+G4 -> 1974607.9 | J4: 50000 | K4: 0 | L4: =(I4-F4)/F4*100 -> -1.0046655 | M4: =P3 -> 534238.63 | N4: =E4*M4/CY4 -> -5367.3111 | O4: - | P4: =M4+N4 -> 528871.32 | Q4: 0 | R4: =(P4-M4)/M4*100 -> -1.0046655 | S4: =V3 -> 545794.09 | T4: =E4*S4/CY4 -> -5483.4048 | U4: - | V4: =S4+T4 -> 540310.68 | W4: 0 | X4: =(V4-S4)/S4*100 -> -1.0046655 | CY4: =F4+M4+S4 -> 3074680.1
A5: 45528 | B5: =EDATE(B4,1) -> 45505 | C5: =SUM('PROP DAILY PNL'!B43:B63) -> 707933.75 | D5: =Charges!H6 -> 75613 | E5: =C5-D5 -> 632320.75 | F5: =I4-50000 -> 1924607.9 | G5: =E5*F5/CY5 -> 406497.97 | H5: - | I5: =F5+G5 -> 2331105.8 | J5: 50000 | K5: 400000 | L5: =(I5-F5)/F5*100 -> 21.12108 | M5: =P4 -> 528871.32 | N5: =E5*M5/CY5 -> 111703.33 | O5: - | P5: =M5+N5 -> 640574.65 | Q5: 0 | R5: =(P5-M5)/M5*100 -> 21.12108 | S5: =V4 -> 540310.68 | T5: =E5*S5/CY5 -> 114119.45 | U5: - | V5: =S5+T5 -> 654430.13 | W5: 250000 | X5: =(V5-S5)/S5*100 -> 21.12108 | CY5: =F5+M5+S5 -> 2993789.9
A6: 45559 | B6: =EDATE(B5,1) -> 45536 | C6: =SUM('PROP DAILY PNL'!B64:B84) -> 1234853.2 | D6: =Charges!H8 -> 100168 | E6: =C6-D6 -> 1134685.2 | F6: =I5-50000-50000-15000+K5 -> 2616105.8 | G6: =SUM(Sheet!C64:C84) -> 776356.86 | H6: =Charges!I8 -> 62975.997 | I6: =F6+G6-H6 -> 3329486.7 | J6: 50000 | K6: 500000 | L6: =(I6-F6)/F6*100 -> 27.268808 | M6: =P5 -> 640574.65 | N6: =SUM(Sheet!D64:D84) -> 190097.25 | O6: =Charges!K8 -> 15420.182 | P6: =M6+N6-O6 -> 815251.72 | Q6: 0 | R6: =(P6-M6)/M6*100 -> 27.268808 | S6: =V5+W5 -> 904430.13 | T6: =SUM(Sheet!E64:E84) -> 268399.14 | U6: =Charges!M8 -> 21771.822 | V6: =S6+T6-U6 -> 1151057.4 | X6: =(V6-S6)/S6*100 -> 27.268808 | CY6: =F6+M6+S6 -> 4161110.6
A7: 45589 | B7: =EDATE(B6,1) -> 45566 | C7: =SUM('PROP DAILY PNL'!B85:B106) -> 182541.5 | D7: =Charges!H10 -> 182386 | E7: =C7-D7 -> 155.5 | F7: =I6-50000+K6 -> 3779486.7 | G7: =SUM(Sheet!C85:C106) -> 120072.69 | H7: =Charges!I10 -> 119970.41 | I7: =F7+G7-H7 -> 3779589 | J7: 50000 | K7: 0 | L7: =(I7-F7)/F7*100 -> 0.0027063266 | M7: =P6 -> 815251.72 | N7: =SUM(Sheet!D85:D106) -> 25900.202 | O7: =Charges!K10 -> 25878.138 | P7: =M7+N7-O7 -> 815273.79 | Q7: 0 | R7: =(P7-M7)/M7*100 -> 0.0027063266 | S7: =V6 -> 1151057.4 | T7: =SUM(Sheet!E85:E106) -> 36568.607 | U7: =Charges!M10 -> 36537.456 | V7: =S7+T7-U7 -> 1151088.6 | W7: 0 | X7: =(V7-S7)/S7*100 -> 0.0027063266 | CY7: =F7+M7+S7 -> 5745795.9
A8: 45620 | B8: =EDATE(B7,1) -> 45597 | C8: =SUM('PROP DAILY PNL'!B107:B124) -> 564849 | D8: =Charges!H12 -> 109026 | E8: =C8-D8 -> 455823 | F8: =I7-50000 -> 3729589 | G8: =SUM(Sheet!C107:C124) -> 370742.45 | H8: =Charges!I12 -> 71403.448 | I8: =F8+G8-H8 -> 4028928 | J8: 50000 | K8: - | L8: =(I8-F8)/F8*100 -> 8.0260588 | M8: =P7 -> 815273.79 | N8: =SUM(Sheet!D107:D124) -> 80478.543 | O8: =Charges!K12 -> 15598.691 | P8: =M8+N8-O8 -> 880153.64 | Q8: 0 | R8: =(P8-M8)/M8*100 -> 7.9580446 | S8: =V7 -> 1151088.6 | T8: =SUM(Sheet!E107:E124) -> 113628 | U8: =Charges!M12 -> 22023.86 | V8: =S8+T8-U8 -> 1242692.7 | W8: 0 | X8: =(V8-S8)/S8*100 -> 7.9580446 | CY8: =F8+M8+S8 -> 5695951.4
A9: 45650 | B9: =EDATE(B8,1) -> 45627 | C9: =sum(Sheet!B125:B145) -> 268802.25 | D9: =Charges!H14 -> 169070 | E9: =C9-D9 -> 99732.25 | F9: =I8-50000 -> 3978928 | G9: =SUM(Sheet!C125:C145) -> 175119.12 | H9: =Charges!I14 -> 110249.46 | I9: =F9+G9-H9 -> 4043797.6 | J9: 50000 | K9: 500000 | L9: =(I9-F9)/F9*100 -> 1.63033 | M9: =P8 -> 880153.64 | N9: =SUM(Sheet!D125:D145) -> 38841.975 | O9: =Charges!K14 -> 24387.591 | P9: =M9+N9-O9 -> 894608.02 | Q9: 125000 | R9: =(P9-M9)/M9*100 -> 1.642257 | S9: =V8 -> 1242692.7 | T9: =SUM(Sheet!E125:E145) -> 54841.154 | U9: =Charges!M14 -> 34432.945 | V9: =S9+T9-U9 -> 1263101 | W9: 0 | X9: =(V9-S9)/S9*100 -> 1.642257 | CY9: =F9+M9+S9 -> 6101774.4
A10: 45681 | B10: =EDATE(B9,1) -> 45658 | C10: =SUM(Sheet!B146:B168) -> 916672.5 | D10: =Charges!H16 -> 253025 | E10: =C10-D10 -> 663647.5 | F10: =I9-50000+K9 -> 4493797.6 | G10: =SUM(Sheet!C146:C168) -> 460612.91 | H10: =Charges!I16+Charges!J16 -> 133888.64 | I10: =F10+G10-H10 -> 4820521.9 | J10: 50000 | K10: 200000 | L10: =(I10-F10)/F10*100 -> 7.2705603 | M10: =P9+Q9 -> 1019608 | N10: =SUM(Sheet!D146:D168) -> 104509.52 | O10: =Charges!K16+Charges!L16 -> 30378.299 | P10: =M10+N10-O10 -> 1093739.2 | R10: =(P10-M10)/M10*100 -> 7.2705603 | S10: =V9 -> 1263101 | T10: =SUM(Sheet!E146:E168) -> 129467.47 | U10: =Charges!M16+Charges!N16 -> 37632.951 | V10: =S10+T10-U10 -> 1354935.5 | W10: 0 | X10: =(V10-S10)/S10*100 -> 7.2705603 | Y10: ='Clients Balance'!F152 -> 1666666 | Z10: =SUM(Sheet!F146:F168) -> 170832.76 | AA10: =Charges!O16+Charges!P16 -> 52660.341 | AB10: =Y10+Z10-AA10 -> 1784838.4 | AC10: 0 | AD10: =(AB10-Y10)/Y10*100 -> 7.0903482 | AE10: ='Clients Balance'!G152 -> 500000 | AF10: =SUM(Sheet!G146:G168) -> 51249.849 | AG10: =Charges!Q16+Charges!R16 -> 15798.106 | AH10: =AE10+AF10-AG10 -> 535451.74 | AI10: 0 | AJ10: =(AH10-AE10)/AE10*100 -> 7.0903487 | CY10: =F10+M10+S10+Y10+AE10 -> 8943172.6
A11: 45712 | B11: =EDATE(B10,1) -> 45689 | C11: =SUM(Sheet!B169:B188) -> 607092.5 | D11: =Charges!H18+Charges!P18+Charges!R18+Charges!T18 -> 261128.22 | E11: =C11-D11 -> 345964.28 | F11: =I10-50000+K10 -> 4970521.9 | G11: =SUM(Sheet!C169:C188) -> 260375.93 | H11: =Charges!I18+Charges!J18 -> 103398.08 | I11: =F11+G11-H11 -> 5127499.8 | J11: 50000 | K11: 500000 | L11: =(I11-F11)/F11*100 -> 3.1581765 | M11: =P10 -> 1093739.2 | N11: =SUM(Sheet!D169:D188) -> 57043.051 | O11: =Charges!K18+Charges!L18 -> 23020.213 | P11: =M11+N11-O11 -> 1127762.1 | Q11: 0 | R11: =(P11-M11)/M11*100 -> 3.1106901 | S11: =V10 -> 1354935.5 | T11: =SUM(Sheet!E169:E188) -> 70665.497 | U11: =Charges!M18+Charges!N18 -> 28517.668 | V11: =S11+T11-U11 -> 1397083.3 | W11: -250000 | X11: =(V11-S11)/S11*100 -> 3.110689 | Y11: =AB10 -> 1784838.4 | Z11: =SUM(Sheet!F169:F188) -> 93086.748 | AA11: =Charges!O18+Charges!P18 -> 44370.45 | AB11: =Y11+Z11-AA11 -> 1833554.7 | AC11: 0 | AD11: =(AB11-Y11)/Y11*100 -> 2.7294515 | AE11: =AH10 -> 535451.74 | AF11: =SUM(Sheet!G169:G188) -> 27926.036 | AG11: =Charges!Q18+Charges!R18 -> 13311.137 | AH11: =AE11+AF11-AG11 -> 550066.64 | AI11: 333333 | AJ11: =(AH11-AE11)/AE11*100 -> 2.729452 | AK11: ='Clients Balance'!H177 -> 1666666 | AL11: =SUM(Sheet!H169:H188) -> 97995.24 | AM11: =Charges!S18+Charges!T18 -> 40093.539 | AN11: =AK11+AL11-AM11 -> 1724567.7 | AO11: 0 | AP11: =(AN11-AK11)/AK11*100 -> 3.4741034 | CY11: =F11+M11+S11+Y11+AE11+AK11 -> 11406153
A12: 45740 | B12: =EDATE(B11,1) -> 45717 | C12: =sum('PROP DAILY PNL'!B189:B207) -> 1003418.8 | D12: =Charges!H19 -> 260251 | E12: =C12-D12 -> 743167.75 | F12: =I11-J11+K11 -> 5577499.8 | G12: =SUMIFS(Sheet!C:C,Sheet!A:A, ">="&B12,Sheet!A:A, "<="&EOMONTH(B12,0)) -> 457391.03 | H12: =Charges!I19+Charges!J19 -> 118445.55 | I12: =F12+G12-H12 -> 5916445.2 | J12: 150000 | K12: 1100000 | L12: =(I12-F12)/F12*100 -> 6.0770148 | M12: =P11 -> 1127762.1 | N12: =SUMIFS(Sheet!D:D,Sheet!A:A, ">="&B12,Sheet!A:A, "<="&EOMONTH(B12,0)) -> 92553.018 | O12: =Charges!K19+Charges!L19 -> 23950.798 | P12: =M12+N12-O12 -> 1196364.3 | Q12: -100000 | R12: =(P12-M12)/M12*100 -> 6.0830402 | S12: =V11+W11 -> 1147083.3 | T12: =SUMIFS(Sheet!E:E,Sheet!A:A, ">="&B12,Sheet!A:A, "<="&EOMONTH(B12,0)) -> 95100.663 | U12: =Charges!M19+Charges!N19 -> 24379.004 | V12: =S12+T12-U12 -> 1217805 | W12: -150000 | X12: =(V12-S12)/S12*100 -> 6.1653464 | Y12: =AB11 -> 1833554.7 | Z12: =SUMIFS(Sheet!F:F,Sheet!A:A, ">="&B12,Sheet!A:A, "<="&EOMONTH(B12,0)) -> 150502.09 | AA12: =Charges!O19+Charges!P19 -> 38940.525 | AB12: =Y12+Z12-AA12 -> 1945116.3 | AC12: 0 | AD12: =(AB12-Y12)/Y12*100 -> 6.0844417 | AE12: =AH11+AI11 -> 883399.64 | AF12: =SUMIFS(Sheet!G:G,Sheet!A:A, ">="&B12,Sheet!A:A, "<="&EOMONTH(B12,0)) -> 67596.631 | AG12: =Charges!R19+Charges!Q19 -> 17911.827 | AH12: =AE12+AF12-AG12 -> 933084.45 | AI12: 0 | AJ12: =(AH12-AE12)/AE12*100 -> 5.6242726 | AK12: =AN11 -> 1724567.7 | AL12: =SUMIFS(Sheet!H:H,Sheet!A:A, ">="&B12,Sheet!A:A, "<="&EOMONTH(B12,0)) -> 141425.7 | AM12: =Charges!T19+Charges!S19 -> 36623.466 | AN12: =AK12+AL12-AM12 -> 1829369.9 | AO12: =1666666+972558 -> 2639224 | AP12: =(AN12-AK12)/AK12*100 -> 6.0770148 | CY12: =F12+M12+S12+Y12+AE12+AK12 -> 12293867
A13: 45772 | B13: =EDATE(B12,1) -> 45748 | C13: =sum('PROP DAILY PNL'!B208:B226) -> 269920.5 | D13: =Charges!H20 -> 390584 | E13: =C13-D13 -> -120663.5 | F13: =I12-J12+K12 -> 6866445.2 | G13: =SUMIFS(Sheet!C:C,Sheet!A:A, ">="&B13,Sheet!A:A, "<="&EOMONTH(B13,0)) -> 69209.203 | H13: =Charges!I20+Charges!J20 -> 135609.67 | I13: =F13+G13-H13 -> 6800044.8 | J13: 150000 | K13: 109856 | L13: =(I13-F13)/F13*100 -> -0.96702829 | M13: =P12+Q12 -> 1096364.3 | N13: =SUMIFS(Sheet!D:D,Sheet!A:A, ">="&B13,Sheet!A:A, "<="&EOMONTH(B13,0)) -> 11050.623 | O13: =Charges!K20+Charges!L20 -> 21652.776 | P13: =M13+N13-O13 -> 1085762.1 | Q13: 375000 | R13: =(P13-M13)/M13*100 -> -0.96702829 | S13: =V12+W12 -> 1067805 | T13: =SUMIFS(Sheet!E:E,Sheet!A:A, ">="&B13,Sheet!A:A, "<="&EOMONTH(B13,0)) -> 10762.764 | U13: =Charges!M20+Charges!N20 -> 21088.74 | V13: =S13+T13-U13 -> 1057479 | W13: 150000 | X13: =(V13-S13)/S13*100 -> -0.96702829 | Y13: ACCOUNT CLOSED | Z13: =SUMIFS(Sheet!F:F,Sheet!A:A, ">="&B13,Sheet!A:A, "<="&EOMONTH(B13,0)) -> 0 | AA13: =Charges!O20+Charges!P20 -> 0 | AD13: =(AB13-Y13)/Y13*100 -> #VALUE! | AE13: =AH12+AI12 -> 933084.45 | AF13: =SUMIFS(Sheet!G:G,Sheet!A:A, ">="&B13,Sheet!A:A, "<="&EOMONTH(B13,0)) -> 9404.8709 | AG13: =Charges!R20+Charges!Q20 -> 18428.061 | AH13: =AE13+AF13-AG13 -> 924061.26 | AI13: 0 | AJ13: =(AH13-AE13)/AE13*100 -> -0.96702829 | AK13: =AN12+AO12 -> 4468593.9 | AL13: =SUMIFS(Sheet!H:H,Sheet!A:A, ">="&B13,Sheet!A:A, "<="&EOMONTH(B13,0)) -> 45040.456 | AM13: =Charges!T20+Charges!S20 -> 88253.024 | AN13: =AK13+AL13-AM13 -> 4425381.4 | AO13: =11500000/3 -> 3833333.3 | AP13: =(AN13-AK13)/AK13*100 -> -0.96702829 | AQ13: ='Clients Balance'!I214 -> 833333 | AR13: =SUMIFS(Sheet!I:I,Sheet!A:A, ">="&B13,Sheet!A:A, "<="&EOMONTH(B13,0)) -> 8399.4426 | AS13: =Charges!U20+Charges!V20 -> 16458.009 | AT13: =AQ13+AR13-AS13 -> 825274.43 | AV13: =(AT13-AQ13)/AQ13*100 -> -0.96702829 | AW13: ='Clients Balance'!J214 -> 1666666 | AX13: =SUMIFS(Sheet!J:J,Sheet!A:A, ">="&B13,Sheet!A:A, "<="&EOMONTH(B13,0)) -> 16798.885 | AY13: =Charges!W20+Charges!X20 -> 32916.017 | AZ13: =AW13+AX13-AY13 -> 1650548.9 | BB13: =(AZ13-AW13)/AW13*100 -> -0.96702829 | BC13: ='Clients Balance'!K214 -> 833333 | BD13: =SUMIFS(Sheet!K:K,Sheet!A:A, ">="&B13,Sheet!A:A, "<="&EOMONTH(B13,0)) -> 8399.4426 | BE13: =Charges!Y20+Charges!Z20 -> 16458.009 | BF13: =BC13+BD13-BE13 -> 825274.43 | BH13: =(BF13-BC13)/BC13*100 -> -0.96702829 | BI13: 486297 | BJ13: =SUMIFS(Sheet!L:L,Sheet!A:A, ">="&B13,Sheet!A:A, "<="&EOMONTH(B13,0)) -> 4901.5505 | BK13: =Charges!AA20+Charges!AB20 -> 9604.18 | BL13: =BI13+BJ13-BK13 -> 481594.37 | BM13: 0 | BN13: =(BL13-BI13)/BI13*100 -> -0.96702829 | BO13: 486297 | BP13: =SUMIFS(Sheet!M:M,Sheet!A:A, ">="&B13,Sheet!A:A, "<="&EOMONTH(B13,0)) -> 4901.5505 | BQ13: =Charges!AC20+Charges!AD20 -> 9604.18 | BR13: =BO13+BP13-BQ13 -> 481594.37 | BT13: =(BR13-BO13)/BO13*100 -> -0.96702829 | BU13: 833333 | BV13: =SUMIFS(Sheet!N:N,Sheet!A:A, ">="&B13,Sheet!A:A, "<="&EOMONTH(B13,0)) -> 73733.354 | BW13: =Charges!AE20+Charges!AF20 -> 13250.669 | BX13: =BU13+BV13-BW13 -> 893815.68 | BY13: CLOSED | BZ13: =(BX13-BU13)/BU13*100 -> 7.2579251 | CA13: 500000 | CB13: =SUMIFS(Sheet!O:O,Sheet!A:A, ">="&B13,Sheet!A:A, "<="&EOMONTH(B13,0)) -> 7318.3564 | CC13: =Charges!AG20+Charges!AH20 -> 7260.8037 | CD13: =CA13+CB13-CC13 -> 500057.55 | CE13: 0 | CF13: =(CD13-CA13)/CA13*100 -> 0.011510543 | CY13: =F13+M13+S13+AE13+AK13+BC13+AW13+AQ13+BO13+BI13+BX13+CA13 -> 20132035 | CZ13: =CY13*3 -> 60396104 | DA13: =CZ13*0.7 -> 42277273
A14: 45804 | B14: =EDATE(B13,1) -> 45778 | C14: =sum('PROP DAILY PNL'!B227:B247) -> -824834 | D14: =Charges!H21 -> 496882 | E14: =C14-D14 -> -1321716 | F14: =I13-J13+K13 -> 6759900.8 | G14: =SUMIFS(Sheet!C:C,Sheet!A:A, ">="&B14,Sheet!A:A, "<="&EOMONTH(B14,0)) -> -227361.69 | H14: =Charges!I21+Charges!J21 -> 138353.18 | I14: =F14+G14-H14 -> 6394185.9 | J14: 150000 | K14: 29407 | L14: =(I14-F14)/F14*100 -> -5.4100626 | M14: =P13+Q13 -> 1460762.1 | N14: =SUMIFS(Sheet!D:D,Sheet!A:A, ">="&B14,Sheet!A:A, "<="&EOMONTH(B14,0)) -> -49131.098 | O14: =Charges!K21+Charges!L21 -> 29897.049 | P14: =M14+N14-O14 -> 1381734 | Q14: 0 | R14: =(P14-M14)/M14*100 -> -5.4100626 | S14: =V13+W13 -> 1207479 | T14: =SUMIFS(Sheet!E:E,Sheet!A:A, ">="&B14,Sheet!A:A, "<="&EOMONTH(B14,0)) -> -40612.202 | U14: =Charges!M21+Charges!N21 -> 24713.167 | V14: =S14+T14-U14 -> 1142153.6 | W14: 0 | X14: =(V14-S14)/S14*100 -> -5.4100626 | Z14: =SUMIFS(Sheet!F:F,Sheet!A:A, ">="&B14,Sheet!A:A, "<="&EOMONTH(B14,0)) -> 0 | AA14: =Charges!O21+Charges!P21 -> 0 | AB14: =Y14+Z14-AA14 -> 0 | AD14: =(AB14-Y14)/Y14*100 -> #DIV/0! | AE14: =AH13+AI13 -> 924061.26 | AF14: =SUMIFS(Sheet!G:G,Sheet!A:A, ">="&B14,Sheet!A:A, "<="&EOMONTH(B14,0)) -> -31079.765 | AG14: =Charges!R21+Charges!Q21 -> 18912.528 | AH14: =AE14+AF14-AG14 -> 874068.96 | AI14: 0 | AJ14: =(AH14-AE14)/AE14*100 -> -5.4100626 | AK14: =AN13+AO13 -> 8258714.7 | AL14: =SUMIFS(Sheet!H:H,Sheet!A:A, ">="&B14,Sheet!A:A, "<="&EOMONTH(B14,0)) -> -277460.48 | AM14: =Charges!T21+Charges!S21 -> 167218.69 | AN14: =AK14+AL14-AM14 -> 7814035.5 | AO14: 0 | AP14: =(AN14-AK14)/AK14*100 -> -5.3843629 | AQ14: =AT13+AU13 -> 825274.43 | AR14: =SUMIFS(Sheet!I:I,Sheet!A:A, ">="&B14,Sheet!A:A, "<="&EOMONTH(B14,0)) -> -27757.181 | AS14: =Charges!U21+Charges!V21 -> 16890.683 | AT14: =AQ14+AR14-AS14 -> 780626.57 | AU14: 0 | AV14: =(AT14-AQ14)/AQ14*100 -> -5.4100626 | AW14: =AZ13+BA13 -> 1650548.9 | AX14: =SUMIFS(Sheet!J:J,Sheet!A:A, ">="&B14,Sheet!A:A, "<="&EOMONTH(B14,0)) -> -55514.362 | AY14: =Charges!W21+Charges!X21 -> 33781.366 | AZ14: =AW14+AX14-AY14 -> 1561253.1 | BB14: =(AZ14-AW14)/AW14*100 -> -5.4100626 | BC14: =BF13+BG13 -> 825274.43 | BD14: =SUMIFS(Sheet!K:K,Sheet!A:A, ">="&B14,Sheet!A:A, "<="&EOMONTH(B14,0)) -> -27757.181 | BE14: =Charges!Y21+Charges!Z21 -> 16890.683 | BF14: =BC14+BD14-BE14 -> 780626.57 | BG14: 0 | BH14: =(BF14-BC14)/BC14*100 -> -5.4100626 | BI14: =BL13+BM13 -> 481594.37 | BJ14: =SUMIFS(Sheet!L:L,Sheet!A:A, ">="&B14,Sheet!A:A, "<="&EOMONTH(B14,0)) -> -16197.887 | BK14: =Charges!AA21+Charges!AB21 -> 9856.6701 | BL14: =BI14+BJ14-BK14 -> 455539.81 | BO14: =BR13+BS13 -> 481594.37 | BP14: =SUMIFS(Sheet!M:M,Sheet!A:A, ">="&B14,Sheet!A:A, "<="&EOMONTH(B14,0)) -> -16197.887 | BQ14: =Charges!AC21+Charges!AD21 -> 9856.6701 | BR14: =BO14+BP14-BQ14 -> 455539.81 | BU14: 0 | CA14: =CD13+CE13 -> 500057.55 | CB14: =SUMIFS(Sheet!O:O,Sheet!A:A, ">="&B14,Sheet!A:A, "<="&EOMONTH(B14,0)) -> -16818.875 | CC14: =Charges!AG21+Charges!AH21 -> 10234.551 | CD14: =CA14+CB14-CC14 -> 473004.13 | CE14: 0 | CF14: =(CD14-CA14)/CA14*100 -> -5.4100626 | CG14: 300000 | CH14: =SUMIFS(Sheet!P:P,Sheet!A:A, ">="&B14,Sheet!A:A, "<="&EOMONTH(B14,0)) -> -10033.983 | CI14: =Charges!AI21+Charges!AJ21 -> 5814.1667 | CJ14: =CG14+CH14-CI14 -> 284151.85 | CK14: 0 | CL14: =(CJ14-CG14)/CG14*100 -> -5.2827167 | CM14: 833333 | CN14: =SUMIFS(Sheet!Q:Q,Sheet!A:A, ">="&B14,Sheet!A:A, "<="&EOMONTH(B14,0)) -> -28911.41 | CO14: =Charges!AK21+Charges!AL21 -> 14465.796 | CP14: =CM14+CN14-CO14 -> 789955.79 | CQ14: 0 | CR14: =(CP14-CM14)/CM14*100 -> -5.2052668 | CY14: =F14+M14+S14+Y14+AE14+AK14+BC14+AW14+AQ14+CA14+BI14+BO14+CM14 -> 24208595 | CZ14: =CY14*3 -> 72625785 | DA14: =CZ14*0.83 -> 60279401
A15: 45836 | B15: =EDATE(B14,1) -> 45809 | F15: =I14-J14+K14 -> 6273592.9 | G15: =SUMIFS(Sheet!C:C,Sheet!A:A, ">="&B15,Sheet!A:A, "<="&EOMONTH(B15,0)) -> 84639.974 | H15: =Charges!I22+Charges!J22 -> 130076.42 | I15: =F15+G15-H15 -> 6228156.5 | J15: 150000 | K15: 37641 | L15: =(I15-F15)/F15*100 -> -0.72424918 | M15: =P14+Q14 -> 1381734 | N15: =SUMIFS(Sheet!D:D,Sheet!A:A, ">="&B15,Sheet!A:A, "<="&EOMONTH(B15,0)) -> 18641.619 | O15: =Charges!K22+Charges!L22 -> 28648.831 | P15: =M15+N15-O15 -> 1371726.8 | R15: =(P15-M15)/M15*100 -> -0.72425022 | S15: =V14+W14 -> 1142153.6 | T15: =SUMIFS(Sheet!E:E,Sheet!A:A, ">="&B15,Sheet!A:A, "<="&EOMONTH(B15,0)) -> 15409.328 | U15: =Charges!M22+Charges!N22 -> 23681.307 | V15: =S15+T15-U15 -> 1133881.6 | X15: =(V15-S15)/S15*100 -> -0.72424401 | Z15: =SUMIFS(Sheet!F:F,Sheet!A:A, ">="&B15,Sheet!A:A, "<="&EOMONTH(B15,0)) -> 0 | AA15: =Charges!O22+Charges!P22 -> 0 | AB15: =Y15+Z15-AA15 -> 0 | AD15: =(AB15-Y15)/Y15*100 -> #DIV/0! | AE15: =AH14+AI14 -> 874068.96 | AF15: =SUMIFS(Sheet!G:G,Sheet!A:A, ">="&B15,Sheet!A:A, "<="&EOMONTH(B15,0)) -> 11792.473 | AG15: =Charges!R22+Charges!Q22 -> 22216.153 | AH15: =AE15+AF15-AG15 -> 863645.28 | AJ15: =(AH15-AE15)/AE15*100 -> -1.1925466 | AK15: =AN14+AO14 -> 7814035.5 | AL15: =SUMIFS(Sheet!H:H,Sheet!A:A, ">="&B15,Sheet!A:A, "<="&EOMONTH(B15,0)) -> 105422.81 | AM15: =Charges!T22+Charges!S22 -> 160210.49 | AN15: =AK15+AL15-AM15 -> 7759247.8 | AP15: =(AN15-AK15)/AK15*100 -> -0.7011446 | AQ15: =AT14+AU14 -> 780626.57 | AR15: =SUMIFS(Sheet!I:I,Sheet!A:A, ">="&B15,Sheet!A:A, "<="&EOMONTH(B15,0)) -> 10531.798 | AS15: =Charges!U22+Charges!V22 -> 20910.183 | AT15: =AQ15+AR15-AS15 -> 770248.19 | AV15: =(AT15-AQ15)/AQ15*100 -> -1.3294942 | AW15: =AZ14+BA14 -> 1561253.1 | AX15: =SUMIFS(Sheet!J:J,Sheet!A:A, ">="&B15,Sheet!A:A, "<="&EOMONTH(B15,0)) -> 21063.596 | AY15: =Charges!W22+Charges!X22 -> 41820.366 | AZ15: =AW15+AX15-AY15 -> 1540496.4 | BB15: =(AZ15-AW15)/AW15*100 -> -1.3294942 | BC15: =BF14+BG14 -> 780626.57 | BD15: =SUMIFS(Sheet!K:K,Sheet!A:A, ">="&B15,Sheet!A:A, "<="&EOMONTH(B15,0)) -> 10531.798 | BE15: =Charges!Y22+Charges!Z22 -> 20910.183 | BF15: =BC15+BD15-BE15 -> 770248.19 | BH15: =(BF15-BC15)/BC15*100 -> -1.3294942 | BI15: =BL14+BM14 -> 455539.81 | BJ15: =SUMIFS(Sheet!L:L,Sheet!A:A, ">="&B15,Sheet!A:A, "<="&EOMONTH(B15,0)) -> 6145.9005 | BK15: =Charges!AA22+Charges!AB22 -> 11366.816 | BL15: =BI15+BJ15-BK15 -> 450318.9 | BO15: =BR14+BS14 -> 455539.81 | BP15: =SUMIFS(Sheet!M:M,Sheet!A:A, ">="&B15,Sheet!A:A, "<="&EOMONTH(B15,0)) -> 6145.9005 | BQ15: =Charges!AC22+Charges!AD22 -> 11366.816 | BR15: =BO15+BP15-BQ15 -> 450318.9 | CA15: =CD14+CE14 -> 473004.13 | CB15: =SUMIFS(Sheet!O:O,Sheet!A:A, ">="&B15,Sheet!A:A, "<="&EOMONTH(B15,0)) -> 6381.5197 | CC15: =Charges!AG22+Charges!AH22 -> 9807.2103 | CD15: =CA15+CB15-CC15 -> 469578.44 | CG15: =CJ14+CK14 -> 284151.85 | CH15: =SUMIFS(Sheet!P:P,Sheet!A:A, ">="&B15,Sheet!A:A, "<="&EOMONTH(B15,0)) -> 3833.6254 | CI15: =Charges!AI22+Charges!AJ22 -> 5891.6031 | CJ15: =CG15+CH15-CI15 -> 282093.87 | CK15: 0 | CL15: =(CJ15-CG15)/CG15*100 -> -0.72425278 | CM15: =CP14+CQ14 -> 789955.79 | CN15: =SUMIFS(Sheet!Q:Q,Sheet!A:A, ">="&B15,Sheet!A:A, "<="&EOMONTH(B15,0)) -> 10657.663 | CO15: =Charges!AK22+Charges!AL22 -> 21040.57 | CP15: =CM15+CN15-CO15 -> 779572.89 | CY15: =F15+M15+S15+AE15+AK15+BC15+AW15+AQ15+CA15+BI15+BO15+CM15+CG15 -> 23066283 | CZ15: =CY15*3 -> 69198848 | DA15: =CZ15*0.83 -> 57435044
A16: 45868 | B16: =EDATE(B15,1) -> 45839 | F16: =I15-J15+K15 -> 6115797.5 | G16: =SUMIFS(Sheet!C:C,Sheet!A:A, ">="&B16,Sheet!A:A, "<="&EOMONTH(B16,0)) -> 132180.62 | H16: =Charges!I23+Charges!J23 -> 161999.1 | I16: =F16+G16-H16 -> 6085979 | J16: 150000 | K16: 30900 | L16: =(I16-F16)/F16*100 -> -0.48756477 | M16: =P15+Q15 -> 1371726.8 | N16: =SUMIFS(Sheet!D:D,Sheet!A:A, ">="&B16,Sheet!A:A, "<="&EOMONTH(B16,0)) -> 28084.764 | O16: =Charges!K23+Charges!L23 -> 36087.183 | P16: =M16+N16-O16 -> 1363724.4 | R16: =(P16-M16)/M16*100 -> -0.58338291 | S16: =V15+W15 -> 1133881.6 | T16: =SUMIFS(Sheet!E:E,Sheet!A:A, ">="&B16,Sheet!A:A, "<="&EOMONTH(B16,0)) -> 23215.117 | U16: =Charges!M23+Charges!N23 -> 29830.102 | V16: =S16+T16-U16 -> 1127266.6 | X16: =(V16-S16)/S16*100 -> -0.58339288 | Z16: =SUMIFS(Sheet!F:F,Sheet!A:A, ">="&B16,Sheet!A:A, "<="&EOMONTH(B16,0)) -> 0 | AA16: =Charges!O23+Charges!P23 -> 0 | AB16: =Y16+Z16-AA16 -> 0 | AD16: =(AB16-Y16)/Y16*100 -> #DIV/0! | AE16: =AH15+AI15 -> 863645.28 | AF16: =SUMIFS(Sheet!G:G,Sheet!A:A, ">="&B16,Sheet!A:A, "<="&EOMONTH(B16,0)) -> 17682.292 | AG16: =Charges!R23+Charges!Q23 -> 25800.892 | AH16: =AE16+AF16-AG16 -> 855526.68 | AJ16: =(AH16-AE16)/AE16*100 -> -0.94003869 | AK16: =AN15+AO15 -> 7759247.8 | AL16: =SUMIFS(Sheet!H:H,Sheet!A:A, ">="&B16,Sheet!A:A, "<="&EOMONTH(B16,0)) -> 141803.35 | AM16: =Charges!T23+Charges!S23 -> 61704.387 | AN16: =AK16+AL16-AM16 -> 7839346.8 | AP16: =(AN16-AK16)/AK16*100 -> 1.0323032 | AQ16: =AT15+AU15 -> 770248.19 | AR16: =SUMIFS(Sheet!I:I,Sheet!A:A, ">="&B16,Sheet!A:A, "<="&EOMONTH(B16,0)) -> 0 | AS16: =Charges!U23+Charges!V23 -> 0 | AT16: =AQ16+AR16-AS16 -> 770248.19 | AV16: =(AT16-AQ16)/AQ16*100 -> 0 | AW16: =AZ15+BA15 -> 1540496.4 | AX16: =SUMIFS(Sheet!J:J,Sheet!A:A, ">="&B16,Sheet!A:A, "<="&EOMONTH(B16,0)) -> 31540.156 | AY16: =Charges!W23+Charges!X23 -> 48189.783 | AZ16: =AW16+AX16-AY16 -> 1523846.7 | BB16: =(AZ16-AW16)/AW16*100 -> -1.0807962 | BC16: =BF15+BG15 -> 770248.19 | BD16: =SUMIFS(Sheet!K:K,Sheet!A:A, ">="&B16,Sheet!A:A, "<="&EOMONTH(B16,0)) -> 14076.593 | BE16: =Charges!Y23+Charges!Z23 -> 7799.0661 | BF16: =BC16+BD16-BE16 -> 776525.71 | BH16: =(BF16-BC16)/BC16*100 -> 0.81500055 | BI16: =BL15+BM15 -> 450318.9 | BJ16: =SUMIFS(Sheet!L:L,Sheet!A:A, ">="&B16,Sheet!A:A, "<="&EOMONTH(B16,0)) -> 9219.8389 | BK16: =Charges!AA23+Charges!AB23 -> 13239.077 | BL16: =BI16+BJ16-BK16 -> 446299.66 | BM16: 416666 | BO16: =BR15+BS15 -> 450318.9 | BP16: =SUMIFS(Sheet!M:M,Sheet!A:A, ">="&B16,Sheet!A:A, "<="&EOMONTH(B16,0)) -> 9219.8389 | BQ16: =Charges!AC23+Charges!AD23 -> 13239.077 | BR16: =BO16+BP16-BQ16 -> 446299.66 | BS16: 416666 | CA16: =CD15+CE15 -> 469578.44 | CB16: =SUMIFS(Sheet!O:O,Sheet!A:A, ">="&B16,Sheet!A:A, "<="&EOMONTH(B16,0)) -> 9614.159 | CC16: =Charges!AG23+Charges!AH23 -> 12353.583 | CD16: =CA16+CB16-CC16 -> 466839.01 | CG16: =CJ15+CK15 -> 282093.87 | CH16: =SUMIFS(Sheet!P:P,Sheet!A:A, ">="&B16,Sheet!A:A, "<="&EOMONTH(B16,0)) -> 5775.596 | CI16: =Charges!AI23+Charges!AJ23 -> 7421.3008 | CJ16: =CG16+CH16-CI16 -> 280448.17 | CK16: 0 | CL16: =(CJ16-CG16)/CG16*100 -> -0.58338906 | CM16: =CP15+CQ15 -> 779572.89 | CN16: =SUMIFS(Sheet!Q:Q,Sheet!A:A, ">="&B16,Sheet!A:A, "<="&EOMONTH(B16,0)) -> 15960.992 | CO16: =Charges!AK23+Charges!AL23 -> 24263.193 | CP16: =CM16+CN16-CO16 -> 771270.69 | CY16: =F16+M16+S16+Y16+AE16+AK16+BC16+AW16+AQ16 -> 20325292
A17: 45900 | B17: =EDATE(B16,1) -> 45870 | F17: =I16-J16+K16 -> 5966879 | G17: =SUMIFS(Sheet!C:C,Sheet!A:A, ">="&B17,Sheet!A:A, "<="&EOMONTH(B17,0)) -> 185685.31 | H17: =Charges!I24+Charges!J24 -> 130307.05 | I17: =F17+G17-H17 -> 6022257.3 | J17: 150000 | K17: =24000+42433 -> 66433 | L17: =(I17-F17)/F17*100 -> 0.92809428 | M17: =P16+Q16 -> 1363724.4 | N17: =SUMIFS(Sheet!D:D,Sheet!A:A, ">="&B17,Sheet!A:A, "<="&EOMONTH(B17,0)) -> 42438.192 | O17: =Charges!K24+Charges!L24 -> 29777.258 | P17: =M17+N17-O17 -> 1376385.3 | R17: =(P17-M17)/M17*100 -> 0.92840856 | S17: =V16+W16 -> 1127266.6 | T17: =SUMIFS(Sheet!E:E,Sheet!A:A, ">="&B17,Sheet!A:A, "<="&EOMONTH(B17,0)) -> 35079.775 | U17: =Charges!M24+Charges!N24 -> 24614.078 | V17: =S17+T17-U17 -> 1137732.3 | X17: =(V17-S17)/S17*100 -> 0.92841361 | Z17: =SUMIFS(Sheet!F:F,Sheet!A:A, ">="&B17,Sheet!A:A, "<="&EOMONTH(B17,0)) -> 0 | AA17: =Charges!O24+Charges!P24 -> 0 | AB17: =Y17+Z17-AA17 -> 0 | AD17: =(AB17-Y17)/Y17*100 -> #DIV/0! | AE17: =AH16+AI16 -> 855526.68 | AF17: =SUMIFS(Sheet!G:G,Sheet!A:A, ">="&B17,Sheet!A:A, "<="&EOMONTH(B17,0)) -> 26623.405 | AG17: =Charges!R24+Charges!Q24 -> 21816.039 | AH17: =AE17+AF17-AG17 -> 860334.05 | AJ17: =(AH17-AE17)/AE17*100 -> 0.56191895 | AL17: =SUMIFS(Sheet!H:H,Sheet!A:A, ">="&B17,Sheet!A:A, "<="&EOMONTH(B17,0)) -> 0 | AM17: =Charges!T24+Charges!S24 -> 0 | AN17: =AK17+AL17-AM17 -> 0 | AP17: =(AN17-AK17)/AK17*100 -> #DIV/0! | AR17: =SUMIFS(Sheet!I:I,Sheet!A:A, ">="&B17,Sheet!A:A, "<="&EOMONTH(B17,0)) -> 0 | AS17: =Charges!U24+Charges!V24 -> 0 | AT17: =AQ17+AR17-AS17 -> 0 | AV17: =(AT17-AQ17)/AQ17*100 -> #DIV/0! | AX17: =SUMIFS(Sheet!J:J,Sheet!A:A, ">="&B17,Sheet!A:A, "<="&EOMONTH(B17,0)) -> 0 | AY17: =Charges!W24+Charges!X24 -> 0 | AZ17: =AW17+AX17-AY17 -> 0 | BB17: =(AZ17-AW17)/AW17*100 -> #DIV/0! | BD17: =SUMIFS(Sheet!K:K,Sheet!A:A, ">="&B17,Sheet!A:A, "<="&EOMONTH(B17,0)) -> 0 | BE17: =Charges!Y24+Charges!Z24 -> 0 | BF17: =BC17+BD17-BE17 -> 0 | BH17: =(BF17-BC17)/BC17*100 -> #DIV/0! | BI17: =BL16+BM16 -> 862965.66 | BJ17: =SUMIFS(Sheet!L:L,Sheet!A:A, ">="&B17,Sheet!A:A, "<="&EOMONTH(B17,0)) -> 26854.902 | BK17: =Charges!AA24+Charges!AB24 -> 21918.669 | BL17: =BI17+BJ17-BK17 -> 867901.89 | BO17: =BR16+BS16 -> 862965.66 | BP17: =SUMIFS(Sheet!M:M,Sheet!A:A, ">="&B17,Sheet!A:A, "<="&EOMONTH(B17,0)) -> 26854.902 | BQ17: =Charges!AC24+Charges!AD24 -> 21918.669 | BR17: =BO17+BP17-BQ17 -> 867901.89 | CA17: =CD16+CE16 -> 466839.01 | CB17: =SUMIFS(Sheet!O:O,Sheet!A:A, ">="&B17,Sheet!A:A, "<="&EOMONTH(B17,0)) -> 14527.722 | CC17: =Charges!AG24+Charges!AH24 -> 10193.501 | CD17: =CA17+CB17-CC17 -> 471173.23 | CG17: =CJ16+CK16 -> 280448.17 | CH17: =SUMIFS(Sheet!P:P,Sheet!A:A, ">="&B17,Sheet!A:A, "<="&EOMONTH(B17,0)) -> 8727.3569 | CI17: =Charges!AI24+Charges!AJ24 -> 6123.6668 | CJ17: =CG17+CH17-CI17 -> 283051.86 | CK17: 0 | CL17: =(CJ17-CG17)/CG17*100 -> 0.92840331 | CM17: =CP16+CQ16 -> 771270.69 | CN17: =SUMIFS(Sheet!Q:Q,Sheet!A:A, ">="&B17,Sheet!A:A, "<="&EOMONTH(B17,0)) -> 24001.435 | CO17: =Charges!AK24+Charges!AL24 -> 20653.632 | CP17: =CM17+CN17-CO17 -> 774618.49 | CY17: =F17+M17+S17+Y17+AE17+AK17+BC17+AW17+AQ17 -> 9313396.7
A18: Sept-25 | B18: =EDATE(B17,1) -> 45901 | F18: =I17-J17+K17 -> 5938690.3 | G18: =SUMIFS(Sheet!C:C,Sheet!A:A, ">="&B18,Sheet!A:A, "<="&EOMONTH(B18,0)) -> 294709.49 | H18: =Charges!I25+Charges!J25 -> 191489.5 | I18: =F18+G18-H18 -> 6041910.2 | J18: 150000 | K18: =16000+148337 -> 164337 | L18: =(I18-F18)/F18*100 -> 1.7380935 | M18: =P17+Q17 -> 1376385.3 | N18: =SUMIFS(Sheet!D:D,Sheet!A:A, ">="&B18,Sheet!A:A, "<="&EOMONTH(B18,0)) -> 68303.581 | O18: =Charges!K25+Charges!L25 -> 44182.909 | P18: =M18+N18-O18 -> 1400506 | R18: =(P18-M18)/M18*100 -> 1.7524651 | S18: =V17+W17 -> 1137732.3 | T18: =SUMIFS(Sheet!E:E,Sheet!A:A, ">="&B18,Sheet!A:A, "<="&EOMONTH(B18,0)) -> 56460.348 | U18: =Charges!M25+Charges!N25 -> 36538.631 | V18: =S18+T18-U18 -> 1157654.1 | X18: =(V18-S18)/S18*100 -> 1.7510021 | Z18: =SUMIFS(Sheet!F:F,Sheet!A:A, ">="&B18,Sheet!A:A, "<="&EOMONTH(B18,0)) -> 0 | AA18: =Charges!O25+Charges!P25 -> 0 | AB18: =Y18+Z18-AA18 -> 0 | AD18: =(AB18-Y18)/Y18*100 -> #DIV/0! | AE18: =AH17+AI17 -> 860334.05 | AF18: =SUMIFS(Sheet!G:G,Sheet!A:A, ">="&B18,Sheet!A:A, "<="&EOMONTH(B18,0)) -> 42694.365 | AG18: =Charges!R25+Charges!Q25 -> 31452.618 | AH18: =AE18+AF18-AG18 -> 871575.8 | AJ18: =(AH18-AE18)/AE18*100 -> 1.3066723 | AL18: =SUMIFS(Sheet!H:H,Sheet!A:A, ">="&B18,Sheet!A:A, "<="&EOMONTH(B18,0)) -> 0 | AM18: =Charges!T25+Charges!S25 -> 0 | AN18: =AK18+AL18-AM18 -> 0 | AP18: =(AN18-AK18)/AK18*100 -> #DIV/0! | AR18: =SUMIFS(Sheet!I:I,Sheet!A:A, ">="&B18,Sheet!A:A, "<="&EOMONTH(B18,0)) -> 0 | AS18: =Charges!U25+Charges!V25 -> 0 | AT18: =AQ18+AR18-AS18 -> 0 | AV18: =(AT18-AQ18)/AQ18*100 -> #DIV/0! | AX18: =SUMIFS(Sheet!J:J,Sheet!A:A, ">="&B18,Sheet!A:A, "<="&EOMONTH(B18,0)) -> 0 | AY18: =Charges!W25+Charges!X25 -> 0 | AZ18: =AW18+AX18-AY18 -> 0 | BB18: =(AZ18-AW18)/AW18*100 -> #DIV/0! | BD18: =SUMIFS(Sheet!K:K,Sheet!A:A, ">="&B18,Sheet!A:A, "<="&EOMONTH(B18,0)) -> 0 | BE18: =Charges!Y25+Charges!Z25 -> 0 | BF18: =BC18+BD18-BE18 -> 0 | BH18: =(BF18-BC18)/BC18*100 -> #DIV/0! | BI18: =BL17+BM17 -> 867901.89 | BJ18: =SUMIFS(Sheet!L:L,Sheet!A:A, ">="&B18,Sheet!A:A, "<="&EOMONTH(B18,0)) -> 43069.922 | BK18: =Charges!AA25+Charges!AB25 -> 31618.981 | BL18: =BI18+BJ18-BK18 -> 879352.83 | BO18: =BR17+BS17 -> 867901.89 | BP18: =SUMIFS(Sheet!M:M,Sheet!A:A, ">="&B18,Sheet!A:A, "<="&EOMONTH(B18,0)) -> 43069.922 | BQ18: =Charges!AC25+Charges!AD25 -> 31618.981 | BR18: =BO18+BP18-BQ18 -> 879352.83 | CA18: =CD17+CE17 -> 471173.23 | CB18: =SUMIFS(Sheet!O:O,Sheet!A:A, ">="&B18,Sheet!A:A, "<="&EOMONTH(B18,0)) -> 23382.129 | CC18: =Charges!AG25+Charges!AH25 -> 15131.743 | CD18: =CA18+CB18-CC18 -> 479423.62 | CG18: =CJ17+CK17 -> 283051.86 | CH18: =SUMIFS(Sheet!P:P,Sheet!A:A, ">="&B18,Sheet!A:A, "<="&EOMONTH(B18,0)) -> 14046.543 | CI18: =Charges!AI25+Charges!AJ25 -> 9082.2943 | CJ18: =CG18+CH18-CI18 -> 288016.11 | CK18: 0 | CL18: =(CJ18-CG18)/CG18*100 -> 1.7538301 | CM18: =CP17+CQ17 -> 774618.49 | CN18: =SUMIFS(Sheet!Q:Q,Sheet!A:A, ">="&B18,Sheet!A:A, "<="&EOMONTH(B18,0)) -> 38440.702 | CO18: =Charges!AK25+Charges!AL25 -> 29568.343 | CP18: =CM18+CN18-CO18 -> 783490.85 | CY18: =F18+M18+S18+Y18+AE18+AK18+BC18+AW18+AQ18 -> 9313141.9
A19: 45932 | B19: =EDATE(B18,1) -> 45931 | F19: =I18-J18+K18 -> 6056247.2 | G19: =SUMIFS(Sheet!C:C,Sheet!A:A, ">="&B19,Sheet!A:A, "<="&EOMONTH(B19,0)) -> 442208.55 | H19: =Charges!I26+Charges!J26 -> 140809.68 | I19: =F19+G19-H19 -> 6357646.1 | J19: 150000 | K19: =110536+2711-150000 -> -36753 | L19: =(I19-F19)/F19*100 -> 4.9766605 | M19: =P18+Q18 -> 1400506 | N19: =SUMIFS(Sheet!D:D,Sheet!A:A, ">="&B19,Sheet!A:A, "<="&EOMONTH(B19,0)) -> 102260.64 | O19: =Charges!K26+Charges!L26 -> 29771.927 | P19: =M19+N19-O19 -> 1472994.7 | Q19: -326 | R19: =(P19-M19)/M19*100 -> 5.1758945 | S19: =V18+W18 -> 1157654.1 | T19: =SUMIFS(Sheet!E:E,Sheet!A:A, ">="&B19,Sheet!A:A, "<="&EOMONTH(B19,0)) -> 84528.339 | U19: =Charges!M26+Charges!N26 -> 23922.652 | V19: =S19+T19-U19 -> 1218259.7 | W19: -113 | X19: =(V19-S19)/S19*100 -> 5.2352157 | Z19: =SUMIFS(Sheet!F:F,Sheet!A:A, ">="&B19,Sheet!A:A, "<="&EOMONTH(B19,0)) -> 0 | AA19: =Charges!O26+Charges!P26 -> 0 | AB19: =Y19+Z19-AA19 -> 0 | AD19: =(AB19-Y19)/Y19*100 -> #DIV/0! | AE19: =AH18+AI18 -> 871575.8 | AF19: =SUMIFS(Sheet!G:G,Sheet!A:A, ">="&B19,Sheet!A:A, "<="&EOMONTH(B19,0)) -> 63639.784 | AG19: =Charges!R26+Charges!Q26 -> 35451.812 | AH19: =AE19+AF19-AG19 -> 899763.77 | AJ19: =(AH19-AE19)/AE19*100 -> 3.2341389 | AL19: =SUMIFS(Sheet!H:H,Sheet!A:A, ">="&B19,Sheet!A:A, "<="&EOMONTH(B19,0)) -> 0 | AM19: =Charges!T26+Charges!S26 -> 0 | AN19: =AK19+AL19-AM19 -> 0 | AP19: =(AN19-AK19)/AK19*100 -> #DIV/0! | AR19: =SUMIFS(Sheet!I:I,Sheet!A:A, ">="&B19,Sheet!A:A, "<="&EOMONTH(B19,0)) -> 0 | AS19: =Charges!U26+Charges!V26 -> 0 | AT19: =AQ19+AR19-AS19 -> 0 | AV19: =(AT19-AQ19)/AQ19*100 -> #DIV/0! | AX19: =SUMIFS(Sheet!J:J,Sheet!A:A, ">="&B19,Sheet!A:A, "<="&EOMONTH(B19,0)) -> 0 | AY19: =Charges!W26+Charges!X26 -> 0 | AZ19: =AW19+AX19-AY19 -> 0 | BB19: =(AZ19-AW19)/AW19*100 -> #DIV/0! | BD19: =SUMIFS(Sheet!K:K,Sheet!A:A, ">="&B19,Sheet!A:A, "<="&EOMONTH(B19,0)) -> 0 | BE19: =Charges!Y26+Charges!Z26 -> 0 | BF19: =BC19+BD19-BE19 -> 0 | BH19: =(BF19-BC19)/BC19*100 -> #DIV/0! | BI19: =BL18+BM18 -> 879352.83 | BJ19: =SUMIFS(Sheet!L:L,Sheet!A:A, ">="&B19,Sheet!A:A, "<="&EOMONTH(B19,0)) -> 47814.755 | BK19: =Charges!AA26+Charges!AB26 -> 21929.42 | BL19: =BI19+BJ19-BK19 -> 905238.17 | BO19: =BR18+BS18 -> 879352.83 | BP19: =SUMIFS(Sheet!M:M,Sheet!A:A, ">="&B19,Sheet!A:A, "<="&EOMONTH(B19,0)) -> 47814.755 | BQ19: =Charges!AC26+Charges!AD26 -> 21929.42 | BR19: =BO19+BP19-BQ19 -> 905238.17 | CA19: =CD18+CE18 -> 479423.62 | CB19: =SUMIFS(Sheet!O:O,Sheet!A:A, ">="&B19,Sheet!A:A, "<="&EOMONTH(B19,0)) -> 35006.038 | CC19: =Charges!AG26+Charges!AH26 -> 10232.273 | CD19: =CA19+CB19-CC19 -> 504197.38 | CE19: -1242 | CG19: =CJ18+CK18 -> 288016.11 | CH19: =SUMIFS(Sheet!P:P,Sheet!A:A, ">="&B19,Sheet!A:A, "<="&EOMONTH(B19,0)) -> 21030.05 | CI19: =Charges!AI26+Charges!AJ26 -> 5617.743 | CJ19: =CG19+CH19-CI19 -> 303428.41 | CK19: -1029 | CL19: =(CJ19-CG19)/CG19*100 -> 5.3511963 | CM19: =CP18+CQ18 -> 783490.85 | CN19: =SUMIFS(Sheet!Q:Q,Sheet!A:A, ">="&B19,Sheet!A:A, "<="&EOMONTH(B19,0)) -> 57208.092 | CO19: =Charges!AK26+Charges!AL26 -> 24115.722 | CP19: =CM19+CN19-CO19 -> 816583.22 | CY19: =F19+M19+S19+Y19+AE19+AK19+BC19+AW19+AQ19 -> 9485983.1
A20: 45964 | B20: =EDATE(B19,1) -> 45962 | F20: =I19-J19+K19 -> 6170893.1 | G20: =SUMIFS(Sheet!C:C,Sheet!A:A, ">="&B20,Sheet!A:A, "<="&EOMONTH(B20,0)) -> -218576.12 | H20: =Charges!I27+Charges!J27 -> 53365.396 | I20: =F20+G20-H20 -> 5898951.6 | J20: 150000 | K20: 0 | L20: =(I20-F20)/F20*100 -> -4.4068421 | M20: =P19+Q19 -> 1472668.7 | N20: =SUMIFS(Sheet!D:D,Sheet!A:A, ">="&B20,Sheet!A:A, "<="&EOMONTH(B20,0)) -> -52162.661 | O20: =Charges!K27+Charges!L27 -> 12735.522 | P20: =M20+N20-O20 -> 1407770.5 | R20: =(P20-M20)/M20*100 -> -4.4068421 | S20: =V19+W19 -> 1218146.7 | T20: =SUMIFS(Sheet!E:E,Sheet!A:A, ">="&B20,Sheet!A:A, "<="&EOMONTH(B20,0)) -> -43147.367 | U20: =Charges!M27+Charges!N27 -> 10534.437 | V20: =S20+T20-U20 -> 1164464.9 | W20: -100000 | X20: =(V20-S20)/S20*100 -> -4.4068421 | Z20: =SUMIFS(Sheet!F:F,Sheet!A:A, ">="&B20,Sheet!A:A, "<="&EOMONTH(B20,0)) -> 0 | AA20: =Charges!O27+Charges!P27 -> 0 | AB20: =Y20+Z20-AA20 -> 0 | AD20: =(AB20-Y20)/Y20*100 -> #DIV/0! | AE20: =AH19+AI19 -> 899763.77 | AF20: =SUMIFS(Sheet!G:G,Sheet!A:A, ">="&B20,Sheet!A:A, "<="&EOMONTH(B20,0)) -> 0 | AG20: =Charges!R27+Charges!Q27 -> 0 | AH20: =AE20+AF20-AG20 -> 899763.77 | AJ20: =(AH20-AE20)/AE20*100 -> 0 | AL20: =SUMIFS(Sheet!H:H,Sheet!A:A, ">="&B20,Sheet!A:A, "<="&EOMONTH(B20,0)) -> 0 | AM20: =Charges!T27+Charges!S27 -> 0 | AN20: =AK20+AL20-AM20 -> 0 | AP20: =(AN20-AK20)/AK20*100 -> #DIV/0! | AR20: =SUMIFS(Sheet!I:I,Sheet!A:A, ">="&B20,Sheet!A:A, "<="&EOMONTH(B20,0)) -> 0 | AS20: =Charges!U27+Charges!V27 -> 0 | AT20: =AQ20+AR20-AS20 -> 0 | AV20: =(AT20-AQ20)/AQ20*100 -> #DIV/0! | AX20: =SUMIFS(Sheet!J:J,Sheet!A:A, ">="&B20,Sheet!A:A, "<="&EOMONTH(B20,0)) -> 0 | AY20: =Charges!W27+Charges!X27 -> 0 | AZ20: =AW20+AX20-AY20 -> 0 | BB20: =(AZ20-AW20)/AW20*100 -> #DIV/0! | BD20: =SUMIFS(Sheet!K:K,Sheet!A:A, ">="&B20,Sheet!A:A, "<="&EOMONTH(B20,0)) -> 0 | BE20: =Charges!Y27+Charges!Z27 -> 0 | BF20: =BC20+BD20-BE20 -> 0 | BH20: =(BF20-BC20)/BC20*100 -> #DIV/0! | BI20: =BL19+BM19 -> 905238.17 | BJ20: =SUMIFS(Sheet!L:L,Sheet!A:A, ">="&B20,Sheet!A:A, "<="&EOMONTH(B20,0)) -> 0 | BK20: =Charges!AA27+Charges!AB27 -> 0 | BL20: =BI20+BJ20-BK20 -> 905238.17 | BO20: =BR19+BS19 -> 905238.17 | BP20: =SUMIFS(Sheet!M:M,Sheet!A:A, ">="&B20,Sheet!A:A, "<="&EOMONTH(B20,0)) -> 0 | BQ20: =Charges!AC27+Charges!AD27 -> 0 | BR20: =BO20+BP20-BQ20 -> 905238.17 | CA20: =CD19+CE19 -> 502955.38 | CB20: =SUMIFS(Sheet!O:O,Sheet!A:A, ">="&B20,Sheet!A:A, "<="&EOMONTH(B20,0)) -> -17814.931 | CC20: =Charges!AG27+Charges!AH27 -> 4349.5184 | CD20: =CA20+CB20-CC20 -> 480790.93 | CG20: =CJ19+CK19 -> 302399.41 | CH20: =SUMIFS(Sheet!P:P,Sheet!A:A, ">="&B20,Sheet!A:A, "<="&EOMONTH(B20,0)) -> -10711.138 | CI20: =Charges!AI27+Charges!AJ27 -> 2615.1262 | CJ20: =CG20+CH20-CI20 -> 289073.15 | CK20: 0 | CL20: =(CJ20-CG20)/CG20*100 -> -4.4068421 | CM20: =CP19+CQ19 -> 816583.22 | CN20: =SUMIFS(Sheet!Q:Q,Sheet!A:A, ">="&B20,Sheet!A:A, "<="&EOMONTH(B20,0)) -> -28923.786 | CO20: =Charges!AK27+Charges!AL27 -> 12502 | CP20: =CM20+CN20-CO20 -> 775157.43 | CY20: =F20+M20+S20+Y20+AE20+AK20+BC20+AW20+AQ20 -> 9761472.3
A21: 45996 | B21: =EDATE(B20,1) -> 45992 | F21: =I20-J20+K20 -> 5748951.6 | G21: =SUMIFS(Sheet!C:C,Sheet!A:A, ">="&B21,Sheet!A:A, "<="&EOMONTH(B21,0)) -> 409332.39 | H21: =Charges!I28+Charges!J28 -> 0 | I21: =F21+G21-H21 -> 6158284 | J21: 150000 | L21: =(I21-F21)/F21*100 -> 7.1201224 | M21: =P20+Q20 -> 1407770.5 | N21: =SUMIFS(Sheet!D:D,Sheet!A:A, ">="&B21,Sheet!A:A, "<="&EOMONTH(B21,0)) -> 100234.98 | O21: =Charges!K28+Charges!L28 -> 0 | P21: =M21+N21-O21 -> 1508005.5 | R21: =(P21-M21)/M21*100 -> 7.1201224 | S21: =V20+W20 -> 1064464.9 | T21: =SUMIFS(Sheet!E:E,Sheet!A:A, ">="&B21,Sheet!A:A, "<="&EOMONTH(B21,0)) -> 75791.207 | U21: =Charges!M28+Charges!N28 -> 0 | V21: =S21+T21-U21 -> 1140256.1 | X21: =(V21-S21)/S21*100 -> 7.1201224 | Z21: =SUMIFS(Sheet!F:F,Sheet!A:A, ">="&B21,Sheet!A:A, "<="&EOMONTH(B21,0)) -> 0 | AA21: =Charges!O28+Charges!P28 -> 0 | AB21: =Y21+Z21-AA21 -> 0 | AD21: =(AB21-Y21)/Y21*100 -> #DIV/0! | AE21: =AH20+AI20 -> 899763.77 | AF21: =SUMIFS(Sheet!G:G,Sheet!A:A, ">="&B21,Sheet!A:A, "<="&EOMONTH(B21,0)) -> 0 | AG21: =Charges!R28+Charges!Q28 -> 0 | AH21: =AE21+AF21-AG21 -> 899763.77 | AJ21: =(AH21-AE21)/AE21*100 -> 0 | AL21: =SUMIFS(Sheet!H:H,Sheet!A:A, ">="&B21,Sheet!A:A, "<="&EOMONTH(B21,0)) -> 0 | AM21: =Charges!T28+Charges!S28 -> 0 | AN21: =AK21+AL21-AM21 -> 0 | AP21: =(AN21-AK21)/AK21*100 -> #DIV/0! | AR21: =SUMIFS(Sheet!I:I,Sheet!A:A, ">="&B21,Sheet!A:A, "<="&EOMONTH(B21,0)) -> 0 | AS21: =Charges!U28+Charges!V28 -> 0 | AT21: =AQ21+AR21-AS21 -> 0 | AV21: =(AT21-AQ21)/AQ21*100 -> #DIV/0! | AX21: =SUMIFS(Sheet!J:J,Sheet!A:A, ">="&B21,Sheet!A:A, "<="&EOMONTH(B21,0)) -> 0 | AY21: =Charges!W28+Charges!X28 -> 0 | AZ21: =AW21+AX21-AY21 -> 0 | BB21: =(AZ21-AW21)/AW21*100 -> #DIV/0! | BD21: =SUMIFS(Sheet!K:K,Sheet!A:A, ">="&B21,Sheet!A:A, "<="&EOMONTH(B21,0)) -> 0 | BE21: =Charges!Y28+Charges!Z28 -> 0 | BF21: =BC21+BD21-BE21 -> 0 | BH21: =(BF21-BC21)/BC21*100 -> #DIV/0! | BI21: =BL20+BM20 -> 905238.17 | BO21: =BR20+BS20 -> 905238.17 | CA21: =CD20+CE20 -> 480790.93 | CG21: =CJ20+CK20 -> 289073.15 | CH21: =SUMIFS(Sheet!P:P,Sheet!A:A, ">="&B21,Sheet!A:A, "<="&EOMONTH(B21,0)) -> 20582.362 | CI21: =Charges!AI28+Charges!AJ28 -> 0 | CJ21: =CG21+CH21-CI21 -> 309655.51 | CK21: 0 | CL21: =(CJ21-CG21)/CG21*100 -> 7.1201224 | CM21: =CP20+CQ20 -> 775157.43 | CN21: =SUMIFS(Sheet!Q:Q,Sheet!A:A, ">="&B21,Sheet!A:A, "<="&EOMONTH(B21,0)) -> 55192.158 | CO21: =Charges!AK28+Charges!AL28 -> 0 | CP21: =CM21+CN21-CO21 -> 830349.59 | CY21: =F21+M21+S21+Y21+AE21+AK21+BC21+AW21+AQ21 -> 9120950.8
AP22: =(AN22-AK22)/AK22*100 -> #DIV/0!

Sheet Clients Prop charges bifurcatio
A1: Date | B1: Prop charges | C1: Abhishek S | D1: Radhika | E1: KARAN | F1: Pavan | G1: Rasul | H1: SIVA | I1: RAVI | J1: MAHESH | K1: JAGADISH | L1: Bharghav | M1: Kaushik | N1: MAHESH A | O1: Aayushi A | P1: Dishant | Q1: BHARATH | R1: NARESH
C2: =Charges!J18 -> 24780.4 | D2: =Charges!L18 -> 5681.4111 | E2: =Charges!N18 -> 7038.1884 | F2: =Charges!P18 -> 16075.808 | G2: =Charges!R18 -> 4822.7413 | H2: =Charges!T18 -> 16666.67
A3: No. of days | B3: =count(A4:A23) -> 20 | C3: =C2/$B$3 -> 1239.02 | D3: =D2/$B$3 -> 284.07056 | E3: =E2/$B$3 -> 351.90942 | F3: =F2/$B$3 -> 803.79039 | G3: =G2/$B$3 -> 241.13706 | H3: =H2/18 -> 925.92611
A4: 45689 | C4: =$C$3 -> 1239.02 | D4: =D$3 -> 284.07056 | E4: =E$3 -> 351.90942 | F4: =F$3 -> 803.79039 | G4: =G$3 -> 241.13706 | H4: 0
A5: 45691 | C5: =$C$3 -> 1239.02 | D5: =D$3 -> 284.07056 | E5: =E$3 -> 351.90942 | F5: =F$3 -> 803.79039 | G5: =G$3 -> 241.13706 | H5: 0
A6: 45692 | C6: =$C$3 -> 1239.02 | D6: =D$3 -> 284.07056 | E6: =E$3 -> 351.90942 | F6: =F$3 -> 803.79039 | G6: =G$3 -> 241.13706 | H6: =H$3 -> 925.92611 | X6: 62.1 | Y6: 8248226 | Z6: Opening BAL
A7: 45693 | C7: =$C$3 -> 1239.02 | D7: =D$3 -> 284.07056 | E7: =E$3 -> 351.90942 | F7: =F$3 -> 803.79039 | G7: =G$3 -> 241.13706 | H7: =H$3 -> 925.92611 | Y7: 10000000 | Z7: PROP CLIENTS
A8: 45694 | C8: =$C$3 -> 1239.02 | D8: =D$3 -> 284.07056 | E8: =E$3 -> 351.90942 | F8: =F$3 -> 803.79039 | G8: =G$3 -> 241.13706 | H8: =H$3 -> 925.92611 | Y8: 0 | Z8: FUNDS ADDED
A9: 45695 | C9: =$C$3 -> 1239.02 | D9: =D$3 -> 284.07056 | E9: =E$3 -> 351.90942 | F9: =F$3 -> 803.79039 | G9: =G$3 -> 241.13706 | H9: =H$3 -> 925.92611 | Y9: =SUM(Y6:Y8) -> 18248226
A10: 45698 | C10: =$C$3 -> 1239.02 | D10: =D$3 -> 284.07056 | E10: =E$3 -> 351.90942 | F10: =F$3 -> 803.79039 | G10: =G$3 -> 241.13706 | H10: =H$3 -> 925.92611 | AB10: =SUM(Y6:Y9) -> 36496452 | AC10: total
A11: 45699 | C11: =$C$3 -> 1239.02 | D11: =D$3 -> 284.07056 | E11: =E$3 -> 351.90942 | F11: =F$3 -> 803.79039 | G11: =G$3 -> 241.13706 | H11: =H$3 -> 925.92611 | Y11: =AB11-Y9 -> 41751774 | AB11: 60000000 | AC11: leverage
A12: 45700 | C12: =$C$3 -> 1239.02 | D12: =D$3 -> 284.07056 | E12: =E$3 -> 351.90942 | F12: =F$3 -> 803.79039 | G12: =G$3 -> 241.13706 | H12: =H$3 -> 925.92611 | Y12: =Y11*0.4/100 -> 167007.1 | AB12: =AB11-AB10 -> 23503548 | AC12: Difference | AD12: Leverage factor | AE12: 0.004
A13: 45701 | C13: =$C$3 -> 1239.02 | D13: =D$3 -> 284.07056 | E13: =E$3 -> 351.90942 | F13: =F$3 -> 803.79039 | G13: =G$3 -> 241.13706 | H13: =H$3 -> 925.92611 | Y13: =Y12/21 -> 7952.7189 | AB13: =AB12*0.4% -> 94014.192 | AC13: Interest
A14: 45702 | C14: =$C$3 -> 1239.02 | D14: =D$3 -> 284.07056 | E14: =E$3 -> 351.90942 | F14: =F$3 -> 803.79039 | G14: =G$3 -> 241.13706 | H14: =H$3 -> 925.92611 | AB14: =73118/19 -> 3848.3158 | AC14: Per day interest
A15: 45705 | C15: =$C$3 -> 1239.02 | D15: =D$3 -> 284.07056 | E15: =E$3 -> 351.90942 | F15: =F$3 -> 803.79039 | G15: =G$3 -> 241.13706 | H15: =H$3 -> 925.92611
A16: 45706 | C16: =$C$3 -> 1239.02 | D16: =D$3 -> 284.07056 | E16: =E$3 -> 351.90942 | F16: =F$3 -> 803.79039 | G16: =G$3 -> 241.13706 | H16: =H$3 -> 925.92611
A17: 45707 | C17: =$C$3 -> 1239.02 | D17: =D$3 -> 284.07056 | E17: =E$3 -> 351.90942 | F17: =F$3 -> 803.79039 | G17: =G$3 -> 241.13706 | H17: =H$3 -> 925.92611 | AB17: 73118.375
A18: 45708 | C18: =$C$3 -> 1239.02 | D18: =D$3 -> 284.07056 | E18: =E$3 -> 351.90942 | F18: =F$3 -> 803.79039 | G18: =G$3 -> 241.13706 | H18: =H$3 -> 925.92611
A19: 45709 | C19: =$C$3 -> 1239.02 | D19: =D$3 -> 284.07056 | E19: =E$3 -> 351.90942 | F19: =F$3 -> 803.79039 | G19: =G$3 -> 241.13706 | H19: =H$3 -> 925.92611
A20: 45712 | C20: =$C$3 -> 1239.02 | D20: =D$3 -> 284.07056 | E20: =E$3 -> 351.90942 | F20: =F$3 -> 803.79039 | G20: =G$3 -> 241.13706 | H20: =H$3 -> 925.92611
A21: 45713 | C21: =$C$3 -> 1239.02 | D21: =D$3 -> 284.07056 | E21: =E$3 -> 351.90942 | F21: =F$3 -> 803.79039 | G21: =G$3 -> 241.13706 | H21: =H$3 -> 925.92611
A22: 45715 | C22: =$C$3 -> 1239.02 | D22: =D$3 -> 284.07056 | E22: =E$3 -> 351.90942 | F22: =F$3 -> 803.79039 | G22: =G$3 -> 241.13706 | H22: =H$3 -> 925.92611
A23: 45716 | C23: =$C$3 -> 1239.02 | D23: =D$3 -> 284.07056 | E23: =E$3 -> 351.90942 | F23: =F$3 -> 803.79039 | G23: =G$3 -> 241.13706 | H23: =H$3 -> 925.92611
A24: 45719 | B24: 3848.32 | C24: =B24*'Clients Balance'!C195/'Clients Balance'!B195 -> 1794.569 | D24: =B24*'Clients Balance'!D195/'Clients Balance'!B195 -> 362.85916 | E24: =B24*'Clients Balance'!E195/'Clients Balance'!B195 -> 369.07579 | F24: =B24*'Clients Balance'!F195/'Clients Balance'!B195 -> 589.94901 | G24: =B24*'Clients Balance'!G195/'Clients Balance'!B195 -> 176.98478 | H24: =B24*'Clients Balance'!H195/'Clients Balance'!B195 -> 554.88227
A25: 45720 | B25: 3848.32 | C25: =B25*'Clients Balance'!C196/'Clients Balance'!B196 -> 1794.3959 | D25: =B25*'Clients Balance'!D196/'Clients Balance'!B196 -> 362.84459 | E25: =B25*'Clients Balance'!E196/'Clients Balance'!B196 -> 369.34988 | F25: =B25*'Clients Balance'!F196/'Clients Balance'!B196 -> 589.9332 | G25: =B25*'Clients Balance'!G196/'Clients Balance'!B196 -> 176.9677 | H25: =B25*'Clients Balance'!H196/'Clients Balance'!B196 -> 554.82874
A26: 45721 | B26: 3848.32 | C26: =B26*'Clients Balance'!C197/'Clients Balance'!B197 -> 1746.3851 | D26: =B26*'Clients Balance'!D197/'Clients Balance'!B197 -> 353.13648 | E26: =B26*'Clients Balance'!E197/'Clients Balance'!B197 -> 359.46492 | F26: =B26*'Clients Balance'!F197/'Clients Balance'!B197 -> 574.14912 | G26: =B26*'Clients Balance'!G197/'Clients Balance'!B197 -> 275.20062 | H26: =B26*'Clients Balance'!H197/'Clients Balance'!B197 -> 539.98377
A27: 45722 | B27: 3848.32 | C27: =B27*'Clients Balance'!C198/'Clients Balance'!B198 -> 1746.3851 | D27: =B27*'Clients Balance'!D198/'Clients Balance'!B198 -> 353.13648 | E27: =B27*'Clients Balance'!E198/'Clients Balance'!B198 -> 359.46492 | F27: =B27*'Clients Balance'!F198/'Clients Balance'!B198 -> 574.14912 | G27: =B27*'Clients Balance'!G198/'Clients Balance'!B198 -> 275.20062 | H27: =B27*'Clients Balance'!H198/'Clients Balance'!B198 -> 539.98377
A28: 45723 | B28: 3848.32 | C28: =B28*'Clients Balance'!C199/'Clients Balance'!B199 -> 1746.3851 | D28: =B28*'Clients Balance'!D199/'Clients Balance'!B199 -> 353.13648 | E28: =B28*'Clients Balance'!E199/'Clients Balance'!B199 -> 359.46492 | F28: =B28*'Clients Balance'!F199/'Clients Balance'!B199 -> 574.14912 | G28: =B28*'Clients Balance'!G199/'Clients Balance'!B199 -> 275.20062 | H28: =B28*'Clients Balance'!H199/'Clients Balance'!B199 -> 539.98377
A29: 45726 | B29: 3848.32 | C29: =B29*'Clients Balance'!C200/'Clients Balance'!B200 -> 1746.3851 | D29: =B29*'Clients Balance'!D200/'Clients Balance'!B200 -> 353.13648 | E29: =B29*'Clients Balance'!E200/'Clients Balance'!B200 -> 359.46492 | F29: =B29*'Clients Balance'!F200/'Clients Balance'!B200 -> 574.14912 | G29: =B29*'Clients Balance'!G200/'Clients Balance'!B200 -> 275.20062 | H29: =B29*'Clients Balance'!H200/'Clients Balance'!B200 -> 539.98377
A30: 45727 | B30: 3848.32 | C30: =B30*'Clients Balance'!C201/'Clients Balance'!B201 -> 1746.3851 | D30: =B30*'Clients Balance'!D201/'Clients Balance'!B201 -> 353.13648 | E30: =B30*'Clients Balance'!E201/'Clients Balance'!B201 -> 359.46492 | F30: =B30*'Clients Balance'!F201/'Clients Balance'!B201 -> 574.14912 | G30: =B30*'Clients Balance'!G201/'Clients Balance'!B201 -> 275.20062 | H30: =B30*'Clients Balance'!H201/'Clients Balance'!B201 -> 539.98377
A31: 45728 | B31: 3848.32 | C31: =B31*'Clients Balance'!C202/'Clients Balance'!B202 -> 1746.3851 | D31: =B31*'Clients Balance'!D202/'Clients Balance'!B202 -> 353.13648 | E31: =B31*'Clients Balance'!E202/'Clients Balance'!B202 -> 359.46492 | F31: =B31*'Clients Balance'!F202/'Clients Balance'!B202 -> 574.14912 | G31: =B31*'Clients Balance'!G202/'Clients Balance'!B202 -> 275.20062 | H31: =B31*'Clients Balance'!H202/'Clients Balance'!B202 -> 539.98377
A32: 45729 | B32: 3848.32 | C32: =B32*'Clients Balance'!C203/'Clients Balance'!B203 -> 1746.3851 | D32: =B32*'Clients Balance'!D203/'Clients Balance'!B203 -> 353.13648 | E32: =B32*'Clients Balance'!E203/'Clients Balance'!B203 -> 359.46492 | F32: =B32*'Clients Balance'!F203/'Clients Balance'!B203 -> 574.14912 | G32: =B32*'Clients Balance'!G203/'Clients Balance'!B203 -> 275.20062 | H32: =B32*'Clients Balance'!H203/'Clients Balance'!B203 -> 539.98377
A33: 45733 | B33: 3848.32 | C33: =B33*'Clients Balance'!C204/'Clients Balance'!B204 -> 1746.3851 | D33: =B33*'Clients Balance'!D204/'Clients Balance'!B204 -> 353.13648 | E33: =B33*'Clients Balance'!E204/'Clients Balance'!B204 -> 359.46492 | F33: =B33*'Clients Balance'!F204/'Clients Balance'!B204 -> 574.14912 | G33: =B33*'Clients Balance'!G204/'Clients Balance'!B204 -> 275.20062 | H33: =B33*'Clients Balance'!H204/'Clients Balance'!B204 -> 539.98377
A34: 45734 | B34: 3848.32 | C34: =B34*'Clients Balance'!C205/'Clients Balance'!B205 -> 1746.3851 | D34: =B34*'Clients Balance'!D205/'Clients Balance'!B205 -> 353.13648 | E34: =B34*'Clients Balance'!E205/'Clients Balance'!B205 -> 359.46492 | F34: =B34*'Clients Balance'!F205/'Clients Balance'!B205 -> 574.14912 | G34: =B34*'Clients Balance'!G205/'Clients Balance'!B205 -> 275.20062 | H34: =B34*'Clients Balance'!H205/'Clients Balance'!B205 -> 539.98377
A35: 45735 | B35: 3848.32 | C35: =B35*'Clients Balance'!C206/'Clients Balance'!B206 -> 1746.3851 | D35: =B35*'Clients Balance'!D206/'Clients Balance'!B206 -> 353.13648 | E35: =B35*'Clients Balance'!E206/'Clients Balance'!B206 -> 359.46492 | F35: =B35*'Clients Balance'!F206/'Clients Balance'!B206 -> 574.14912 | G35: =B35*'Clients Balance'!G206/'Clients Balance'!B206 -> 275.20062 | H35: =B35*'Clients Balance'!H206/'Clients Balance'!B206 -> 539.98377
... A42: 45744 | B42: 3848.32 | C42: =B42*'Clients Balance'!C213/'Clients Balance'!B213 -> 1746.3851 | D42: =B42*'Clients Balance'!D213/'Clients Balance'!B213 -> 353.13648 | E42: =B42*'Clients Balance'!E213/'Clients Balance'!B213 -> 359.46492 | F42: =B42*'Clients Balance'!F213/'Clients Balance'!B213 -> 574.14912 | G42: =B42*'Clients Balance'!G213/'Clients Balance'!B213 -> 275.20062 | H42: =B42*'Clients Balance'!H213/'Clients Balance'!B213 -> 539.98377
A43: ='PROP DAILY PNL'!A208 -> 45748 | B43: 5826.32 | C43: =$B43*'PERCENTAGE SHARING'!C2 -> 2135.0005 | D43: =$B43*'PERCENTAGE SHARING'!D2 -> 340.89522 | E43: =$B43*'PERCENTAGE SHARING'!E2 -> 332.01519 | F43: =$B43*'PERCENTAGE SHARING'!F2 -> 0 | G43: =$B43*'PERCENTAGE SHARING'!G2 -> 290.12622 | H43: =$B43*'PERCENTAGE SHARING'!H2 -> 1389.4308 | I43: =$B43*'PERCENTAGE SHARING'!I2 -> 259.11026 | J43: =$B43*'PERCENTAGE SHARING'!J2 -> 518.22052 | ... R43: =$B43*'PERCENTAGE SHARING'!R2 -> 0
A44: ='PROP DAILY PNL'!A209 -> 45749 | B44: 5826.32 | C44: =$B44*'PERCENTAGE SHARING'!C3 -> 2041.5426 | D44: =$B44*'PERCENTAGE SHARING'!D3 -> 325.9728 | E44: =$B44*'PERCENTAGE SHARING'!E3 -> 317.48149 | F44: =$B44*'PERCENTAGE SHARING'!F3 -> 0 | G44: =$B44*'PERCENTAGE SHARING'!G3 -> 277.42617 | H44: =$B44*'PERCENTAGE SHARING'!H3 -> 1328.6096 | I44: =$B44*'PERCENTAGE SHARING'!I3 -> 247.76791 | J44: =$B44*'PERCENTAGE SHARING'!J3 -> 495.53582 | ... R44: =$B44*'PERCENTAGE SHARING'!R3 -> 0
A45: ='PROP DAILY PNL'!A210 -> 45750 | B45: 5826.32 | C45: =$B45*'PERCENTAGE SHARING'!C4 -> 2041.5426 | D45: =$B45*'PERCENTAGE SHARING'!D4 -> 325.9728 | E45: =$B45*'PERCENTAGE SHARING'!E4 -> 317.48149 | F45: =$B45*'PERCENTAGE SHARING'!F4 -> 0 | G45: =$B45*'PERCENTAGE SHARING'!G4 -> 277.42617 | H45: =$B45*'PERCENTAGE SHARING'!H4 -> 1328.6096 | I45: =$B45*'PERCENTAGE SHARING'!I4 -> 247.76791 | J45: =$B45*'PERCENTAGE SHARING'!J4 -> 495.53582 | ... R45: =$B45*'PERCENTAGE SHARING'!R4 -> 0
A46: ='PROP DAILY PNL'!A211 -> 45751 | B46: 5826.32 | C46: =$B46*'PERCENTAGE SHARING'!C5 -> 2041.5426 | D46: =$B46*'PERCENTAGE SHARING'!D5 -> 325.9728 | E46: =$B46*'PERCENTAGE SHARING'!E5 -> 317.48149 | F46: =$B46*'PERCENTAGE SHARING'!F5 -> 0 | G46: =$B46*'PERCENTAGE SHARING'!G5 -> 277.42617 | H46: =$B46*'PERCENTAGE SHARING'!H5 -> 1328.6096 | I46: =$B46*'PERCENTAGE SHARING'!I5 -> 247.76791 | J46: =$B46*'PERCENTAGE SHARING'!J5 -> 495.53582 | ... R46: =$B46*'PERCENTAGE SHARING'!R5 -> 0
A47: ='PROP DAILY PNL'!A212 -> 45754 | B47: 5826.32 | C47: =$B47*'PERCENTAGE SHARING'!C6 -> 2041.5426 | D47: =$B47*'PERCENTAGE SHARING'!D6 -> 325.9728 | E47: =$B47*'PERCENTAGE SHARING'!E6 -> 317.48149 | F47: =$B47*'PERCENTAGE SHARING'!F6 -> 0 | G47: =$B47*'PERCENTAGE SHARING'!G6 -> 277.42617 | H47: =$B47*'PERCENTAGE SHARING'!H6 -> 1328.6096 | I47: =$B47*'PERCENTAGE SHARING'!I6 -> 247.76791 | J47: =$B47*'PERCENTAGE SHARING'!J6 -> 495.53582 | ... R47: =$B47*'PERCENTAGE SHARING'!R6 -> 0
A48: ='PROP DAILY PNL'!A213 -> 45755 | B48: 5826.32 | C48: =$B48*'PERCENTAGE SHARING'!C7 -> 1990.5244 | D48: =$B48*'PERCENTAGE SHARING'!D7 -> 317.82674 | E48: =$B48*'PERCENTAGE SHARING'!E7 -> 309.54763 | F48: =$B48*'PERCENTAGE SHARING'!F7 -> 0 | G48: =$B48*'PERCENTAGE SHARING'!G7 -> 270.49329 | H48: =$B48*'PERCENTAGE SHARING'!H7 -> 1295.4076 | I48: =$B48*'PERCENTAGE SHARING'!I7 -> 241.57619 | J48: =$B48*'PERCENTAGE SHARING'!J7 -> 483.15238 | ... R48: =$B48*'PERCENTAGE SHARING'!R7 -> 0
A49: ='PROP DAILY PNL'!A214 -> 45756 | B49: 5826.32 | C49: =$B49*'PERCENTAGE SHARING'!C8 -> 1990.5244 | D49: =$B49*'PERCENTAGE SHARING'!D8 -> 317.82674 | E49: =$B49*'PERCENTAGE SHARING'!E8 -> 309.54763 | F49: =$B49*'PERCENTAGE SHARING'!F8 -> 0 | G49: =$B49*'PERCENTAGE SHARING'!G8 -> 270.49329 | H49: =$B49*'PERCENTAGE SHARING'!H8 -> 1295.4076 | I49: =$B49*'PERCENTAGE SHARING'!I8 -> 241.57619 | J49: =$B49*'PERCENTAGE SHARING'!J8 -> 483.15238 | ... R49: =$B49*'PERCENTAGE SHARING'!R8 -> 0
A50: ='PROP DAILY PNL'!A215 -> 45758 | B50: 5826.32 | C50: =$B50*'PERCENTAGE SHARING'!C9 -> 1990.5244 | D50: =$B50*'PERCENTAGE SHARING'!D9 -> 317.82674 | E50: =$B50*'PERCENTAGE SHARING'!E9 -> 309.54763 | F50: =$B50*'PERCENTAGE SHARING'!F9 -> 0 | G50: =$B50*'PERCENTAGE SHARING'!G9 -> 270.49329 | H50: =$B50*'PERCENTAGE SHARING'!H9 -> 1295.4076 | I50: =$B50*'PERCENTAGE SHARING'!I9 -> 241.57619 | J50: =$B50*'PERCENTAGE SHARING'!J9 -> 483.15238 | ... R50: =$B50*'PERCENTAGE SHARING'!R9 -> 0
A51: ='PROP DAILY PNL'!A216 -> 45762 | B51: 5826.32 | C51: =$B51*'PERCENTAGE SHARING'!C10 -> 1990.5244 | D51: =$B51*'PERCENTAGE SHARING'!D10 -> 317.82674 | E51: =$B51*'PERCENTAGE SHARING'!E10 -> 309.54763 | F51: =$B51*'PERCENTAGE SHARING'!F10 -> 0 | G51: =$B51*'PERCENTAGE SHARING'!G10 -> 270.49329 | H51: =$B51*'PERCENTAGE SHARING'!H10 -> 1295.4076 | I51: =$B51*'PERCENTAGE SHARING'!I10 -> 241.57619 | J51: =$B51*'PERCENTAGE SHARING'!J10 -> 483.15238 | ... R51: =$B51*'PERCENTAGE SHARING'!R10 -> 0
A52: ='PROP DAILY PNL'!A217 -> 45763 | B52: 5826.32 | C52: =$B52*'PERCENTAGE SHARING'!C11 -> 1990.5244 | D52: =$B52*'PERCENTAGE SHARING'!D11 -> 317.82674 | E52: =$B52*'PERCENTAGE SHARING'!E11 -> 309.54763 | F52: =$B52*'PERCENTAGE SHARING'!F11 -> 0 | G52: =$B52*'PERCENTAGE SHARING'!G11 -> 270.49329 | H52: =$B52*'PERCENTAGE SHARING'!H11 -> 1295.4076 | I52: =$B52*'PERCENTAGE SHARING'!I11 -> 241.57619 | J52: =$B52*'PERCENTAGE SHARING'!J11 -> 483.15238 | ... R52: =$B52*'PERCENTAGE SHARING'!R11 -> 0
A53: ='PROP DAILY PNL'!A218 -> 45764 | B53: 5826.32 | C53: =$B53*'PERCENTAGE SHARING'!C12 -> 1990.5244 | D53: =$B53*'PERCENTAGE SHARING'!D12 -> 317.82674 | E53: =$B53*'PERCENTAGE SHARING'!E12 -> 309.54763 | F53: =$B53*'PERCENTAGE SHARING'!F12 -> 0 | G53: =$B53*'PERCENTAGE SHARING'!G12 -> 270.49329 | H53: =$B53*'PERCENTAGE SHARING'!H12 -> 1295.4076 | I53: =$B53*'PERCENTAGE SHARING'!I12 -> 241.57619 | J53: =$B53*'PERCENTAGE SHARING'!J12 -> 483.15238 | ... R53: =$B53*'PERCENTAGE SHARING'!R12 -> 0
A54: ='PROP DAILY PNL'!A219 -> 45768 | B54: 5826.32 | C54: =$B54*'PERCENTAGE SHARING'!C13 -> 1990.5244 | D54: =$B54*'PERCENTAGE SHARING'!D13 -> 317.82674 | E54: =$B54*'PERCENTAGE SHARING'!E13 -> 309.54763 | F54: =$B54*'PERCENTAGE SHARING'!F13 -> 0 | G54: =$B54*'PERCENTAGE SHARING'!G13 -> 270.49329 | H54: =$B54*'PERCENTAGE SHARING'!H13 -> 1295.4076 | I54: =$B54*'PERCENTAGE SHARING'!I13 -> 241.57619 | J54: =$B54*'PERCENTAGE SHARING'!J13 -> 483.15238 | ... R54: =$B54*'PERCENTAGE SHARING'!R13 -> 0
... A82: ='PROP DAILY PNL'!A247 -> 45807 | B82: 7318 | C82: =$B82*'PERCENTAGE SHARING'!C41 -> 2018.4768 | D82: =$B82*'PERCENTAGE SHARING'!D41 -> 436.17719 | E82: =$B82*'PERCENTAGE SHARING'!E41 -> 360.54794 | F82: =$B82*'PERCENTAGE SHARING'!F41 -> 0 | G82: =$B82*'PERCENTAGE SHARING'!G41 -> 275.92065 | H82: =$B82*'PERCENTAGE SHARING'!H41 -> 2466.1123 | I82: =$B82*'PERCENTAGE SHARING'!I41 -> 246.42334 | J82: =$B82*'PERCENTAGE SHARING'!J41 -> 492.84668 | ... R82: =$B82*'PERCENTAGE SHARING'!R41 -> 0
A83: ='PROP DAILY PNL'!A248 -> 45810 | C83: 2018.83 | D83: 444.64 | E83: 367.54 | F83: =$B83*'PERCENTAGE SHARING'!$F$42 -> 0 | G83: 476.19 | H83: 2428.57 | I83: 476.19 | J83: 952.38 | K83: 476.19 | L83: 238.1 | M83: 238.1 | N83: =$B83*'PERCENTAGE SHARING'!N42 -> 0 | O83: 152.21 | P83: 91.44 | Q83: 476.19 | R83: =$B83*'PERCENTAGE SHARING'!$R$42 -> 0
A84: ='PROP DAILY PNL'!A249 -> 45811 | C84: 2018.83 | D84: 444.64 | E84: 367.54 | F84: =$B84*'PERCENTAGE SHARING'!$F$42 -> 0 | G84: 476.19 | H84: 2428.57 | I84: 476.19 | J84: 952.38 | K84: 476.19 | L84: 238.1 | M84: 238.1 | N84: =$B84*'PERCENTAGE SHARING'!N43 -> 0 | O84: 152.21 | P84: 91.44 | Q84: 476.19 | R84: =$B84*'PERCENTAGE SHARING'!$R$42 -> 0
A85: ='PROP DAILY PNL'!A250 -> 45812 | C85: 2018.83 | D85: 444.64 | E85: 367.54 | F85: =$B85*'PERCENTAGE SHARING'!$F$42 -> 0 | G85: 476.19 | H85: 2428.57 | I85: 476.19 | J85: 952.38 | K85: 476.19 | L85: 238.1 | M85: 238.1 | N85: =$B85*'PERCENTAGE SHARING'!N44 -> 0 | O85: 152.21 | P85: 91.44 | Q85: 476.19 | R85: =$B85*'PERCENTAGE SHARING'!$R$42 -> 0
A86: ='PROP DAILY PNL'!A251 -> 45813 | C86: 2018.83 | D86: 444.64 | E86: 367.54 | F86: =$B86*'PERCENTAGE SHARING'!$F$42 -> 0 | G86: 476.19 | H86: 2428.57 | I86: 476.19 | J86: 952.38 | K86: 476.19 | L86: 238.1 | M86: 238.1 | N86: =$B86*'PERCENTAGE SHARING'!N45 -> 0 | O86: 152.21 | P86: 91.44 | Q86: 476.19 | R86: =$B86*'PERCENTAGE SHARING'!$R$42 -> 0
A87: ='PROP DAILY PNL'!A252 -> 45814 | C87: 2018.83 | D87: 444.64 | E87: 367.54 | F87: =$B87*'PERCENTAGE SHARING'!$F$42 -> 0 | G87: 476.19 | H87: 2428.57 | I87: 476.19 | J87: 952.38 | K87: 476.19 | L87: 238.1 | M87: 238.1 | N87: =$B87*'PERCENTAGE SHARING'!N46 -> 0 | O87: 152.21 | P87: 91.44 | Q87: 476.19 | R87: =$B87*'PERCENTAGE SHARING'!$R$42 -> 0
A88: ='PROP DAILY PNL'!A253 -> 45817 | C88: 2018.83 | D88: 444.64 | E88: 367.54 | F88: =$B88*'PERCENTAGE SHARING'!$F$42 -> 0 | G88: 476.19 | H88: 2428.57 | I88: 476.19 | J88: 952.38 | K88: 476.19 | L88: 238.1 | M88: 238.1 | N88: =$B88*'PERCENTAGE SHARING'!N47 -> 0 | O88: 152.21 | P88: 91.44 | Q88: 476.19 | R88: =$B88*'PERCENTAGE SHARING'!$R$42 -> 0
A89: ='PROP DAILY PNL'!A254 -> 45818 | C89: 2018.83 | D89: 444.64 | E89: 367.54 | F89: =$B89*'PERCENTAGE SHARING'!$F$42 -> 0 | G89: 476.19 | H89: 2428.57 | I89: 476.19 | J89: 952.38 | K89: 476.19 | L89: 238.1 | M89: 238.1 | N89: =$B89*'PERCENTAGE SHARING'!N48 -> 0 | O89: 152.21 | P89: 91.44 | Q89: 476.19 | R89: =$B89*'PERCENTAGE SHARING'!$R$42 -> 0
A90: ='PROP DAILY PNL'!A255 -> 45819 | C90: 2018.83 | D90: 444.64 | E90: 367.54 | F90: =$B90*'PERCENTAGE SHARING'!$F$42 -> 0 | G90: 476.19 | H90: 2428.57 | I90: 476.19 | J90: 952.38 | K90: 476.19 | L90: 238.1 | M90: 238.1 | N90: =$B90*'PERCENTAGE SHARING'!N49 -> 0 | O90: 152.21 | P90: 91.44 | Q90: 476.19 | R90: =$B90*'PERCENTAGE SHARING'!$R$42 -> 0
A91: ='PROP DAILY PNL'!A256 -> 45820 | C91: 2018.83 | D91: 444.64 | E91: 367.54 | F91: =$B91*'PERCENTAGE SHARING'!$F$42 -> 0 | G91: 476.19 | H91: 2428.57 | I91: 476.19 | J91: 952.38 | K91: 476.19 | L91: 238.1 | M91: 238.1 | N91: =$B91*'PERCENTAGE SHARING'!N50 -> 0 | O91: 152.21 | P91: 91.44 | Q91: 476.19 | R91: =$B91*'PERCENTAGE SHARING'!$R$42 -> 0
A92: ='PROP DAILY PNL'!A257 -> 45821 | C92: 2018.83 | D92: 444.64 | E92: 367.54 | F92: =$B92*'PERCENTAGE SHARING'!$F$42 -> 0 | G92: 476.19 | H92: 2428.57 | I92: 476.19 | J92: 952.38 | K92: 476.19 | L92: 238.1 | M92: 238.1 | N92: =$B92*'PERCENTAGE SHARING'!N51 -> 0 | O92: 152.21 | P92: 91.44 | Q92: 476.19 | R92: =$B92*'PERCENTAGE SHARING'!$R$42 -> 0
A93: ='PROP DAILY PNL'!A258 -> 45824 | C93: 2018.83 | D93: 444.64 | E93: 367.54 | F93: =$B93*'PERCENTAGE SHARING'!$F$42 -> 0 | G93: 476.19 | H93: 2428.57 | I93: 476.19 | J93: 952.38 | K93: 476.19 | L93: 238.1 | M93: 238.1 | N93: =$B93*'PERCENTAGE SHARING'!N52 -> 0 | O93: 152.21 | P93: 91.44 | Q93: 476.19 | R93: =$B93*'PERCENTAGE SHARING'!$R$42 -> 0
A94: ='PROP DAILY PNL'!A259 -> 45825 | C94: 2018.83 | D94: 444.64 | E94: 367.54 | F94: =$B94*'PERCENTAGE SHARING'!$F$42 -> 0 | G94: 476.19 | H94: 2428.57 | I94: 476.19 | J94: 952.38 | K94: 476.19 | L94: 238.1 | M94: 238.1 | N94: =$B94*'PERCENTAGE SHARING'!N53 -> 0 | O94: 152.21 | P94: 91.44 | Q94: 476.19 | R94: =$B94*'PERCENTAGE SHARING'!$R$42 -> 0
... A103: ='PROP DAILY PNL'!A268 -> 45838 | C103: 2018.83 | D103: 444.64 | E103: 367.54 | F103: =$B103*'PERCENTAGE SHARING'!$F$42 -> 0 | G103: 476.19 | H103: 2428.57 | I103: 476.19 | J103: 952.38 | K103: 476.19 | L103: 238.1 | M103: 238.1 | N103: =$B103*'PERCENTAGE SHARING'!N62 -> 0 | O103: 152.21 | P103: 91.44 | Q103: 476.19 | R103: =$B103*'PERCENTAGE SHARING'!$R$42 -> 0
A104: ='PROP DAILY PNL'!A269 -> 45839 | C104: 2169.64 | D104: 477.85 | E104: 395 | F104: =$B104*'PERCENTAGE SHARING'!F63 -> 0 | G104: 434.78 | H104: 4456 | I104: =$B104*'PERCENTAGE SHARING'!I63 -> 0 | J104: 869.8 | K104: 681.45 | L104: 217.4 | M104: 217.4 | N104: =$B104*'PERCENTAGE SHARING'!N63 -> 0 | O104: 163.58 | P104: 98.27 | Q104: 434.8 | R104: 434.8
A105: ='PROP DAILY PNL'!A270 -> 45840 | C105: 2169.64 | D105: 477.85 | E105: 395 | F105: =$B105*'PERCENTAGE SHARING'!F64 -> 0 | G105: 434.78 | H105: 4456 | I105: =$B105*'PERCENTAGE SHARING'!I64 -> 0 | J105: 869.8 | K105: 681.45 | L105: 217.4 | M105: 217.4 | N105: =$B105*'PERCENTAGE SHARING'!N64 -> 0 | O105: 163.58 | P105: 98.27 | Q105: 434.8 | R105: 434.8
A106: ='PROP DAILY PNL'!A271 -> 45841 | C106: 2169.64 | D106: 477.85 | E106: 395 | F106: =$B106*'PERCENTAGE SHARING'!F65 -> 0 | G106: 434.78 | H106: 4456 | I106: =$B106*'PERCENTAGE SHARING'!I65 -> 0 | J106: 869.8 | K106: 681.45 | L106: 217.4 | M106: 217.4 | N106: =$B106*'PERCENTAGE SHARING'!N65 -> 0 | O106: 163.58 | P106: 98.27 | Q106: 434.8 | R106: 434.8
A107: ='PROP DAILY PNL'!A272 -> 45842 | C107: 2169.64 | D107: 477.85 | E107: 395 | F107: =$B107*'PERCENTAGE SHARING'!F66 -> 0 | G107: 434.78 | H107: 4456 | I107: =$B107*'PERCENTAGE SHARING'!I66 -> 0 | J107: 869.8 | K107: 681.45 | L107: 217.4 | M107: 217.4 | N107: =$B107*'PERCENTAGE SHARING'!N66 -> 0 | O107: 163.58 | P107: 98.27 | Q107: 434.8 | R107: 434.8
A108: ='PROP DAILY PNL'!A273 -> 45845 | C108: 2169.64 | D108: 477.85 | E108: 395 | F108: =$B108*'PERCENTAGE SHARING'!F67 -> 0 | G108: 434.78 | H108: 4456 | I108: =$B108*'PERCENTAGE SHARING'!I67 -> 0 | J108: 869.8 | K108: 681.45 | L108: 217.4 | M108: 217.4 | N108: =$B108*'PERCENTAGE SHARING'!N67 -> 0 | O108: 163.58 | P108: 98.27 | Q108: 434.8 | R108: 434.8
A109: ='PROP DAILY PNL'!A274 -> 45846 | C109: 2169.64 | D109: 477.85 | E109: 395 | F109: =$B109*'PERCENTAGE SHARING'!F68 -> 0 | G109: 434.78 | H109: 4456 | I109: =$B109*'PERCENTAGE SHARING'!I68 -> 0 | J109: 869.8 | K109: 681.45 | L109: 217.4 | M109: 217.4 | N109: =$B109*'PERCENTAGE SHARING'!N68 -> 0 | O109: 163.58 | P109: 98.27 | Q109: 434.8 | R109: 434.8
A110: ='PROP DAILY PNL'!A275 -> 45847 | C110: 2169.64 | D110: 477.85 | E110: 395 | F110: =$B110*'PERCENTAGE SHARING'!F69 -> 0 | G110: 434.78 | H110: 4456 | I110: =$B110*'PERCENTAGE SHARING'!I69 -> 0 | J110: 869.8 | K110: 681.45 | L110: 217.4 | M110: 217.4 | N110: =$B110*'PERCENTAGE SHARING'!N69 -> 0 | O110: 163.58 | P110: 98.27 | Q110: 434.8 | R110: 434.8
A111: ='PROP DAILY PNL'!A276 -> 45848 | C111: 2169.64 | D111: 477.85 | E111: 395 | F111: =$B111*'PERCENTAGE SHARING'!F70 -> 0 | G111: 434.78 | H111: 0 | I111: =$B111*'PERCENTAGE SHARING'!I70 -> 0 | J111: 869.8 | K111: 0 | L111: 217.4 | M111: 217.4 | N111: =$B111*'PERCENTAGE SHARING'!N70 -> 0 | O111: 163.58 | P111: 98.27 | Q111: 434.8 | R111: 434.8
A112: ='PROP DAILY PNL'!A277 -> 45849 | C112: 2169.64 | D112: 477.85 | E112: 395 | F112: =$B112*'PERCENTAGE SHARING'!F71 -> 0 | G112: 434.78 | H112: 0 | I112: =$B112*'PERCENTAGE SHARING'!I71 -> 0 | J112: 869.8 | K112: 0 | L112: 217.4 | M112: 217.4 | N112: =$B112*'PERCENTAGE SHARING'!N71 -> 0 | O112: 163.58 | P112: 98.27 | Q112: 434.8 | R112: 434.8
A113: ='PROP DAILY PNL'!A278 -> 45852 | C113: 2169.64 | D113: 477.85 | E113: 395 | F113: =$B113*'PERCENTAGE SHARING'!F72 -> 0 | G113: 434.78 | H113: 0 | I113: =$B113*'PERCENTAGE SHARING'!I72 -> 0 | J113: 869.8 | K113: 0 | L113: 217.4 | M113: 217.4 | N113: =$B113*'PERCENTAGE SHARING'!N72 -> 0 | O113: 163.58 | P113: 98.27 | Q113: 434.8 | R113: 434.8
A114: ='PROP DAILY PNL'!A279 -> 45853 | C114: 2169.64 | D114: 477.85 | E114: 395 | F114: =$B114*'PERCENTAGE SHARING'!F73 -> 0 | G114: 434.78 | H114: 0 | I114: =$B114*'PERCENTAGE SHARING'!I73 -> 0 | J114: 869.8 | K114: 0 | L114: 217.4 | M114: 217.4 | N114: =$B114*'PERCENTAGE SHARING'!N73 -> 0 | O114: 163.58 | P114: 98.27 | Q114: 434.8 | R114: 434.8
A115: ='PROP DAILY PNL'!A280 -> 45854 | C115: 2169.64 | D115: 477.85 | E115: 395 | F115: =$B115*'PERCENTAGE SHARING'!F74 -> 0 | G115: 434.78 | H115: 0 | I115: =$B115*'PERCENTAGE SHARING'!I74 -> 0 | J115: 869.8 | K115: 0 | L115: 217.4 | M115: 217.4 | N115: =$B115*'PERCENTAGE SHARING'!N74 -> 0 | O115: 163.58 | P115: 98.27 | Q115: 434.8 | R115: 434.8
... A126: ='PROP DAILY PNL'!A291 -> 45869 | C126: 2169.64 | D126: 477.85 | E126: 395 | F126: =$B126*'PERCENTAGE SHARING'!F85 -> 0 | G126: 434.78 | H126: 0 | I126: =$B126*'PERCENTAGE SHARING'!I85 -> 0 | J126: 869.8 | K126: 0 | L126: 217.4 | M126: 217.4 | N126: =$B126*'PERCENTAGE SHARING'!N85 -> 0 | O126: 163.58 | P126: 98.27 | Q126: 434.8 | R126: 434.8
A127: ='PROP DAILY PNL'!A292 -> 45870 | C127: 2525.61 | D127: 577 | E127: 476.95 | F127: =$B127*'PERCENTAGE SHARING'!F86 -> 0 | G127: 527 | H127: =$B127*'PERCENTAGE SHARING'!H86 -> 0 | I127: =$B127*'PERCENTAGE SHARING'!I86 -> 0 | J127: =$B127*'PERCENTAGE SHARING'!J86 -> 0 | K127: =$B127*'PERCENTAGE SHARING'!K86 -> 0 | L127: 527 | M127: 527 | N127: =$B127*'PERCENTAGE SHARING'!N86 -> 0 | O127: 197.52 | P127: 118.66 | Q127: 527 | R127: =$B127*'PERCENTAGE SHARING'!R86 -> 0
A128: ='PROP DAILY PNL'!A293 -> 45873 | C128: 2525.61 | D128: 577 | E128: 476.95 | F128: =$B128*'PERCENTAGE SHARING'!F87 -> 0 | G128: 527 | H128: =$B128*'PERCENTAGE SHARING'!H87 -> 0 | I128: =$B128*'PERCENTAGE SHARING'!I87 -> 0 | J128: =$B128*'PERCENTAGE SHARING'!J87 -> 0 | K128: =$B128*'PERCENTAGE SHARING'!K87 -> 0 | L128: 527 | M128: 527 | N128: =$B128*'PERCENTAGE SHARING'!N87 -> 0 | O128: 197.52 | P128: 118.66 | Q128: 527 | R128: =$B128*'PERCENTAGE SHARING'!R87 -> 0
A129: ='PROP DAILY PNL'!A294 -> 45874 | C129: 2525.61 | D129: 577 | E129: 476.95 | F129: =$B129*'PERCENTAGE SHARING'!F88 -> 0 | G129: 527 | H129: =$B129*'PERCENTAGE SHARING'!H88 -> 0 | I129: =$B129*'PERCENTAGE SHARING'!I88 -> 0 | J129: =$B129*'PERCENTAGE SHARING'!J88 -> 0 | K129: =$B129*'PERCENTAGE SHARING'!K88 -> 0 | L129: 527 | M129: 527 | N129: =$B129*'PERCENTAGE SHARING'!N88 -> 0 | O129: 197.52 | P129: 118.66 | Q129: 527 | R129: =$B129*'PERCENTAGE SHARING'!R88 -> 0
A130: ='PROP DAILY PNL'!A295 -> 45875 | C130: 2525.61 | D130: 577 | E130: 476.95 | F130: =$B130*'PERCENTAGE SHARING'!F89 -> 0 | G130: 527 | H130: =$B130*'PERCENTAGE SHARING'!H89 -> 0 | I130: =$B130*'PERCENTAGE SHARING'!I89 -> 0 | J130: =$B130*'PERCENTAGE SHARING'!J89 -> 0 | K130: =$B130*'PERCENTAGE SHARING'!K89 -> 0 | L130: 527 | M130: 527 | N130: =$B130*'PERCENTAGE SHARING'!N89 -> 0 | O130: 197.52 | P130: 118.66 | Q130: 527 | R130: =$B130*'PERCENTAGE SHARING'!R89 -> 0
A131: ='PROP DAILY PNL'!A296 -> 45876 | C131: 2525.61 | D131: 577 | E131: 476.95 | F131: =$B131*'PERCENTAGE SHARING'!F90 -> 0 | G131: 527 | H131: =$B131*'PERCENTAGE SHARING'!H90 -> 0 | I131: =$B131*'PERCENTAGE SHARING'!I90 -> 0 | J131: =$B131*'PERCENTAGE SHARING'!J90 -> 0 | K131: =$B131*'PERCENTAGE SHARING'!K90 -> 0 | L131: 527 | M131: 527 | N131: =$B131*'PERCENTAGE SHARING'!N90 -> 0 | O131: 197.52 | P131: 118.66 | Q131: 527 | R131: =$B131*'PERCENTAGE SHARING'!R90 -> 0
A132: ='PROP DAILY PNL'!A297 -> 45877 | C132: 2525.61 | D132: 577 | E132: 476.95 | F132: =$B132*'PERCENTAGE SHARING'!F91 -> 0 | G132: 527 | H132: =$B132*'PERCENTAGE SHARING'!H91 -> 0 | I132: =$B132*'PERCENTAGE SHARING'!I91 -> 0 | J132: =$B132*'PERCENTAGE SHARING'!J91 -> 0 | K132: =$B132*'PERCENTAGE SHARING'!K91 -> 0 | L132: 527 | M132: 527 | N132: =$B132*'PERCENTAGE SHARING'!N91 -> 0 | O132: 197.52 | P132: 118.66 | Q132: 527 | R132: =$B132*'PERCENTAGE SHARING'!R91 -> 0
A133: ='PROP DAILY PNL'!A298 -> 45880 | C133: 2525.61 | D133: 577 | E133: 476.95 | F133: =$B133*'PERCENTAGE SHARING'!F92 -> 0 | G133: 527 | H133: =$B133*'PERCENTAGE SHARING'!H92 -> 0 | I133: =$B133*'PERCENTAGE SHARING'!I92 -> 0 | J133: =$B133*'PERCENTAGE SHARING'!J92 -> 0 | K133: =$B133*'PERCENTAGE SHARING'!K92 -> 0 | L133: 527 | M133: 527 | N133: =$B133*'PERCENTAGE SHARING'!N92 -> 0 | O133: 197.52 | P133: 118.66 | Q133: 527 | R133: =$B133*'PERCENTAGE SHARING'!R92 -> 0
A134: ='PROP DAILY PNL'!A299 -> 45881 | C134: 2525.61 | D134: 577 | E134: 476.95 | F134: =$B134*'PERCENTAGE SHARING'!F93 -> 0 | G134: 527 | H134: =$B134*'PERCENTAGE SHARING'!H93 -> 0 | I134: =$B134*'PERCENTAGE SHARING'!I93 -> 0 | J134: =$B134*'PERCENTAGE SHARING'!J93 -> 0 | K134: =$B134*'PERCENTAGE SHARING'!K93 -> 0 | L134: 527 | M134: 527 | N134: =$B134*'PERCENTAGE SHARING'!N93 -> 0 | O134: 197.52 | P134: 118.66 | Q134: 527 | R134: =$B134*'PERCENTAGE SHARING'!R93 -> 0
A135: ='PROP DAILY PNL'!A300 -> 45882 | C135: 2525.61 | D135: 577 | E135: 476.95 | F135: =$B135*'PERCENTAGE SHARING'!F94 -> 0 | G135: 527 | H135: =$B135*'PERCENTAGE SHARING'!H94 -> 0 | I135: =$B135*'PERCENTAGE SHARING'!I94 -> 0 | J135: =$B135*'PERCENTAGE SHARING'!J94 -> 0 | K135: =$B135*'PERCENTAGE SHARING'!K94 -> 0 | L135: 527 | M135: 527 | N135: =$B135*'PERCENTAGE SHARING'!N94 -> 0 | O135: 197.52 | P135: 118.66 | Q135: 527 | R135: =$B135*'PERCENTAGE SHARING'!R94 -> 0
A136: ='PROP DAILY PNL'!A301 -> 45883 | C136: 2525.61 | D136: 577 | E136: 476.95 | F136: =$B136*'PERCENTAGE SHARING'!F95 -> 0 | G136: 527 | H136: =$B136*'PERCENTAGE SHARING'!H95 -> 0 | I136: =$B136*'PERCENTAGE SHARING'!I95 -> 0 | J136: =$B136*'PERCENTAGE SHARING'!J95 -> 0 | K136: =$B136*'PERCENTAGE SHARING'!K95 -> 0 | L136: 527 | M136: 527 | N136: =$B136*'PERCENTAGE SHARING'!N95 -> 0 | O136: 197.52 | P136: 118.66 | Q136: 527 | R136: =$B136*'PERCENTAGE SHARING'!R95 -> 0
A137: ='PROP DAILY PNL'!A302 -> 45887 | C137: 2525.61 | D137: 577 | E137: 476.95 | F137: =$B137*'PERCENTAGE SHARING'!F96 -> 0 | G137: 527 | H137: =$B137*'PERCENTAGE SHARING'!H96 -> 0 | I137: =$B137*'PERCENTAGE SHARING'!I96 -> 0 | J137: =$B137*'PERCENTAGE SHARING'!J96 -> 0 | K137: =$B137*'PERCENTAGE SHARING'!K96 -> 0 | L137: 527 | M137: 527 | N137: =$B137*'PERCENTAGE SHARING'!N96 -> 0 | O137: 197.52 | P137: 118.66 | Q137: 527 | R137: =$B137*'PERCENTAGE SHARING'!R96 -> 0
A138: ='PROP DAILY PNL'!A303 -> 45888 | C138: 2525.61 | D138: 577 | E138: 476.95 | F138: =$B138*'PERCENTAGE SHARING'!F97 -> 0 | G138: 527 | H138: =$B138*'PERCENTAGE SHARING'!H97 -> 0 | I138: =$B138*'PERCENTAGE SHARING'!I97 -> 0 | J138: =$B138*'PERCENTAGE SHARING'!J97 -> 0 | K138: =$B138*'PERCENTAGE SHARING'!K97 -> 0 | L138: 527 | M138: 527 | N138: =$B138*'PERCENTAGE SHARING'!N97 -> 0 | O138: 197.52 | P138: 118.66 | Q138: 527 | R138: =$B138*'PERCENTAGE SHARING'!R97 -> 0
... A167: ='PROP DAILY PNL'!A332 -> 45930 | C167: 2770 | D167: 633 | E167: 524 | F167: =$B167*'PERCENTAGE SHARING'!F126 -> 0 | G167: 570 | H167: =$B167*'PERCENTAGE SHARING'!H126 -> 0 | I167: =$B167*'PERCENTAGE SHARING'!I126 -> 0 | J167: =$B167*'PERCENTAGE SHARING'!J126 -> 0 | K167: =$B167*'PERCENTAGE SHARING'!K126 -> 0 | L167: 570 | M167: 570 | N167: =$B167*'PERCENTAGE SHARING'!N126 -> 0 | O167: 217 | P167: 130 | Q167: 570 | R167: =$B167*'PERCENTAGE SHARING'!R126 -> 0
A168: ='PROP DAILY PNL'!A333 -> 45931 | C168: 2278 | D168: 514.4 | E168: 425.1 | F168: =$B168*'PERCENTAGE SHARING'!F127 -> 0 | G168: 625 | H168: =$B168*'PERCENTAGE SHARING'!H127 -> 0 | I168: =$B168*'PERCENTAGE SHARING'!I127 -> 0 | J168: =$B168*'PERCENTAGE SHARING'!J127 -> 0 | K168: =$B168*'PERCENTAGE SHARING'!K127 -> 0 | L168: 570 | M168: 570 | N168: =$B168*'PERCENTAGE SHARING'!N127 -> 0 | O168: 177 | P168: 106.2 | Q168: 625 | R168: =$B168*'PERCENTAGE SHARING'!R127 -> 0 | T168: 25000 | U168: done
A169: ='PROP DAILY PNL'!A334 -> 45932 | C169: 0 | D169: 0 | E169: 0 | F169: =$B169*'PERCENTAGE SHARING'!F128 -> 0 | G169: 0 | H169: =$B169*'PERCENTAGE SHARING'!H128 -> 0 | I169: =$B169*'PERCENTAGE SHARING'!I128 -> 0 | J169: =$B169*'PERCENTAGE SHARING'!J128 -> 0 | K169: =$B169*'PERCENTAGE SHARING'!K128 -> 0 | L169: 0 | M169: 0 | N169: =$B169*'PERCENTAGE SHARING'!N128 -> 0 | O169: 0 | P169: 0 | Q169: 0 | R169: =$B169*'PERCENTAGE SHARING'!R128 -> 0 | T169: 6840 | U169: done
A170: ='PROP DAILY PNL'!A335 -> 45933 | C170: 2278 | D170: 514.4 | E170: 425.1 | F170: =$B170*'PERCENTAGE SHARING'!F129 -> 0 | G170: 625 | H170: =$B170*'PERCENTAGE SHARING'!H129 -> 0 | I170: =$B170*'PERCENTAGE SHARING'!I129 -> 0 | J170: =$B170*'PERCENTAGE SHARING'!J129 -> 0 | K170: =$B170*'PERCENTAGE SHARING'!K129 -> 0 | L170: 570 | M170: 570 | N170: =$B170*'PERCENTAGE SHARING'!N129 -> 0 | O170: 177 | P170: 106.2 | Q170: 625 | R170: =$B170*'PERCENTAGE SHARING'!R129 -> 0 | T170: 6840 | U170: done
A171: ='PROP DAILY PNL'!A336 -> 45936 | C171: 2278 | D171: 514.4 | E171: 425.1 | F171: =$B171*'PERCENTAGE SHARING'!F130 -> 0 | G171: 625 | H171: =$B171*'PERCENTAGE SHARING'!H130 -> 0 | I171: =$B171*'PERCENTAGE SHARING'!I130 -> 0 | J171: =$B171*'PERCENTAGE SHARING'!J130 -> 0 | K171: =$B171*'PERCENTAGE SHARING'!K130 -> 0 | L171: 570 | M171: 570 | N171: =$B171*'PERCENTAGE SHARING'!N130 -> 0 | O171: 177 | P171: 106.2 | Q171: 625 | R171: =$B171*'PERCENTAGE SHARING'!R130 -> 0 | T171: 42000
A172: ='PROP DAILY PNL'!A337 -> 45937 | C172: 2278 | D172: 514.4 | E172: 425.1 | F172: =$B172*'PERCENTAGE SHARING'!F131 -> 0 | G172: 625 | H172: =$B172*'PERCENTAGE SHARING'!H131 -> 0 | I172: =$B172*'PERCENTAGE SHARING'!I131 -> 0 | J172: =$B172*'PERCENTAGE SHARING'!J131 -> 0 | K172: =$B172*'PERCENTAGE SHARING'!K131 -> 0 | L172: 570 | M172: 570 | N172: =$B172*'PERCENTAGE SHARING'!N131 -> 0 | O172: 177 | P172: 106.2 | Q172: 625 | R172: =$B172*'PERCENTAGE SHARING'!R131 -> 0 | T172: 23400
A173: ='PROP DAILY PNL'!A338 -> 45938 | C173: 2278 | D173: 514.4 | E173: 425.1 | F173: =$B173*'PERCENTAGE SHARING'!F132 -> 0 | G173: 625 | H173: =$B173*'PERCENTAGE SHARING'!H132 -> 0 | I173: =$B173*'PERCENTAGE SHARING'!I132 -> 0 | J173: =$B173*'PERCENTAGE SHARING'!J132 -> 0 | K173: =$B173*'PERCENTAGE SHARING'!K132 -> 0 | L173: 570 | M173: 570 | N173: =$B173*'PERCENTAGE SHARING'!N132 -> 0 | O173: 177 | P173: 106.2 | Q173: 625 | R173: =$B173*'PERCENTAGE SHARING'!R132 -> 0
A174: ='PROP DAILY PNL'!A339 -> 45939 | C174: 2278 | D174: 514.4 | E174: 425.1 | F174: =$B174*'PERCENTAGE SHARING'!F133 -> 0 | G174: 625 | H174: =$B174*'PERCENTAGE SHARING'!H133 -> 0 | I174: =$B174*'PERCENTAGE SHARING'!I133 -> 0 | J174: =$B174*'PERCENTAGE SHARING'!J133 -> 0 | K174: =$B174*'PERCENTAGE SHARING'!K133 -> 0 | L174: 570 | M174: 570 | N174: =$B174*'PERCENTAGE SHARING'!N133 -> 0 | O174: 177 | P174: 106.2 | Q174: 625 | R174: =$B174*'PERCENTAGE SHARING'!R133 -> 0
A175: ='PROP DAILY PNL'!A340 -> 45940 | C175: 2278 | D175: 514.4 | E175: 425.1 | F175: =$B175*'PERCENTAGE SHARING'!F134 -> 0 | G175: 625 | H175: =$B175*'PERCENTAGE SHARING'!H134 -> 0 | I175: =$B175*'PERCENTAGE SHARING'!I134 -> 0 | J175: =$B175*'PERCENTAGE SHARING'!J134 -> 0 | K175: =$B175*'PERCENTAGE SHARING'!K134 -> 0 | L175: 570 | M175: 570 | N175: =$B175*'PERCENTAGE SHARING'!N134 -> 0 | O175: 177 | P175: 106.2 | Q175: 625 | R175: =$B175*'PERCENTAGE SHARING'!R134 -> 0 | T175: Abh | U175: 62 | V175: =U175/$U$181 -> 0.6508503 | W175: =$T$171*V175/12 -> 2277.9761 | X175: =$T$172*V175/8 -> 1903.7371
A176: ='PROP DAILY PNL'!A341 -> 45943 | C176: 2278 | D176: 514.4 | E176: 425.1 | F176: =$B176*'PERCENTAGE SHARING'!F135 -> 0 | G176: 625 | H176: =$B176*'PERCENTAGE SHARING'!H135 -> 0 | I176: =$B176*'PERCENTAGE SHARING'!I135 -> 0 | J176: =$B176*'PERCENTAGE SHARING'!J135 -> 0 | K176: =$B176*'PERCENTAGE SHARING'!K135 -> 0 | L176: 570 | M176: 570 | N176: =$B176*'PERCENTAGE SHARING'!N135 -> 0 | O176: 177 | P176: 106.2 | Q176: 625 | R176: =$B176*'PERCENTAGE SHARING'!R135 -> 0 | T176: Radh | U176: 14 | V176: =U176/$U$181 -> 0.1469662 | W176: =$T$171*V176/12 -> 514.38169 | X176: =$T$172*V176/8 -> 429.87613
A177: ='PROP DAILY PNL'!A342 -> 45944 | C177: 2278 | D177: 514.4 | E177: 425.1 | F177: =$B177*'PERCENTAGE SHARING'!F136 -> 0 | G177: 625 | H177: =$B177*'PERCENTAGE SHARING'!H136 -> 0 | I177: =$B177*'PERCENTAGE SHARING'!I136 -> 0 | J177: =$B177*'PERCENTAGE SHARING'!J136 -> 0 | K177: =$B177*'PERCENTAGE SHARING'!K136 -> 0 | L177: 570 | M177: 570 | N177: =$B177*'PERCENTAGE SHARING'!N136 -> 0 | O177: 177 | P177: 106.2 | Q177: 625 | R177: =$B177*'PERCENTAGE SHARING'!R136 -> 0 | T177: karan | U177: 11.57 | V177: =U177/$U$181 -> 0.12145706 | W177: =$T$171*V177/12 -> 425.09973 | X177: =$T$172*V177/8 -> 355.26191
A178: ='PROP DAILY PNL'!A343 -> 45945 | C178: 2278 | D178: 514.4 | E178: 425.1 | F178: =$B178*'PERCENTAGE SHARING'!F137 -> 0 | G178: 625 | H178: =$B178*'PERCENTAGE SHARING'!H137 -> 0 | I178: =$B178*'PERCENTAGE SHARING'!I137 -> 0 | J178: =$B178*'PERCENTAGE SHARING'!J137 -> 0 | K178: =$B178*'PERCENTAGE SHARING'!K137 -> 0 | L178: 570 | M178: 570 | N178: =$B178*'PERCENTAGE SHARING'!N137 -> 0 | O178: 177 | P178: 106.2 | Q178: 625 | R178: =$B178*'PERCENTAGE SHARING'!R137 -> 0 | T178: aayush | U178: 4.8 | V178: =U178/$U$181 -> 0.050388411 | W178: =$T$171*V178/12 -> 176.35944 | X178: =$T$172*V178/8 -> 147.3861
A179: ='PROP DAILY PNL'!A344 -> 45946 | C179: 2278 | D179: 514.4 | E179: 425.1 | F179: =$B179*'PERCENTAGE SHARING'!F138 -> 0 | G179: 625 | H179: =$B179*'PERCENTAGE SHARING'!H138 -> 0 | I179: =$B179*'PERCENTAGE SHARING'!I138 -> 0 | J179: =$B179*'PERCENTAGE SHARING'!J138 -> 0 | K179: =$B179*'PERCENTAGE SHARING'!K138 -> 0 | L179: 570 | M179: 570 | N179: =$B179*'PERCENTAGE SHARING'!N138 -> 0 | O179: 177 | P179: 106.2 | Q179: 625 | R179: =$B179*'PERCENTAGE SHARING'!R138 -> 0 | T179: dish | U179: 2.89 | V179: =U179/$U$181 -> 0.030338022 | W179: =$T$171*V179/12 -> 106.18308 | X179: =$T$172*V179/8 -> 88.738715
...

Sheet Sheet
A1: Month | B1: Entire Profit | C1: Abhishek S | D1: Radhika A | E1: KARAN | F1: Pavan | G1: Rasul | H1: SIVA | I1: RAVI | J1: MAHESH| | K1: JAGADISH | L1: Bharghav | M1: Kaushik | N1: MAHESH A | O1: Aayushi A | P1: Dishant | Q1: Bharath | R1: NARESH
A2: 45446 | B2: ='PROP DAILY PNL'!B2 -> 82622.25 | C2: ='Clients Balance'!C2/'Clients Balance'!B2*Sheet!B2 -> 54064.212 | D2: ='Clients Balance'!D2/'Clients Balance'!C2*Sheet!C2 -> 14126.245 | E2: ='Clients Balance'!E2/'Clients Balance'!D2*Sheet!D2 -> 14431.793
A3: 45447 | B3: ='PROP DAILY PNL'!B3 -> 155760 | C3: ='Clients Balance'!C3/'Clients Balance'!B3*Sheet!B3 -> 101922.2 | D3: ='Clients Balance'!D3/'Clients Balance'!C3*Sheet!C3 -> 26630.889 | E3: ='Clients Balance'!E3/'Clients Balance'!D3*Sheet!D3 -> 27206.909
A4: 45448 | B4: ='PROP DAILY PNL'!B4 -> -13672.5 | C4: ='Clients Balance'!C4/'Clients Balance'!B4*Sheet!B4 -> -8946.6571 | D4: ='Clients Balance'!D4/'Clients Balance'!C4*Sheet!C4 -> -2337.6401 | E4: ='Clients Balance'!E4/'Clients Balance'!D4*Sheet!D4 -> -2388.2028
A5: 45449 | B5: ='PROP DAILY PNL'!B5 -> 5907 | C5: ='Clients Balance'!C5/'Clients Balance'!B5*Sheet!B5 -> 3865.27 | D5: ='Clients Balance'!D5/'Clients Balance'!C5*Sheet!C5 -> 1009.9426 | E5: ='Clients Balance'!E5/'Clients Balance'!D5*Sheet!D5 -> 1031.7874
A6: 45450 | B6: ='PROP DAILY PNL'!B6 -> 32298 | C6: ='Clients Balance'!C6/'Clients Balance'!B6*Sheet!B6 -> 21134.33 | D6: ='Clients Balance'!D6/'Clients Balance'!C6*Sheet!C6 -> 5522.1138 | E6: ='Clients Balance'!E6/'Clients Balance'!D6*Sheet!D6 -> 5641.5559
A7: 45453 | B7: ='PROP DAILY PNL'!B7 -> 32068.5 | C7: ='Clients Balance'!C7/'Clients Balance'!B7*Sheet!B7 -> 20984.156 | D7: ='Clients Balance'!D7/'Clients Balance'!C7*Sheet!C7 -> 5482.8753 | E7: ='Clients Balance'!E7/'Clients Balance'!D7*Sheet!D7 -> 5601.4686
A8: 45454 | B8: ='PROP DAILY PNL'!B8 -> 537 | C8: ='Clients Balance'!C8/'Clients Balance'!B8*Sheet!B8 -> 351.38818 | D8: ='Clients Balance'!D8/'Clients Balance'!C8*Sheet!C8 -> 91.812964 | E8: ='Clients Balance'!E8/'Clients Balance'!D8*Sheet!D8 -> 93.798857
A9: 45455 | B9: ='PROP DAILY PNL'!B9 -> -8304 | C9: ='Clients Balance'!C9/'Clients Balance'!B9*Sheet!B9 -> -5433.7569 | D9: ='Clients Balance'!D9/'Clients Balance'!C9*Sheet!C9 -> -1419.767 | E9: ='Clients Balance'!E9/'Clients Balance'!D9*Sheet!D9 -> -1450.4762
A10: 45456 | B10: ='PROP DAILY PNL'!B10 -> 9743.25 | C10: ='Clients Balance'!C10/'Clients Balance'!B10*Sheet!B10 -> 6375.5361 | D10: ='Clients Balance'!D10/'Clients Balance'!C10*Sheet!C10 -> 1665.8411 | E10: ='Clients Balance'!E10/'Clients Balance'!D10*Sheet!D10 -> 1701.8728
A11: 45457 | B11: ='PROP DAILY PNL'!B11 -> 485.5 | C11: ='Clients Balance'!C11/'Clients Balance'!B11*Sheet!B11 -> 317.68894 | D11: ='Clients Balance'!D11/'Clients Balance'!C11*Sheet!C11 -> 83.00781 | E11: ='Clients Balance'!E11/'Clients Balance'!D11*Sheet!D11 -> 84.80325
A12: 45461 | B12: ='PROP DAILY PNL'!B12 -> 6382.25 | C12: ='Clients Balance'!C12/'Clients Balance'!B12*Sheet!B12 -> 4176.2518 | D12: ='Clients Balance'!D12/'Clients Balance'!C12*Sheet!C12 -> 1091.1979 | E12: ='Clients Balance'!E12/'Clients Balance'!D12*Sheet!D12 -> 1114.8003
A13: 45462 | B13: ='PROP DAILY PNL'!B13 -> -57802.75 | C13: ='Clients Balance'!C13/'Clients Balance'!B13*Sheet!B13 -> -37823.469 | D13: ='Clients Balance'!D13/'Clients Balance'!C13*Sheet!C13 -> -9882.7595 | E13: ='Clients Balance'!E13/'Clients Balance'!D13*Sheet!D13 -> -10096.521
... A20: 45471 | B20: ='PROP DAILY PNL'!B20 -> -57876.25 | C20: ='Clients Balance'!C20/'Clients Balance'!B20*Sheet!B20 -> -37871.564 | D20: ='Clients Balance'!D20/'Clients Balance'!C20*Sheet!C20 -> -9895.326 | E20: ='Clients Balance'!E20/'Clients Balance'!D20*Sheet!D20 -> -10109.36
A21: 45474 | B21: ='PROP DAILY PNL'!B21 -> -11219 | C21: ='Clients Balance'!C22/'Clients Balance'!B21*Sheet!B21 -> -7039.1504 | D21: ='Clients Balance'!D22/'Clients Balance'!C21*Sheet!C21 -> -1807.7677 | E21: ='Clients Balance'!E22/'Clients Balance'!D21*Sheet!D21 -> -1815.2719
A22: 45475 | B22: ='PROP DAILY PNL'!B22 -> -24815.5 | C22: ='Clients Balance'!C23/'Clients Balance'!B22*Sheet!B22 -> -16041.829 | D22: ='Clients Balance'!D23/'Clients Balance'!C22*Sheet!C22 -> -4282.0424 | E22: ='Clients Balance'!E23/'Clients Balance'!D22*Sheet!D22 -> -4360.1122
A23: 45476 | B23: ='PROP DAILY PNL'!B23 -> 112503.75 | C23: ='Clients Balance'!C23/'Clients Balance'!B23*Sheet!B23 -> 72980.442 | D23: ='Clients Balance'!D23/'Clients Balance'!C23*Sheet!C23 -> 19549.647 | E23: ='Clients Balance'!E23/'Clients Balance'!D23*Sheet!D23 -> 19973.661
A24: 45477 | B24: ='PROP DAILY PNL'!B24 -> 39878.75 | C24: ='Clients Balance'!C24/'Clients Balance'!B24*Sheet!B24 -> 25868.696 | D24: ='Clients Balance'!D24/'Clients Balance'!C24*Sheet!C24 -> 6929.7797 | E24: ='Clients Balance'!E24/'Clients Balance'!D24*Sheet!D24 -> 7080.2747
A25: 45478 | B25: ='PROP DAILY PNL'!B25 -> -25744.5 | C25: ='Clients Balance'!C25/'Clients Balance'!B25*Sheet!B25 -> -16700.047 | D25: ='Clients Balance'!D25/'Clients Balance'!C25*Sheet!C25 -> -4473.6514 | E25: ='Clients Balance'!E25/'Clients Balance'!D25*Sheet!D25 -> -4570.8019
A26: 45481 | B26: ='PROP DAILY PNL'!B26 -> -44632.5 | C26: ='Clients Balance'!C26/'Clients Balance'!B26*Sheet!B26 -> -28952.391 | D26: ='Clients Balance'!D26/'Clients Balance'!C26*Sheet!C26 -> -7755.841 | E26: ='Clients Balance'!E26/'Clients Balance'!D26*Sheet!D26 -> -7924.268
A27: 45482 | B27: ='PROP DAILY PNL'!B27 -> -12644.75 | C27: ='Clients Balance'!C27/'Clients Balance'!B27*Sheet!B27 -> -8202.4477 | D27: ='Clients Balance'!D27/'Clients Balance'!C27*Sheet!C27 -> -2197.2928 | E27: ='Clients Balance'!E27/'Clients Balance'!D27*Sheet!D27 -> -2245.0095
A28: 45483 | B28: ='PROP DAILY PNL'!B28 -> 61934.25 | C28: ='Clients Balance'!C28/'Clients Balance'!B28*Sheet!B28 -> 40175.76 | D28: ='Clients Balance'!D28/'Clients Balance'!C28*Sheet!C28 -> 10762.386 | E28: ='Clients Balance'!E28/'Clients Balance'!D28*Sheet!D28 -> 10996.104
A29: 45484 | B29: ='PROP DAILY PNL'!B29 -> 21988.75 | C29: ='Clients Balance'!C29/'Clients Balance'!B29*Sheet!B29 -> 14263.751 | D29: ='Clients Balance'!D29/'Clients Balance'!C29*Sheet!C29 -> 3821.0104 | E29: ='Clients Balance'!E29/'Clients Balance'!D29*Sheet!D29 -> 3903.9881
A30: 45485 | B30: ='PROP DAILY PNL'!B30 -> 12094 | C30: ='Clients Balance'!C30/'Clients Balance'!B30*Sheet!B30 -> 7845.1849 | D30: ='Clients Balance'!D30/'Clients Balance'!C30*Sheet!C30 -> 2101.5883 | E30: ='Clients Balance'!E30/'Clients Balance'!D30*Sheet!D30 -> 2147.2267
A31: 45488 | B31: ='PROP DAILY PNL'!B31 -> 2925 | C31: ='Clients Balance'!C31/'Clients Balance'!B31*Sheet!B31 -> 1897.4009 | D31: ='Clients Balance'!D31/'Clients Balance'!C31*Sheet!C31 -> 508.28062 | E31: ='Clients Balance'!E31/'Clients Balance'!D31*Sheet!D31 -> 519.31852
A32: 45489 | B32: ='PROP DAILY PNL'!B32 -> 107071.25 | C32: ='Clients Balance'!C32/'Clients Balance'!B32*Sheet!B32 -> 69455.412 | D32: ='Clients Balance'!D32/'Clients Balance'!C32*Sheet!C32 -> 18605.895 | E32: ='Clients Balance'!E32/'Clients Balance'!D32*Sheet!D32 -> 19009.943
A33: 45491 | B33: ='PROP DAILY PNL'!B33 -> -40965 | C33: ='Clients Balance'!C33/'Clients Balance'!B33*Sheet!B33 -> -26573.342 | D33: ='Clients Balance'!D33/'Clients Balance'!C33*Sheet!C33 -> -7118.5353 | E33: ='Clients Balance'!E33/'Clients Balance'!D33*Sheet!D33 -> -7273.1225
A34: 45492 | B34: ='PROP DAILY PNL'!B34 -> 90556.75 | C34: ='Clients Balance'!C34/'Clients Balance'!B34*Sheet!B34 -> 58742.72 | D34: ='Clients Balance'!D34/'Clients Balance'!C34*Sheet!C34 -> 15736.151 | E34: ='Clients Balance'!E34/'Clients Balance'!D34*Sheet!D34 -> 16077.88
... A52: 45518 | B52: ='PROP DAILY PNL'!B52 -> 38464 | C52: ='Clients Balance'!C52/'Clients Balance'!B52*Sheet!B52 -> 24743.401 | D52: ='Clients Balance'!D52/'Clients Balance'!C52*Sheet!C52 -> 6786.8792 | E52: ='Clients Balance'!E52/'Clients Balance'!D52*Sheet!D52 -> 6933.7196
A53: 45520 | B53: ='PROP DAILY PNL'!B53 -> -5838 | C53: ='Clients Balance'!C54/'Clients Balance'!B54*Sheet!B53 -> -3755.511 | D53: ='Clients Balance'!D54/'Clients Balance'!C54*Sheet!C53 -> -1030.1009 | E53: ='Clients Balance'!E54/'Clients Balance'!D54*Sheet!D53 -> -1052.3881
A54: 45523 | B54: ='PROP DAILY PNL'!B54 -> -15076 | C54: ='Clients Balance'!C55/'Clients Balance'!B55*Sheet!B54 -> -9698.1987 | D54: ='Clients Balance'!D55/'Clients Balance'!C55*Sheet!C54 -> -2660.1235 | E54: ='Clients Balance'!E55/'Clients Balance'!D55*Sheet!D54 -> -2717.6777
A55: 45524 | B55: ='PROP DAILY PNL'!B55 -> 42558 | C55: ='Clients Balance'!C56/'Clients Balance'!B56*Sheet!B55 -> 27377.019 | D55: ='Clients Balance'!D56/'Clients Balance'!C56*Sheet!C55 -> 7509.2556 | E55: ='Clients Balance'!E56/'Clients Balance'!D56*Sheet!D55 -> 7671.7252
A56: 45525 | B56: ='PROP DAILY PNL'!B56 -> -38280 | C56: ='Clients Balance'!C57/'Clients Balance'!B57*Sheet!B56 -> -24625.036 | D56: ='Clients Balance'!D57/'Clients Balance'!C57*Sheet!C56 -> -6754.4129 | E56: ='Clients Balance'!E57/'Clients Balance'!D57*Sheet!D56 -> -6900.5508
A57: 45526 | B57: ='PROP DAILY PNL'!B57 -> 72650 | C57: ='Clients Balance'!C58/'Clients Balance'!B58*Sheet!B57 -> 46734.819 | D57: ='Clients Balance'!D58/'Clients Balance'!C58*Sheet!C57 -> 12818.916 | E57: ='Clients Balance'!E58/'Clients Balance'!D58*Sheet!D57 -> 13096.265
A58: 45527 | B58: ='PROP DAILY PNL'!B58 -> 32712 | C58: ='Clients Balance'!C59/'Clients Balance'!B59*Sheet!B58 -> 21043.213 | D58: ='Clients Balance'!D59/'Clients Balance'!C59*Sheet!C58 -> 5771.9528 | E58: ='Clients Balance'!E59/'Clients Balance'!D59*Sheet!D58 -> 5896.8343
A59: 45530 | B59: ='PROP DAILY PNL'!B59 -> 66870 | C59: ='Clients Balance'!C60/'Clients Balance'!B60*Sheet!B59 -> 43016.619 | D59: ='Clients Balance'!D60/'Clients Balance'!C60*Sheet!C59 -> 11799.049 | E59: ='Clients Balance'!E60/'Clients Balance'!D60*Sheet!D59 -> 12054.332
A60: 45531 | B60: ='PROP DAILY PNL'!B60 -> -36528 | C60: ='Clients Balance'!C61/'Clients Balance'!B61*Sheet!B60 -> -23497.997 | D60: ='Clients Balance'!D61/'Clients Balance'!C61*Sheet!C60 -> -6445.2767 | E60: ='Clients Balance'!E61/'Clients Balance'!D61*Sheet!D60 -> -6584.7262
A61: 45532 | B61: ='PROP DAILY PNL'!B61 -> 102213 | C61: ='Clients Balance'!C62/'Clients Balance'!B62*Sheet!B61 -> 65752.321 | D61: ='Clients Balance'!D62/'Clients Balance'!C62*Sheet!C61 -> 18035.235 | E61: ='Clients Balance'!E62/'Clients Balance'!D62*Sheet!D61 -> 18425.444
A62: 45533 | B62: ='PROP DAILY PNL'!B62 -> -85183 | C62: ='Clients Balance'!C63/'Clients Balance'!B63*Sheet!B62 -> -54797.139 | D62: ='Clients Balance'!D63/'Clients Balance'!C63*Sheet!C62 -> -15030.333 | E62: ='Clients Balance'!E63/'Clients Balance'!D63*Sheet!D62 -> -15355.528
A63: 45534 | B63: ='PROP DAILY PNL'!B63 -> 32478.5 | C63: ='Clients Balance'!C64/'Clients Balance'!B64*Sheet!B63 -> 20893.005 | D63: ='Clients Balance'!D64/'Clients Balance'!C64*Sheet!C63 -> 5730.7523 | E63: ='Clients Balance'!E64/'Clients Balance'!D64*Sheet!D63 -> 5854.7424
A64: 45537 | B64: ='PROP DAILY PNL'!B64 -> -37710.25 | C64: ='Clients Balance'!C67/'Clients Balance'!B67*Sheet!B64 -> -23708.575 | D64: ='Clients Balance'!D67/'Clients Balance'!C67*Sheet!C64 -> -5805.2363 | E64: ='Clients Balance'!E67/'Clients Balance'!D67*Sheet!D64 -> -8196.4383
A65: 45538 | B65: ='PROP DAILY PNL'!B65 -> -134005 | C65: ='Clients Balance'!C68/'Clients Balance'!B68*Sheet!B65 -> -84249.445 | D65: ='Clients Balance'!D68/'Clients Balance'!C68*Sheet!C65 -> -20629.158 | E65: ='Clients Balance'!E68/'Clients Balance'!D68*Sheet!D65 -> -29126.397
A66: 45539 | B66: ='PROP DAILY PNL'!B66 -> 149400 | C66: ='Clients Balance'!C69/'Clients Balance'!B69*Sheet!B66 -> 93928.34 | D66: ='Clients Balance'!D69/'Clients Balance'!C69*Sheet!C66 -> 22999.113 | E66: ='Clients Balance'!E69/'Clients Balance'!D69*Sheet!D66 -> 32472.547
A67: 45540 | B67: ='PROP DAILY PNL'!B67 -> 225402 | C67: ='Clients Balance'!C70/'Clients Balance'!B70*Sheet!B67 -> 141711.08 | D67: ='Clients Balance'!D70/'Clients Balance'!C70*Sheet!C67 -> 34699.103 | E67: ='Clients Balance'!E70/'Clients Balance'!D70*Sheet!D67 -> 48991.815
A68: 45541 | B68: ='PROP DAILY PNL'!B68 -> 18404 | C68: ='Clients Balance'!C71/'Clients Balance'!B71*Sheet!B68 -> 11570.664 | D68: ='Clients Balance'!D71/'Clients Balance'!C71*Sheet!C68 -> 2833.1705 | E68: ='Clients Balance'!E71/'Clients Balance'!D71*Sheet!D68 -> 4000.1658
A69: 45544 | B69: ='PROP DAILY PNL'!B69 -> 75873 | C69: ='Clients Balance'!C72/'Clients Balance'!B72*Sheet!B69 -> 47701.639 | D69: ='Clients Balance'!D72/'Clients Balance'!C72*Sheet!C69 -> 11680.132 | E69: ='Clients Balance'!E72/'Clients Balance'!D72*Sheet!D69 -> 16491.229
A70: 45545 | B70: ='PROP DAILY PNL'!B70 -> -24887 | C70: ='Clients Balance'!C73/'Clients Balance'!B73*Sheet!B70 -> -15646.55 | D70: ='Clients Balance'!D73/'Clients Balance'!C73*Sheet!C70 -> -3831.1842 | E70: ='Clients Balance'!E73/'Clients Balance'!D73*Sheet!D70 -> -5409.2657
A71: 45546 | B71: ='PROP DAILY PNL'!B71 -> 74070 | C71: ='Clients Balance'!C74/'Clients Balance'!B74*Sheet!B71 -> 46568.086 | D71: ='Clients Balance'!D74/'Clients Balance'!C74*Sheet!C71 -> 11402.572 | E71: ='Clients Balance'!E74/'Clients Balance'!D74*Sheet!D71 -> 16099.341
A72: 45547 | B72: ='PROP DAILY PNL'!B72 -> 260346 | C72: ='Clients Balance'!C75/'Clients Balance'!B75*Sheet!B72 -> 163680.51 | D72: ='Clients Balance'!D75/'Clients Balance'!C75*Sheet!C72 -> 40078.494 | E72: ='Clients Balance'!E75/'Clients Balance'!D75*Sheet!D72 -> 56587
A73: 45548 | B73: ='PROP DAILY PNL'!B73 -> -2582 | C73: ='Clients Balance'!C76/'Clients Balance'!B76*Sheet!B73 -> -1623.3131 | D73: ='Clients Balance'!D76/'Clients Balance'!C76*Sheet!C73 -> -397.48132 | E73: ='Clients Balance'!E76/'Clients Balance'!D76*Sheet!D73 -> -561.20561
A74: 45551 | B74: ='PROP DAILY PNL'!B74 -> 97514.5 | C74: ='Clients Balance'!C77/'Clients Balance'!B77*Sheet!B74 -> 61307.731 | D74: ='Clients Balance'!D77/'Clients Balance'!C77*Sheet!C74 -> 15011.693 | E74: ='Clients Balance'!E77/'Clients Balance'!D77*Sheet!D74 -> 21195.075
A75: 45552 | B75: ='PROP DAILY PNL'!B75 -> 132710 | C75: ='Clients Balance'!C78/'Clients Balance'!B78*Sheet!B75 -> 83435.274 | D75: ='Clients Balance'!D78/'Clients Balance'!C78*Sheet!C75 -> 20429.801 | E75: ='Clients Balance'!E78/'Clients Balance'!D78*Sheet!D75 -> 28844.925
... A125: 45628 | B125: ='PROP DAILY PNL'!B125 -> -96942 | C125: ='Clients Balance'!C128/'Clients Balance'!B128*Sheet!B125 -> -63489.379 | D125: ='Clients Balance'!D128/'Clients Balance'!C128*Sheet!C125 -> -13869.796 | E125: ='Clients Balance'!E128/'Clients Balance'!D128*Sheet!D125 -> -19582.825
A126: 45629 | B126: 42496 | C126: ='Clients Balance'!C129/'Clients Balance'!B129*Sheet!B126 -> 27831.535 | D126: ='Clients Balance'!D129/'Clients Balance'!C129*Sheet!C126 -> 6080.0359 | E126: ='Clients Balance'!E129/'Clients Balance'!D129*Sheet!D126 -> 8584.4291
A127: 45630 | B127: ='PROP DAILY PNL'!B127 -> -183782 | C127: ='Clients Balance'!C130/'Clients Balance'!B130*Sheet!B127 -> -119843.07 | D127: ='Clients Balance'!D130/'Clients Balance'!C130*Sheet!C127 -> -26509.731 | E127: ='Clients Balance'!E130/'Clients Balance'!D130*Sheet!D127 -> -37429.204
A128: 45631 | B128: ='PROP DAILY PNL'!B128 -> -100547 | C128: ='Clients Balance'!C131/'Clients Balance'!B131*Sheet!B128 -> -65561.465 | D128: ='Clients Balance'!D131/'Clients Balance'!C131*Sheet!C128 -> -14505.358 | E128: ='Clients Balance'!E131/'Clients Balance'!D131*Sheet!D128 -> -20480.178
A129: 45632 | B129: ='PROP DAILY PNL'!B129 -> 106262 | C129: ='Clients Balance'!C132/'Clients Balance'!B132*Sheet!B129 -> 69290.064 | D129: ='Clients Balance'!D132/'Clients Balance'!C132*Sheet!C129 -> 15328.939 | E129: ='Clients Balance'!E132/'Clients Balance'!D132*Sheet!D129 -> 21642.996
A130: 45635 | B130: ='PROP DAILY PNL'!B130 -> 120105 | C130: ='Clients Balance'!C133/'Clients Balance'!B133*Sheet!B130 -> 78316.548 | D130: ='Clients Balance'!D133/'Clients Balance'!C133*Sheet!C130 -> 17325.916 | E130: ='Clients Balance'!E133/'Clients Balance'!D133*Sheet!D130 -> 24462.536
A131: 45636 | B131: ='PROP DAILY PNL'!B131 -> 15845 | C131: ='Clients Balance'!C134/'Clients Balance'!B134*Sheet!B131 -> 10332.012 | D131: ='Clients Balance'!D134/'Clients Balance'!C134*Sheet!C131 -> 2285.7406 | E131: ='Clients Balance'!E134/'Clients Balance'!D134*Sheet!D131 -> 3227.2471
A132: 45637 | B132: ='PROP DAILY PNL'!B132 -> 92013 | C132: ='Clients Balance'!C135/'Clients Balance'!B135*Sheet!B132 -> 59998.704 | D132: ='Clients Balance'!D135/'Clients Balance'!C135*Sheet!C132 -> 13273.452 | E132: ='Clients Balance'!E135/'Clients Balance'!D135*Sheet!D132 -> 18740.844
A133: 45638 | B133: ='PROP DAILY PNL'!B133 -> -34287 | C133: ='Clients Balance'!C136/'Clients Balance'!B136*Sheet!B133 -> -22357.445 | D133: ='Clients Balance'!D136/'Clients Balance'!C136*Sheet!C133 -> -4946.1147 | E133: ='Clients Balance'!E136/'Clients Balance'!D136*Sheet!D133 -> -6983.4408
A134: 45639 | B134: ='PROP DAILY PNL'!B134 -> -11060 | C134: ='Clients Balance'!C137/'Clients Balance'!B137*Sheet!B134 -> -7211.8685 | D134: ='Clients Balance'!D137/'Clients Balance'!C137*Sheet!C134 -> -1595.4743 | E134: ='Clients Balance'!E137/'Clients Balance'!D137*Sheet!D134 -> -2252.6571
A135: 45642 | B135: ='PROP DAILY PNL'!B135 -> -168690 | C135: ='Clients Balance'!C138/'Clients Balance'!B138*Sheet!B135 -> -109997.3 | D135: ='Clients Balance'!D138/'Clients Balance'!C138*Sheet!C135 -> -24334.59 | E135: ='Clients Balance'!E138/'Clients Balance'!D138*Sheet!D135 -> -34358.113
A136: 45643 | B136: ='PROP DAILY PNL'!B136 -> 120811 | C136: ='Clients Balance'!C139/'Clients Balance'!B139*Sheet!B136 -> 78776.948 | D136: ='Clients Balance'!D139/'Clients Balance'!C139*Sheet!C136 -> 17427.744 | E136: ='Clients Balance'!E139/'Clients Balance'!D139*Sheet!D136 -> 24606.308
A137: 45644 | B137: ='PROP DAILY PNL'!B137 -> -46973.75 | C137: ='Clients Balance'!C140/'Clients Balance'!B140*Sheet!B137 -> -30630.064 | D137: ='Clients Balance'!D140/'Clients Balance'!C140*Sheet!C137 -> -6776.2579 | E137: ='Clients Balance'!E140/'Clients Balance'!D140*Sheet!D137 -> -9567.428
A138: 45645 | B138: ='PROP DAILY PNL'!B138 -> 295950 | C138: ='Clients Balance'!C141/'Clients Balance'!B141*Sheet!B138 -> 192979.43 | D138: ='Clients Balance'!D141/'Clients Balance'!C141*Sheet!C138 -> 42692.643 | E138: ='Clients Balance'!E141/'Clients Balance'!D141*Sheet!D138 -> 60277.928
... A145: 45657 | B145: ='PROP DAILY PNL'!B145 -> 52192 | C145: ='Clients Balance'!C148/'Clients Balance'!B148*Sheet!B145 -> 34032.716 | D145: ='Clients Balance'!D148/'Clients Balance'!C148*Sheet!C145 -> 7529.0232 | E145: ='Clients Balance'!E148/'Clients Balance'!D148*Sheet!D145 -> 10630.261
A146: 45658 | B146: ='PROP DAILY PNL'!B146 -> -97912 | C146: ='Clients Balance'!C152/'Clients Balance'!B152*Sheet!B146 -> -49199.175 | D146: =B146*'Clients Balance'!D152/'Clients Balance'!B152 -> -11162.913 | E146: =B146*'Clients Balance'!E152/'Clients Balance'!B152 -> -13828.732 | F146: =B146*'Clients Balance'!F152/'Clients Balance'!B152 -> -18247.059 | G146: =B146*'Clients Balance'!G152/'Clients Balance'!B152 -> -5474.12
A147: 45659 | B147: ='PROP DAILY PNL'!B147 -> 269887 | C147: ='Clients Balance'!C152/'Clients Balance'!B152*Sheet!B147 -> 135613.79 | D147: =B147*'Clients Balance'!D153/'Clients Balance'!B153 -> 30769.724 | E147: =B147*'Clients Balance'!E153/'Clients Balance'!B153 -> 38117.852 | F147: =B147*'Clients Balance'!F153/'Clients Balance'!B153 -> 50296.635 | G147: =B147*'Clients Balance'!G153/'Clients Balance'!B153 -> 15088.996
A148: 45660 | B148: ='PROP DAILY PNL'!B148 -> -166355 | C148: ='Clients Balance'!C153/'Clients Balance'!B153*Sheet!B148 -> -83590.661 | D148: =B148*'Clients Balance'!D154/'Clients Balance'!B154 -> -18966.076 | E148: =B148*'Clients Balance'!E154/'Clients Balance'!B154 -> -23495.371 | F148: =B148*'Clients Balance'!F154/'Clients Balance'!B154 -> -31002.222 | G148: =B148*'Clients Balance'!G154/'Clients Balance'!B154 -> -9300.6703
A149: 45663 | B149: ='PROP DAILY PNL'!B149 -> -277266 | C149: ='Clients Balance'!C154/'Clients Balance'!B154*Sheet!B149 -> -139321.62 | D149: =B149*'Clients Balance'!D155/'Clients Balance'!B155 -> -31611.001 | E149: =B149*'Clients Balance'!E155/'Clients Balance'!B155 -> -39160.035 | F149: =B149*'Clients Balance'!F155/'Clients Balance'!B155 -> -51671.799 | G149: =B149*'Clients Balance'!G155/'Clients Balance'!B155 -> -15501.546
A150: 45664 | B150: ='PROP DAILY PNL'!B150 -> 281928 | C150: ='Clients Balance'!C155/'Clients Balance'!B155*Sheet!B150 -> 141664.2 | D150: =B150*'Clients Balance'!D156/'Clients Balance'!B156 -> 32142.514 | E150: =B150*'Clients Balance'!E156/'Clients Balance'!B156 -> 39818.478 | F150: =B150*'Clients Balance'!F156/'Clients Balance'!B156 -> 52540.618 | G150: =B150*'Clients Balance'!G156/'Clients Balance'!B156 -> 15762.192
A151: 45665 | B151: ='PROP DAILY PNL'!B151 -> -110010 | C151: ='Clients Balance'!C156/'Clients Balance'!B156*Sheet!B151 -> -55278.222 | D151: =B151*'Clients Balance'!D157/'Clients Balance'!B157 -> -12542.202 | E151: =B151*'Clients Balance'!E157/'Clients Balance'!B157 -> -15537.41 | F151: =B151*'Clients Balance'!F157/'Clients Balance'!B157 -> -20501.665 | G151: =B151*'Clients Balance'!G157/'Clients Balance'!B157 -> -6150.5019
A152: 45666 | B152: ='PROP DAILY PNL'!B152 -> -15116 | C152: ='Clients Balance'!C157/'Clients Balance'!B157*Sheet!B152 -> -7595.5422 | D152: =B152*'Clients Balance'!D158/'Clients Balance'!B158 -> -1723.3699 | E152: =B152*'Clients Balance'!E158/'Clients Balance'!B158 -> -2134.9285 | F152: =B152*'Clients Balance'!F158/'Clients Balance'!B158 -> -2817.0454 | G152: =B152*'Clients Balance'!G158/'Clients Balance'!B158 -> -845.11396
A153: 45667 | B153: ='PROP DAILY PNL'!B153 -> -39304.5 | C153: ='Clients Balance'!C158/'Clients Balance'!B158*Sheet!B153 -> -19749.867 | D153: =B153*'Clients Balance'!D159/'Clients Balance'!B159 -> -4481.0925 | E153: =B153*'Clients Balance'!E159/'Clients Balance'!B159 -> -5551.2236 | F153: =B153*'Clients Balance'!F159/'Clients Balance'!B159 -> -7324.8585 | G153: =B153*'Clients Balance'!G159/'Clients Balance'!B159 -> -2197.4584
A154: 45670 | B154: ='PROP DAILY PNL'!B154 -> 99661 | C154: ='Clients Balance'!C159/'Clients Balance'!B159*Sheet!B154 -> 50078.019 | D154: =B154*'Clients Balance'!D160/'Clients Balance'!B160 -> 11362.316 | E154: =B154*'Clients Balance'!E160/'Clients Balance'!B160 -> 14075.755 | F154: =B154*'Clients Balance'!F160/'Clients Balance'!B160 -> 18573.006 | G154: =B154*'Clients Balance'!G160/'Clients Balance'!B160 -> 5571.9041
A155: 45671 | B155: ='PROP DAILY PNL'!B155 -> 33927 | C155: ='Clients Balance'!C160/'Clients Balance'!B160*Sheet!B155 -> 17047.761 | D155: =B155*'Clients Balance'!D161/'Clients Balance'!B161 -> 3868.0056 | E155: =B155*'Clients Balance'!E161/'Clients Balance'!B161 -> 4791.7252 | F155: =B155*'Clients Balance'!F161/'Clients Balance'!B161 -> 6322.6978 | G155: =B155*'Clients Balance'!G161/'Clients Balance'!B161 -> 1896.8101
A156: 45672 | B156: ='PROP DAILY PNL'!B156 -> 12703 | C156: ='Clients Balance'!C161/'Clients Balance'!B161*Sheet!B156 -> 6383.0493 | D156: =B156*'Clients Balance'!D162/'Clients Balance'!B162 -> 1448.2646 | E156: =B156*'Clients Balance'!E162/'Clients Balance'!B162 -> 1794.1252 | F156: =B156*'Clients Balance'!F162/'Clients Balance'!B162 -> 2367.3543 | G156: =B156*'Clients Balance'!G162/'Clients Balance'!B162 -> 710.20658
A157: 45673 | B157: ='PROP DAILY PNL'!B157 -> 61362 | C157: ='Clients Balance'!C162/'Clients Balance'!B162*Sheet!B157 -> 30833.399 | D157: =B157*'Clients Balance'!D163/'Clients Balance'!B163 -> 6995.8604 | E157: =B157*'Clients Balance'!E163/'Clients Balance'!B163 -> 8666.5442 | F157: =B157*'Clients Balance'!F163/'Clients Balance'!B163 -> 11435.535 | G157: =B157*'Clients Balance'!G163/'Clients Balance'!B163 -> 3430.6617
A158: 45674 | B158: ='PROP DAILY PNL'!B158 -> -52823 | C158: ='Clients Balance'!C163/'Clients Balance'!B163*Sheet!B158 -> -26542.692 | D158: =B158*'Clients Balance'!D164/'Clients Balance'!B164 -> -6022.332 | E158: =B158*'Clients Balance'!E164/'Clients Balance'!B164 -> -7460.5271 | F158: =B158*'Clients Balance'!F164/'Clients Balance'!B164 -> -9844.1909 | G158: =B158*'Clients Balance'!G164/'Clients Balance'!B164 -> -2953.2584
... A168: 45688 | B168: ='PROP DAILY PNL'!B168 -> 198422 | C168: ='Clients Balance'!C173/'Clients Balance'!B173*Sheet!B168 -> 99703.802 | D168: =B168*'Clients Balance'!D174/'Clients Balance'!B174 -> 22622.024 | E168: =B168*'Clients Balance'!E174/'Clients Balance'!B174 -> 28024.397 | F168: =B168*'Clients Balance'!F174/'Clients Balance'!B174 -> 36978.287 | G168: =B168*'Clients Balance'!G174/'Clients Balance'!B174 -> 11093.49
A169: 45689 | B169: ='PROP DAILY PNL'!B169 -> -51515 | C169: ='Clients Balance'!C175/'Clients Balance'!B175*Sheet!B169 -> -25761.705 | D169: =B169*'Clients Balance'!D175/'Clients Balance'!B175 -> -5906.3953 | E169: =B169*'Clients Balance'!E175/'Clients Balance'!B175 -> -7316.901 | F169: =B169*'Clients Balance'!F175/'Clients Balance'!B175 -> -9638.4594 | G169: =B169*'Clients Balance'!G175/'Clients Balance'!B175 -> -2891.539
A170: 45691 | B170: ='PROP DAILY PNL'!B170 -> -8512.5 | C170: ='Clients Balance'!C176/'Clients Balance'!B176*Sheet!B170 -> -4344.7973 | D170: =B170*'Clients Balance'!D176/'Clients Balance'!B176 -> -955.84274 | E170: =B170*'Clients Balance'!E176/'Clients Balance'!B176 -> -1184.1075 | F170: =B170*'Clients Balance'!F176/'Clients Balance'!B176 -> -1559.8095 | G170: =B170*'Clients Balance'!G176/'Clients Balance'!B176 -> -467.94304 | H170: =B170*'Clients Balance'!H176/'Clients Balance'!B176 -> 0
A171: 45692 | B171: ='PROP DAILY PNL'!B171 -> 58212 | C171: ='Clients Balance'!C177/'Clients Balance'!B177*Sheet!B171 -> 25347.109 | D171: =B171*'Clients Balance'!D177/'Clients Balance'!B177 -> 5576.2901 | E171: =B171*'Clients Balance'!E177/'Clients Balance'!B177 -> 6907.9635 | F171: =B171*'Clients Balance'!F177/'Clients Balance'!B177 -> 9099.7713 | G171: =B171*'Clients Balance'!G177/'Clients Balance'!B177 -> 2729.9325 | H171: =B171*'Clients Balance'!H177/'Clients Balance'!B177 -> 8550.9337
A172: 45693 | B172: ='PROP DAILY PNL'!B172 -> -36744.75 | C172: ='Clients Balance'!C178/'Clients Balance'!B178*Sheet!B172 -> -15999.677 | D172: =B172*'Clients Balance'!D178/'Clients Balance'!B178 -> -3519.8823 | E172: =B172*'Clients Balance'!E178/'Clients Balance'!B178 -> -4360.465 | F172: =B172*'Clients Balance'!F178/'Clients Balance'!B178 -> -5743.9844 | G172: =B172*'Clients Balance'!G178/'Clients Balance'!B178 -> -1723.196 | H172: =B172*'Clients Balance'!H178/'Clients Balance'!B178 -> -5397.5455
A173: 45694 | B173: ='PROP DAILY PNL'!B173 -> 195943 | C173: ='Clients Balance'!C179/'Clients Balance'!B179*Sheet!B173 -> 85318.982 | D173: =B173*'Clients Balance'!D179/'Clients Balance'!B179 -> 18769.927 | E173: =B173*'Clients Balance'!E179/'Clients Balance'!B179 -> 23252.372 | F173: =B173*'Clients Balance'!F179/'Clients Balance'!B179 -> 30630.05 | G173: =B173*'Clients Balance'!G179/'Clients Balance'!B179 -> 9189.0188 | H173: =B173*'Clients Balance'!H179/'Clients Balance'!B179 -> 28782.65
A174: 45695 | B174: ='PROP DAILY PNL'!B174 -> 84562 | C174: ='Clients Balance'!C180/'Clients Balance'!B180*Sheet!B174 -> 36820.625 | D174: =B174*'Clients Balance'!D180/'Clients Balance'!B180 -> 8100.4303 | E174: =B174*'Clients Balance'!E180/'Clients Balance'!B180 -> 10034.893 | F174: =B174*'Clients Balance'!F180/'Clients Balance'!B180 -> 13218.836 | G174: =B174*'Clients Balance'!G180/'Clients Balance'!B180 -> 3965.6523 | H174: =B174*'Clients Balance'!H180/'Clients Balance'!B180 -> 12421.564
A175: 45698 | B175: ='PROP DAILY PNL'!B175 -> -9315.75 | C175: ='Clients Balance'!C181/'Clients Balance'!B181*Sheet!B175 -> -4056.3343 | D175: =B175*'Clients Balance'!D181/'Clients Balance'!B181 -> -892.38172 | E175: =B175*'Clients Balance'!E181/'Clients Balance'!B181 -> -1105.4913 | F175: =B175*'Clients Balance'!F181/'Clients Balance'!B181 -> -1456.2495 | G175: =B175*'Clients Balance'!G181/'Clients Balance'!B181 -> -436.87502 | H175: =B175*'Clients Balance'!H181/'Clients Balance'!B181 -> -1368.4182
A176: 45699 | B176: ='PROP DAILY PNL'!B176 -> 502222 | C176: ='Clients Balance'!C182/'Clients Balance'!B182*Sheet!B176 -> 218681.3 | D176: =B176*'Clients Balance'!D182/'Clients Balance'!B182 -> 48109.249 | E176: =B176*'Clients Balance'!E182/'Clients Balance'!B182 -> 59598.214 | F176: =B176*'Clients Balance'!F182/'Clients Balance'!B182 -> 78507.959 | G176: =B176*'Clients Balance'!G182/'Clients Balance'!B182 -> 23552.397 | H176: =B176*'Clients Balance'!H182/'Clients Balance'!B182 -> 73772.882
A177: 45700 | B177: ='PROP DAILY PNL'!B177 -> -209165 | C177: ='Clients Balance'!C183/'Clients Balance'!B183*Sheet!B177 -> -91076.205 | D177: =B177*'Clients Balance'!D183/'Clients Balance'!B183 -> -20036.5 | E177: =B177*'Clients Balance'!E183/'Clients Balance'!B183 -> -24821.414 | F177: =B177*'Clients Balance'!F183/'Clients Balance'!B183 -> -32696.929 | G177: =B177*'Clients Balance'!G183/'Clients Balance'!B183 -> -9809.0828 | H177: =B177*'Clients Balance'!H183/'Clients Balance'!B183 -> -30724.869
A178: 45701 | B178: ='PROP DAILY PNL'!B178 -> -56146.5 | C178: ='Clients Balance'!C184/'Clients Balance'!B184*Sheet!B178 -> -24447.733 | D178: =B178*'Clients Balance'!D184/'Clients Balance'!B184 -> -5378.4301 | E178: =B178*'Clients Balance'!E184/'Clients Balance'!B184 -> -6662.8525 | F178: =B178*'Clients Balance'!F184/'Clients Balance'!B184 -> -8776.8898 | G178: =B178*'Clients Balance'!G184/'Clients Balance'!B184 -> -2633.068 | H178: =B178*'Clients Balance'!H184/'Clients Balance'!B184 -> -8247.5263
A179: 45702 | B179: ='PROP DAILY PNL'!B179 -> -135048 | C179: ='Clients Balance'!C185/'Clients Balance'!B185*Sheet!B179 -> -58803.621 | D179: =B179*'Clients Balance'!D185/'Clients Balance'!B185 -> -12936.625 | E179: =B179*'Clients Balance'!E185/'Clients Balance'!B185 -> -16026.02 | F179: =B179*'Clients Balance'!F185/'Clients Balance'!B185 -> -21110.869 | G179: =B179*'Clients Balance'!G185/'Clients Balance'!B185 -> -6333.2633 | H179: =B179*'Clients Balance'!H185/'Clients Balance'!B185 -> -19837.602
A180: 45705 | B180: ='PROP DAILY PNL'!B180 -> -113030.25 | C180: ='Clients Balance'!C186/'Clients Balance'!B186*Sheet!B180 -> -49216.486 | D180: =B180*'Clients Balance'!D186/'Clients Balance'!B186 -> -10827.483 | E180: =B180*'Clients Balance'!E186/'Clients Balance'!B186 -> -13413.194 | F180: =B180*'Clients Balance'!F186/'Clients Balance'!B186 -> -17669.027 | G180: =B180*'Clients Balance'!G186/'Clients Balance'!B186 -> -5300.7104 | H180: =B180*'Clients Balance'!H186/'Clients Balance'!B186 -> -16603.349
A181: 45706 | B181: ='PROP DAILY PNL'!B181 -> -143378 | C181: ='Clients Balance'!C187/'Clients Balance'!B187*Sheet!B181 -> -62430.732 | D181: =B181*'Clients Balance'!D187/'Clients Balance'!B187 -> -13734.579 | E181: =B181*'Clients Balance'!E187/'Clients Balance'!B187 -> -17014.533 | F181: =B181*'Clients Balance'!F187/'Clients Balance'!B187 -> -22413.025 | G181: =B181*'Clients Balance'!G187/'Clients Balance'!B187 -> -6723.9102 | H181: =B181*'Clients Balance'!H187/'Clients Balance'!B187 -> -21061.221
... A188: 45716 | B188: ='PROP DAILY PNL'!B188 -> -7984 | C188: ='Clients Balance'!C194/'Clients Balance'!B194*Sheet!B188 -> -3476.4536 | D188: =B188*'Clients Balance'!D194/'Clients Balance'!B194 -> -764.80967 | E188: =B188*'Clients Balance'!E194/'Clients Balance'!B194 -> -947.45379 | F188: =B188*'Clients Balance'!F194/'Clients Balance'!B194 -> -1248.0687 | G188: =B188*'Clients Balance'!G194/'Clients Balance'!B194 -> -374.42075 | H188: =B188*'Clients Balance'!H194/'Clients Balance'!B194 -> -1172.7935
A189: 45719 | B189: ='PROP DAILY PNL'!B189 -> 42439 | C189: ='Clients Balance'!C195/'Clients Balance'!B195*Sheet!B189 -> 19790.38 | D189: =B189*'Clients Balance'!D194/'Clients Balance'!B194 -> 4065.3504 | E189: =B189*'Clients Balance'!E194/'Clients Balance'!B194 -> 5036.1963 | F189: =B189*'Clients Balance'!F194/'Clients Balance'!B194 -> 6634.1166 | G189: =B189*'Clients Balance'!G195/'Clients Balance'!B195 -> 1951.7756 | H189: =B189*'Clients Balance'!H195/'Clients Balance'!B195 -> 6119.2023
A190: 45720 | B190: ='PROP DAILY PNL'!B190 -> 120528 | C190: ='Clients Balance'!C196/'Clients Balance'!B196*Sheet!B190 -> 56199.834 | D190: =B190*'Clients Balance'!D195/'Clients Balance'!B195 -> 11364.618 | E190: =B190*'Clients Balance'!E195/'Clients Balance'!B195 -> 11559.321 | F190: =B190*'Clients Balance'!F195/'Clients Balance'!B195 -> 18476.991 | G190: =B190*'Clients Balance'!G196/'Clients Balance'!B196 -> 5542.5649 | H190: =B190*'Clients Balance'!H196/'Clients Balance'!B196 -> 17377.037
A191: 45721 | B191: ='PROP DAILY PNL'!B191 -> 84599 | C191: ='Clients Balance'!C197/'Clients Balance'!B197*Sheet!B191 -> 38391.41 | D191: =B191*'Clients Balance'!D197/'Clients Balance'!B197 -> 7763.126 | E191: =B191*'Clients Balance'!E197/'Clients Balance'!B197 -> 7902.2464 | F191: =B191*'Clients Balance'!F197/'Clients Balance'!B197 -> 12621.726 | G191: =B191*'Clients Balance'!G197/'Clients Balance'!B197 -> 6049.8341 | H191: =B191*'Clients Balance'!H197/'Clients Balance'!B197 -> 11870.657
A192: 45722 | B192: ='PROP DAILY PNL'!B192 -> -146003 | C192: ='Clients Balance'!C198/'Clients Balance'!B198*Sheet!B192 -> -66256.824 | D192: =B192*'Clients Balance'!D198/'Clients Balance'!B198 -> -13397.791 | E192: =B192*'Clients Balance'!E198/'Clients Balance'!B198 -> -13637.888 | F192: =B192*'Clients Balance'!F198/'Clients Balance'!B198 -> -21782.88 | G192: =B192*'Clients Balance'!G198/'Clients Balance'!B198 -> -10440.95 | H192: =B192*'Clients Balance'!H198/'Clients Balance'!B198 -> -20486.667
A193: 45723 | B193: ='PROP DAILY PNL'!B193 -> -173520 | C193: ='Clients Balance'!C199/'Clients Balance'!B199*Sheet!B193 -> -78744.164 | D193: =B193*'Clients Balance'!D199/'Clients Balance'!B199 -> -15922.855 | E193: =B193*'Clients Balance'!E199/'Clients Balance'!B199 -> -16208.203 | F193: =B193*'Clients Balance'!F199/'Clients Balance'!B199 -> -25888.272 | G193: =B193*'Clients Balance'!G199/'Clients Balance'!B199 -> -12408.743 | H193: =B193*'Clients Balance'!H199/'Clients Balance'!B199 -> -24347.763
...

Sheet Performance Dashboard
D29: ALL FIGURES CALCULATED ON DEPOSIT CAPITAL (NOT LEVERAGED CAPITAL)
A31: No of Trades | B31: =COUNT('PROP DAILY PNL'!B:B) -> 391
A32: No of Win Trades | B32: =COUNTIF('PROP DAILY PNL'!B:B,">=0") -> 219
A33: No of loss trades | B33: =B31-B32 -> 172
A34: % win | B34: =B32/B31*100 -> 56.01023
A35: % loss | B35: =100-B34 -> 43.98977
A36: Max loss % | B36: =MIN('PROP DAILY PNL'!C:C) -> -0.060079713
A37: Max Win % | B37: =MAX('PROP DAILY PNL'!C:C) -> 0.078738328
A38: MAX DD | B38: =MIN('PROP DAILY PNL'!H:H) -> -0.09748
A39: Average Winner | B39: =AVERAGEIF('PROP DAILY PNL'!E:E,">=0") -> 0.75590966
A40: Average looser | B40: =abs(AVERAGEIF('PROP DAILY PNL'!E:E,"<=0")) -> 0.53291075
A41: Risk:Reward | B41: =B39/B40 -> 1.4184545
A42: Expectancy | B42: =(B41*B34-B35)/100 -> 0.35458193

Sheet PERCENTAGE SHARING
A1: DATE | B1: TOTAL PERCENTAGE | C1: ABHISHEK S | D1: RADHIKA A | E1: KARAN | F1: PAVAN | G1: RASOOL | H1: SIVA | I1: RAVI | J1: MAHESH | K1: JAGADISH | L1: Bharghav | M1: Kaushik | N1: MAHESH A | O1: Aayushi A | P1: Dishant | Q1: BHARATH | R1: NARESH
A2: ='PROP DAILY PNL'!A208 -> 45748 | B2: =SUM(C2:R2) -> 1 | C2: ='Clients Balance'!C214/'Clients Balance'!$B214 -> 0.36644066 | D2: ='Clients Balance'!D214/'Clients Balance'!$B214 -> 0.058509526 | E2: ='Clients Balance'!E214/'Clients Balance'!$B214 -> 0.056985403 | F2: ='Clients Balance'!F214/'Clients Balance'!$B214 -> 0 | G2: ='Clients Balance'!G214/'Clients Balance'!$B214 -> 0.049795792 | H2: ='Clients Balance'!H214/'Clients Balance'!$B214 -> 0.23847485 | I2: ='Clients Balance'!I214/'Clients Balance'!$B214 -> 0.04447237 | J2: ='Clients Balance'!J214/'Clients Balance'!$B214 -> 0.08894474 | ... R2: ='Clients Balance'!R214/'Clients Balance'!$B214 -> 0
A3: ='PROP DAILY PNL'!A209 -> 45749 | B3: =SUM(C3:R3) -> 1 | C3: ='Clients Balance'!C215/'Clients Balance'!B215 -> 0.35040001 | D3: ='Clients Balance'!D215/'Clients Balance'!$B215 -> 0.055948318 | E3: ='Clients Balance'!E215/'Clients Balance'!$B215 -> 0.054490912 | F3: ='Clients Balance'!F215/'Clients Balance'!$B215 -> 0 | G3: ='Clients Balance'!G215/'Clients Balance'!$B215 -> 0.047616021 | H3: ='Clients Balance'!H215/'Clients Balance'!$B215 -> 0.2280358 | I3: ='Clients Balance'!I215/'Clients Balance'!$B215 -> 0.042525627 | J3: ='Clients Balance'!J215/'Clients Balance'!$B215 -> 0.085051254 | K3: ='Clients Balance'!K215/'Clients Balance'!$B215 -> 0.042525627 | ... R3: ='Clients Balance'!R215/'Clients Balance'!$B215 -> 0
A4: ='PROP DAILY PNL'!A210 -> 45750 | B4: =SUM(C4:R4) -> 1 | C4: ='Clients Balance'!C216/'Clients Balance'!B216 -> 0.35040001 | D4: ='Clients Balance'!D216/'Clients Balance'!$B216 -> 0.055948318 | E4: ='Clients Balance'!E216/'Clients Balance'!$B216 -> 0.054490912 | F4: ='Clients Balance'!F216/'Clients Balance'!$B216 -> 0 | G4: ='Clients Balance'!G216/'Clients Balance'!$B216 -> 0.047616021 | H4: ='Clients Balance'!H216/'Clients Balance'!$B216 -> 0.2280358 | I4: ='Clients Balance'!I216/'Clients Balance'!$B216 -> 0.042525627 | J4: ='Clients Balance'!J216/'Clients Balance'!$B216 -> 0.085051254 | K4: ='Clients Balance'!K216/'Clients Balance'!$B216 -> 0.042525627 | ... R4: ='Clients Balance'!R216/'Clients Balance'!$B216 -> 0
A5: ='PROP DAILY PNL'!A211 -> 45751 | B5: =SUM(C5:R5) -> 1 | C5: ='Clients Balance'!C217/'Clients Balance'!B217 -> 0.35040001 | D5: ='Clients Balance'!D217/'Clients Balance'!$B217 -> 0.055948318 | E5: ='Clients Balance'!E217/'Clients Balance'!$B217 -> 0.054490912 | F5: ='Clients Balance'!F217/'Clients Balance'!$B217 -> 0 | G5: ='Clients Balance'!G217/'Clients Balance'!$B217 -> 0.047616021 | H5: ='Clients Balance'!H217/'Clients Balance'!$B217 -> 0.2280358 | I5: ='Clients Balance'!I217/'Clients Balance'!$B217 -> 0.042525627 | J5: ='Clients Balance'!J217/'Clients Balance'!$B217 -> 0.085051254 | K5: ='Clients Balance'!K217/'Clients Balance'!$B217 -> 0.042525627 | ... R5: ='Clients Balance'!R217/'Clients Balance'!$B217 -> 0
A6: ='PROP DAILY PNL'!A212 -> 45754 | B6: =SUM(C6:R6) -> 1 | C6: ='Clients Balance'!C218/'Clients Balance'!B218 -> 0.35040001 | D6: ='Clients Balance'!D218/'Clients Balance'!$B218 -> 0.055948318 | E6: ='Clients Balance'!E218/'Clients Balance'!$B218 -> 0.054490912 | F6: ='Clients Balance'!F218/'Clients Balance'!$B218 -> 0 | G6: ='Clients Balance'!G218/'Clients Balance'!$B218 -> 0.047616021 | H6: ='Clients Balance'!H218/'Clients Balance'!$B218 -> 0.2280358 | I6: ='Clients Balance'!I218/'Clients Balance'!$B218 -> 0.042525627 | J6: ='Clients Balance'!J218/'Clients Balance'!$B218 -> 0.085051254 | K6: ='Clients Balance'!K218/'Clients Balance'!$B218 -> 0.042525627 | ... R6: ='Clients Balance'!R218/'Clients Balance'!$B218 -> 0
A7: ='PROP DAILY PNL'!A213 -> 45755 | B7: =SUM(C7:R7) -> 1 | C7: ='Clients Balance'!C219/'Clients Balance'!B219 -> 0.34164351 | D7: ='Clients Balance'!D219/'Clients Balance'!$B219 -> 0.054550169 | E7: ='Clients Balance'!E219/'Clients Balance'!$B219 -> 0.053129184 | F7: ='Clients Balance'!F219/'Clients Balance'!$B219 -> 0 | G7: ='Clients Balance'!G219/'Clients Balance'!$B219 -> 0.046426096 | H7: ='Clients Balance'!H219/'Clients Balance'!$B219 -> 0.22233719 | I7: ='Clients Balance'!I219/'Clients Balance'!$B219 -> 0.041462912 | J7: ='Clients Balance'!J219/'Clients Balance'!$B219 -> 0.082925823 | K7: ='Clients Balance'!K219/'Clients Balance'!$B219 -> 0.041462912 | ... R7: ='Clients Balance'!R219/'Clients Balance'!$B219 -> 0
A8: ='PROP DAILY PNL'!A214 -> 45756 | B8: =SUM(C8:R8) -> 1 | C8: ='Clients Balance'!C220/'Clients Balance'!B220 -> 0.34164351 | D8: ='Clients Balance'!D220/'Clients Balance'!$B220 -> 0.054550169 | E8: ='Clients Balance'!E220/'Clients Balance'!$B220 -> 0.053129184 | F8: ='Clients Balance'!F220/'Clients Balance'!$B220 -> 0 | G8: ='Clients Balance'!G220/'Clients Balance'!$B220 -> 0.046426096 | H8: ='Clients Balance'!H220/'Clients Balance'!$B220 -> 0.22233719 | I8: ='Clients Balance'!I220/'Clients Balance'!$B220 -> 0.041462912 | J8: ='Clients Balance'!J220/'Clients Balance'!$B220 -> 0.082925823 | K8: ='Clients Balance'!K220/'Clients Balance'!$B220 -> 0.041462912 | ... R8: ='Clients Balance'!R220/'Clients Balance'!$B220 -> 0
A9: ='PROP DAILY PNL'!A215 -> 45758 | B9: =SUM(C9:R9) -> 1 | C9: ='Clients Balance'!C221/'Clients Balance'!B221 -> 0.34164351 | D9: ='Clients Balance'!D221/'Clients Balance'!$B221 -> 0.054550169 | E9: ='Clients Balance'!E221/'Clients Balance'!$B221 -> 0.053129184 | F9: ='Clients Balance'!F221/'Clients Balance'!$B221 -> 0 | G9: ='Clients Balance'!G221/'Clients Balance'!$B221 -> 0.046426096 | H9: ='Clients Balance'!H221/'Clients Balance'!$B221 -> 0.22233719 | I9: ='Clients Balance'!I221/'Clients Balance'!$B221 -> 0.041462912 | J9: ='Clients Balance'!J221/'Clients Balance'!$B221 -> 0.082925823 | K9: ='Clients Balance'!K221/'Clients Balance'!$B221 -> 0.041462912 | ... R9: ='Clients Balance'!R221/'Clients Balance'!$B221 -> 0
A10: ='PROP DAILY PNL'!A216 -> 45762 | B10: =SUM(C10:R10) -> 1 | C10: ='Clients Balance'!C222/'Clients Balance'!B222 -> 0.34164351 | D10: ='Clients Balance'!D222/'Clients Balance'!$B222 -> 0.054550169 | E10: ='Clients Balance'!E222/'Clients Balance'!$B222 -> 0.053129184 | F10: ='Clients Balance'!F222/'Clients Balance'!$B222 -> 0 | G10: ='Clients Balance'!G222/'Clients Balance'!$B222 -> 0.046426096 | H10: ='Clients Balance'!H222/'Clients Balance'!$B222 -> 0.22233719 | I10: ='Clients Balance'!I222/'Clients Balance'!$B222 -> 0.041462912 | J10: ='Clients Balance'!J222/'Clients Balance'!$B222 -> 0.082925823 | K10: ='Clients Balance'!K222/'Clients Balance'!$B222 -> 0.041462912 | ... R10: ='Clients Balance'!R222/'Clients Balance'!$B222 -> 0
A11: ='PROP DAILY PNL'!A217 -> 45763 | B11: =SUM(C11:R11) -> 1 | C11: ='Clients Balance'!C223/'Clients Balance'!B223 -> 0.34164351 | D11: ='Clients Balance'!D223/'Clients Balance'!$B223 -> 0.054550169 | E11: ='Clients Balance'!E223/'Clients Balance'!$B223 -> 0.053129184 | F11: ='Clients Balance'!F223/'Clients Balance'!$B223 -> 0 | G11: ='Clients Balance'!G223/'Clients Balance'!$B223 -> 0.046426096 | H11: ='Clients Balance'!H223/'Clients Balance'!$B223 -> 0.22233719 | I11: ='Clients Balance'!I223/'Clients Balance'!$B223 -> 0.041462912 | J11: ='Clients Balance'!J223/'Clients Balance'!$B223 -> 0.082925823 | K11: ='Clients Balance'!K223/'Clients Balance'!$B223 -> 0.041462912 | ... R11: ='Clients Balance'!R223/'Clients Balance'!$B223 -> 0
A12: ='PROP DAILY PNL'!A218 -> 45764 | B12: =SUM(C12:R12) -> 1 | C12: ='Clients Balance'!C224/'Clients Balance'!B224 -> 0.34164351 | D12: ='Clients Balance'!D224/'Clients Balance'!$B224 -> 0.054550169 | E12: ='Clients Balance'!E224/'Clients Balance'!$B224 -> 0.053129184 | F12: ='Clients Balance'!F224/'Clients Balance'!$B224 -> 0 | G12: ='Clients Balance'!G224/'Clients Balance'!$B224 -> 0.046426096 | H12: ='Clients Balance'!H224/'Clients Balance'!$B224 -> 0.22233719 | I12: ='Clients Balance'!I224/'Clients Balance'!$B224 -> 0.041462912 | J12: ='Clients Balance'!J224/'Clients Balance'!$B224 -> 0.082925823 | K12: ='Clients Balance'!K224/'Clients Balance'!$B224 -> 0.041462912 | ... R12: ='Clients Balance'!R224/'Clients Balance'!$B224 -> 0
A13: ='PROP DAILY PNL'!A219 -> 45768 | B13: =SUM(C13:R13) -> 1 | C13: ='Clients Balance'!C225/'Clients Balance'!B225 -> 0.34164351 | D13: ='Clients Balance'!D225/'Clients Balance'!$B225 -> 0.054550169 | E13: ='Clients Balance'!E225/'Clients Balance'!$B225 -> 0.053129184 | F13: ='Clients Balance'!F225/'Clients Balance'!$B225 -> 0 | G13: ='Clients Balance'!G225/'Clients Balance'!$B225 -> 0.046426096 | H13: ='Clients Balance'!H225/'Clients Balance'!$B225 -> 0.22233719 | I13: ='Clients Balance'!I225/'Clients Balance'!$B225 -> 0.041462912 | J13: ='Clients Balance'!J225/'Clients Balance'!$B225 -> 0.082925823 | K13: ='Clients Balance'!K225/'Clients Balance'!$B225 -> 0.041462912 | ... R13: ='Clients Balance'!R225/'Clients Balance'!$B225 -> 0
A14: ='PROP DAILY PNL'!A220 -> 45769 | B14: =SUM(C14:R14) -> 1 | C14: ='Clients Balance'!C226/'Clients Balance'!B226 -> 0.34164351 | D14: ='Clients Balance'!D226/'Clients Balance'!$B226 -> 0.054550169 | E14: ='Clients Balance'!E226/'Clients Balance'!$B226 -> 0.053129184 | F14: ='Clients Balance'!F226/'Clients Balance'!$B226 -> 0 | G14: ='Clients Balance'!G226/'Clients Balance'!$B226 -> 0.046426096 | H14: ='Clients Balance'!H226/'Clients Balance'!$B226 -> 0.22233719 | I14: ='Clients Balance'!I226/'Clients Balance'!$B226 -> 0.041462912 | J14: ='Clients Balance'!J226/'Clients Balance'!$B226 -> 0.082925823 | K14: ='Clients Balance'!K226/'Clients Balance'!$B226 -> 0.041462912 | ... R14: ='Clients Balance'!R226/'Clients Balance'!$B226 -> 0
... A773: ='PROP DAILY PNL'!A979 | B773: =SUM(C773:R773) -> 1 | C773: ='Clients Balance'!C985/'Clients Balance'!B985 -> 0.58865747 | D773: ='Clients Balance'!D985/'Clients Balance'!$B985 -> 0.14414709 | E773: ='Clients Balance'!E985/'Clients Balance'!$B985 -> 0.1089947 | F773: ='Clients Balance'!F985/'Clients Balance'!$B985 -> 0 | G773: ='Clients Balance'!G985/'Clients Balance'!$B985 -> 0 | H773: ='Clients Balance'!H985/'Clients Balance'!$B985 -> 0 | I773: ='Clients Balance'!I985/'Clients Balance'!$B985 -> 0 | J773: ='Clients Balance'!J985/'Clients Balance'!$B985 -> 0 | K773: ='Clients Balance'!K985/'Clients Balance'!$B985 -> 0 | ... R773: ='Clients Balance'!R985/'Clients Balance'!$B985 -> 0
A774: ='PROP DAILY PNL'!A980 | B774: =SUM(C774:R774) -> #DIV/0! | C774: ='Clients Balance'!C987/'Clients Balance'!B987 -> #DIV/0! | D774: ='Clients Balance'!D986/'Clients Balance'!$B986 -> 0.14414709 | E774: ='Clients Balance'!E987/'Clients Balance'!$B987 -> #DIV/0! | F774: ='Clients Balance'!F987/'Clients Balance'!$B987 -> #DIV/0! | G774: ='Clients Balance'!G987/'Clients Balance'!$B987 -> #DIV/0! | H774: ='Clients Balance'!H987/'Clients Balance'!$B987 -> #DIV/0! | I774: ='Clients Balance'!I987/'Clients Balance'!$B987 -> #DIV/0! | J774: ='Clients Balance'!J987/'Clients Balance'!$B987 -> #DIV/0! | K774: ='Clients Balance'!K987/'Clients Balance'!$B987 -> #DIV/0! | L774: ='Clients Balance'!L986/'Clients Balance'!$B986 -> 0 | M774: ='Clients Balance'!M986/'Clients Balance'!$B986 -> 0 | N774: ='Clients Balance'!N986/'Clients Balance'!$B986 -> 0 | O774: ='Clients Balance'!O986/'Clients Balance'!$B986 -> 0.04923005 | P774: ='Clients Balance'!P986/'Clients Balance'!$B986 -> 0.029599322 | Q774: ='Clients Balance'!Q986/'Clients Balance'!$B986 -> 0.079371378 | R774: ='Clients Balance'!R986/'Clients Balance'!$B986 -> 0
A775: ='PROP DAILY PNL'!A981 | B775: =SUM(C775:R775) -> #DIV/0! | C775: ='Clients Balance'!C988/'Clients Balance'!B988 -> #DIV/0! | D775: =#REF!/#REF! -> #REF! | E775: ='Clients Balance'!E988/'Clients Balance'!$B988 -> #DIV/0! | F775: ='Clients Balance'!F988/'Clients Balance'!$B988 -> #DIV/0! | G775: ='Clients Balance'!G988/'Clients Balance'!$B988 -> #DIV/0! | H775: ='Clients Balance'!H988/'Clients Balance'!$B988 -> #DIV/0! | I775: ='Clients Balance'!I988/'Clients Balance'!$B988 -> #DIV/0! | J775: ='Clients Balance'!J988/'Clients Balance'!$B988 -> #DIV/0! | K775: ='Clients Balance'!K988/'Clients Balance'!$B988 -> #DIV/0! | L775: =#REF!/#REF! -> #REF! | M775: =#REF!/#REF! -> #REF! | N775: =#REF!/#REF! -> #REF! | O775: =#REF!/#REF! -> #REF! | P775: =#REF!/#REF! -> #REF! | Q775: =#REF!/#REF! -> #REF! | R775: =#REF!/#REF! -> #REF!
A776: ='PROP DAILY PNL'!A982 | B776: =SUM(C776:R776) -> #DIV/0! | C776: ='Clients Balance'!C989/'Clients Balance'!B989 -> #DIV/0! | D776: =#REF!/#REF! -> #REF! | E776: ='Clients Balance'!E989/'Clients Balance'!$B989 -> #DIV/0! | F776: ='Clients Balance'!F989/'Clients Balance'!$B989 -> #DIV/0! | G776: ='Clients Balance'!G989/'Clients Balance'!$B989 -> #DIV/0! | H776: ='Clients Balance'!H989/'Clients Balance'!$B989 -> #DIV/0! | I776: ='Clients Balance'!I989/'Clients Balance'!$B989 -> #DIV/0! | J776: ='Clients Balance'!J989/'Clients Balance'!$B989 -> #DIV/0! | K776: ='Clients Balance'!K989/'Clients Balance'!$B989 -> #DIV/0! | L776: =#REF!/#REF! -> #REF! | M776: =#REF!/#REF! -> #REF! | N776: =#REF!/#REF! -> #REF! | O776: =#REF!/#REF! -> #REF! | P776: =#REF!/#REF! -> #REF! | Q776: =#REF!/#REF! -> #REF! | R776: =#REF!/#REF! -> #REF!
